Workbook

Sheet Dashboard

Sheet Readmefirst
B5: DANH MỤC BÁO CÁO
B7: STT | C7: Nội dung báo cáo | D7: Link
B8: 1 | C8: Danh sách các site | D8: Site list'
B9: =B8+1 -> 2 | C9: Báo cáo kết quả kinh doanh cộng ngang các site tính từ đầu năm đến tháng hiện tại, so sánh cùng kỳ năm trước | D9: Annual_PL conso' | E9: WIP
B10: =B9+1 -> 3 | C10: Báo cáo kết quả kinh doanh hợp nhất từng tháng năm hiện tại, so sánh với budget và so sánh với năm trước | D10: Monthly_PL conso'
B11: =B10+1 -> 4 | C11: Báo cáo Tình hình tài chính (Tài sản, Nợ, Vốn chủ sở hữu) từng tháng năm hiện tại | D11: Conso BS'
B12: =B11+1 -> 5 | C12: Báo cáo kết quả kinh doanh site Hải Dương | D12: HaiDuong
B13: =B12+1 -> 6 | C13: Báo cáo kết quả kinh doanh site Cà Mau | D13: CaMau
B14: =B13+1 -> 7 | C14: Báo cáo kết quả kinh doanh site Thanh Hóa | D14: ThanhHoa
B15: =B14+1 -> 8 | C15: Báo cáo kết quả kinh doanh site Thaí Nguyên | D15: ThaiNguyen
B16: =B15+1 -> 9 | C16: Báo cáo kết quả kinh doanh site Thaí Bình | D16: ThaiBinh
B17: =B16+1 -> 10 | C17: Báo cáo kết quả kinh doanh site Yết Kiêu | D17: YetKieu
B18: =B17+1 -> 11 | C18: Báo cáo kết quả kinh doanh site Nha Trang | D18: NhaTrang
B19: =B18+1 -> 12 | C19: Báo cáo kết quả kinh doanh site Thạch Thất | D19: ThachThat
B20: =B19+1 -> 13 | C20: Báo cáo kết quả kinh doanh site Sóc Sơn | D20: SocSon-1'
B21: =B20+1 -> 14 | C21: Báo cáo kết quả kinh doanh các site liên kết | D21: Site liên kết'
B22: =B21+1 -> 15 | C22: Báo cáo kết quả kinh doanh HM Saigon | D22: HM-2'
B23: =B22+1 -> 16 | C23: Báo cáo kết quả kinh doanh site Hà Tĩnh
B24: =B23+1 -> 17 | C24: Báo cáo kết quả kinh doanh HO | D24: HO
B25: =B24+1 -> 18 | C25: Điểm hòa vốn từng site | D25: Điểm hòa vốn'
B26: =B25+1 -> 19 | C26: Dự báo dòng tiền năm 2026 | D26: CF forecast'
B27: =B26+1 -> 20 | C27: Dự báo kết quả kinh doanh toàn hệ thống
B28: =B27+1 -> 21 | C28: Dự báo kết quả kinh doanh site Hải Dương
B29: =B28+1 -> 22 | C29: Dự báo kết quả kinh doanh site Cà Mau
B30: =B29+1 -> 23 | C30: Dự báo kết quả kinh doanh site Thanh Hóa
B31: =B30+1 -> 24 | C31: Dự báo kết quả kinh doanh site Thaí Nguyên | D31: ThaiNguyen2
B32: =B31+1 -> 25 | C32: Dự báo kết quả kinh doanh site Thaí Bình | D32: ThaiBinh2
B33: =B32+1 -> 26 | C33: Dự báo kết quả kinh doanh site Yết Kiêu | D33: YetKieu-2'
B34: =B33+1 -> 27 | C34: Dự báo kết quả kinh doanh site Nha Trang | D34: NhaTrang-2'
B35: =B34+1 -> 28 | C35: Dự báo kết quả kinh doanh site Thạch Thất | D35: ThachThat
B36: =B35+1 -> 29 | C36: Dự báo kết quả kinh doanh site Sóc Sơn | D36: SocSon
B37: =B36+1 -> 30 | C37: Dự báo kết quả kinh doanh các site liên kết | D37: Site liên kết'
B38: =B37+1 -> 31 | C38: Dự báo kết quả kinh doanh HM Saigon | D38: HM-3'
B39: =B38+1 -> 32 | C39: Dự báo kết quả kinh doanh site Hà Tĩnh | D39: Hà Tĩnh'
B40: =B39+1 -> 33 | C40: Dự báo kết quả kinh doanh HO | D40: HO-2'
B41: =B40+1 -> 34 | C41: Dự báo chị phí bảo trì sửa chữa thay thế máy móc | D41: Maintenance
B42: =B41+1 -> 35 | C42: Bảng tính lãi vay site Cà Mau | D42: VTB_CaMau
... B47: =B46+1 -> 40 | C47: Bảng tính lãi vay site Nha Trang | D47: VTB_Nha trang.'

Sheet Annual_PL conso
B6: BÁO CÁO KẾT QUẢ HOẠT ĐỘNG KINH DOANH HỢP NHẤT
B8: Năm tài chính 2025 | Q8: --------Tổng--------- | S8: ------vs last year-------
B9: VND triệu | F9: Hải Dương | G9: Cà Mau | H9: Thanh Hóa | I9: T.Nguyên | J9: Thái Bình | K9: Yết Kiêu | L9: Nha Trang | M9: T.Thất | N9: Sóc Sơn | O9: HO | P9: Site LK | Q9: VND triệu | R9: %DT | S9: VND triệu | T9: % | W9: Năm 2025 | X9: Trung Bình/tháng
B11: Doanh thu | V11: Hải Dương | W11: 11146.22 | X11: =W11/12 -> 928.85167
C12: Chẩn đoán hình ảnh | V12: Cà Mau | W12: 5416.52 | X12: =W12/12 -> 451.37667
D13: MRI | F13: =HaiDuong!R42 -> 8990.3 | G13: =CaMau!R12 -> 5194.42 | H13: =ThanhHoa!R12 -> 3505.3648 | I13: =ThaiNguyen!R12 -> 3278.95 | J13: =ThaiBinh!R12 -> 1940.29 | K13: =YetKieu!R12 -> 5743.65 | L13: =NhaTrang!R12 -> 5106.311 | M13: 0 | N13: ='SocSon-1'!R22 -> 210.99 | Q13: =SUM(F13:P13) -> 33970.276 | R13: =IFERROR(Q13/Q$20,"") -> 0.74773973 | V13: Thanh Hóa | W13: 10912.091 | X13: =W13/12 -> 909.34087
D14: CT | F14: =HaiDuong!R44 -> 1643.3 | G14: =CaMau!R14 -> 0 | H14: =ThanhHoa!R14 -> 7406.7257 | I14: =ThaiNguyen!R14 -> 35 | J14: =ThaiBinh!R14 -> 0 | K14: =YetKieu!R14 -> 277.346 | L14: =NhaTrang!R13 -> 353.465 | M14: =ThachThat!R12 -> 693.3 | N14: 0 | Q14: =SUM(F14:P14) -> 10409.137 | R14: =IFERROR(Q14/Q$20,"") -> 0.22912163 | V14: T.Nguyên | W14: 3322.05 | X14: =W14/12 -> 276.8375
D15: Mammo X-Quang | F15: =HaiDuong!R43 -> 124.3 | G15: =CaMau!R13 -> 222.1 | H15: =ThanhHoa!R13 -> 0 | I15: =ThaiNguyen!R13 -> 0 | J15: =ThaiBinh!R13 -> 0 | K15: =YetKieu!R13 -> 79.0656 | L15: =NhaTrang!R14 -> 70.12 | M15: =0 -> 0 | N15: =0 -> 0 | Q15: =SUM(F15:P15) -> 495.5856 | R15: =IFERROR(Q15/Q$20,"") -> 0.010908626 | V15: Thái Bình | W15: 1946.44 | X15: =W15/12 -> 162.20333
D16: X-Quang | F16: =HaiDuong!R45 -> 278.5 | G16: =CaMau!R15 -> 0 | H16: =ThanhHoa!R15 -> 0 | I16: =ThaiNguyen!R15 -> 8.1 | J16: =ThaiBinh!R15 -> 6.15 | K16: =YetKieu!R15 -> 67.657 | L16: =0 -> 0 | M16: 0 | N16: 0 | Q16: =SUM(F16:P16) -> 360.407 | R16: =IFERROR(Q16/Q$20,"") -> 0.0079331305 | V16: Yết Kiêu | W16: 6197.5786 | X16: =W16/12 -> 516.46488
D17: Siêu âm | F17: =HaiDuong!R46 -> 114.9 | G17: =CaMau!R16 -> 0 | H17: =ThanhHoa!R16 -> 0 | I17: =ThaiNguyen!R16 -> 0 | J17: =ThaiBinh!R16 -> 0 | K17: =YetKieu!R16 -> 16.64 | L17: 0 | M17: 0 | N17: 0 | Q17: =SUM(F17:P17) -> 131.54 | R17: =IFERROR(Q17/Q$20,"") -> 0.0028954043 | V17: Nha Trang | W17: 5532.746 | X17: =W17/12 -> 461.06217
C18: Tổng- Chẩn đoán hình ảnh | F18: =SUBTOTAL(9,F13:F17) -> 11151.3 | G18: =SUBTOTAL(9,G13:G17) -> 5416.52 | H18: =SUBTOTAL(9,H13:H17) -> 10912.091 | I18: =SUBTOTAL(9,I13:I17) -> 3322.05 | J18: =SUBTOTAL(9,J13:J17) -> 1946.44 | K18: =SUBTOTAL(9,K13:K17) -> 6184.3586 | L18: =SUBTOTAL(9,L13:L17) -> 5529.896 | M18: =SUBTOTAL(9,M13:M17) -> 693.3 | N18: =SUBTOTAL(9,N13:N17) -> 210.99 | Q18: =SUM(F18:N18) -> 45366.945 | R18: =IFERROR(Q18/Q$20,"") -> 0.99859852 | V18: T.Thất | W18: 693.3 | X18: =W18/12 -> 57.775
C19: Tổng- Khác | F19: =HaiDuong!R48 -> 18.92 | G19: =CaMau!R18 -> 0 | H19: =ThanhHoa!R18 -> 0 | I19: =ThaiNguyen!R18 -> 0 | J19: =0 -> 0 | K19: =YetKieu!R17 -> 41.9 | L19: =NhaTrang!R15 -> 2.85 | M19: =0 -> 0 | N19: =0 -> 0 | Q19: =SUM(F19:N19) -> 63.67 | R19: =IFERROR(Q19/Q$20,"") -> 0.0014014778 | V19: Sóc Sơn | W19: 210.99 | X19: =W19/12 -> 17.5825
B20: Tổng- Doanh thu | F20: =SUM(F18:F19) -> 11170.22 | G20: =SUM(G18:G19) -> 5416.52 | H20: =SUM(H18:H19) -> 10912.091 | I20: =SUM(I18:I19) -> 3322.05 | J20: =SUM(J18:J19) -> 1946.44 | K20: =SUM(K18:K19) -> 6226.2586 | L20: =SUM(L18:L19) -> 5532.746 | M20: =SUM(M18:M19) -> 693.3 | N20: =SUM(N18:N19) -> 210.99 | Q20: =SUM(F20:N20) -> 45430.615 | R20: =IFERROR(Q20/Q$20,"") -> 1 | W20: =SUM(W11:W19) -> 45377.935 | X20: =SUM(X11:X19) -> 3781.4946
B21: Giảm trừ doanh thu | F21: =HaiDuong!R50 -> 72.435 | G21: =CaMau!R20 -> 0.9 | H21: =ThanhHoa!R20 -> 8.32 | I21: =ThaiNguyen!R20 -> 675.48 | J21: =ThaiBinh!R18 -> 0 | K21: =YetKieu!R19 -> 0 | L21: =NhaTrang!R21 -> 0 | M21: =ThachThat!R14 -> 0 | N21: ='SocSon-1'!R23 -> 0 | Q21: =SUM(F21:P21) -> 757.135 | R21: =IFERROR(Q21/Q$20,"") -> 0.016665744
B22: Biến phí | R22: =IFERROR(Q22/Q$20,"") -> 0
C23: Vật tư tiêu hao | F23: =HaiDuong!R57 -> 479.98592 | G23: =CaMau!R27 -> 25.7917 | H23: =ThanhHoa!R26 -> 316.33424 | I23: =ThaiNguyen!R27 -> 111.4161 | J23: =ThaiBinh!R21 -> 109.8095 | K23: =YetKieu!R28 -> 608.01031 | L23: =NhaTrang!R24 -> 206.72404 | M23: =ThachThat!R17 -> 34.056 | N23: ='SocSon-1'!R26 -> 11.4673 | Q23: =SUM(F23:P23) -> 1903.5951 | R23: =IFERROR(Q23/Q$20,"") -> 0.041901152
C24: Chi phí đọc kết quả online | F24: =HaiDuong!R58 -> 742.834 | G24: =CaMau!R28 -> 350.505 | H24: =ThanhHoa!R27 -> 929.12 | I24: =ThaiNguyen!R28 -> 207.191 | J24: =ThaiBinh!R22 -> 198.598 | K24: =YetKieu!R29 -> 378.943 | L24: =NhaTrang!R27 -> 373.505 | M24: =ThachThat!R20 -> 94.53 | N24: ='SocSon-1'!R27 -> 20.01 | Q24: =SUM(F24:P24) -> 3295.236 | R24: =IFERROR(Q24/Q$20,"") -> 0.072533378
C25: Tiền thuốc | F25: =HaiDuong!R59 -> 322.55584 | G25: =CaMau!R29 -> 0 | H25: =ThanhHoa!R28 -> 623.05 | I25: =ThaiNguyen!R29 -> 33.748 | J25: =ThaiBinh!R23 -> 2.808616 | K25: =YetKieu!R30 -> 0 | L25: 0 | M25: 0 | N25: ='SocSon-1'!R28 -> 0 | Q25: =SUM(F25:P25) -> 982.16246 | R25: =IFERROR(Q25/Q$20,"") -> 0.021618956
C26: Tư vấn chuyên môn | F26: =HaiDuong!R60 -> 1339.1 | G26: =CaMau!R30 -> 787.15 | H26: =ThanhHoa!R29 -> 1112.695 | I26: =ThaiNguyen!R30 -> 466.4 | J26: =ThaiBinh!R24 -> 306.5 | K26: =YetKieu!R31 -> 898.654 | L26: =NhaTrang!R26 -> 911.875 | M26: =ThachThat!R19 -> 103 | N26: ='SocSon-1'!R29 -> 18.23 | Q26: =SUM(F26:P26) -> 5943.604 | R26: =IFERROR(Q26/Q$20,"") -> 0.13082816
C27: Thưởng hiệu quả kinh doanh | F27: =HaiDuong!R61 -> 278.42 | G27: =CaMau!R31 -> 0 | H27: =ThanhHoa!R30 -> 331.4264 | I27: =ThaiNguyen!R31 -> 73.93 | J27: =ThaiBinh!R25 -> 12.04 | K27: =YetKieu!R32 -> 179.88638 | L27: =NhaTrang!R25 -> 90.2997 | M27: =ThachThat!R18 -> 0 | N27: ='SocSon-1'!R30 -> 0 | Q27: =SUM(F27:P27) -> 966.00248 | R27: =IFERROR(Q27/Q$20,"") -> 0.021263249
C28: Truyền thông marketing | F28: =HaiDuong!R62 -> 78.673914 | G28: =CaMau!R32 -> 0 | H28: =ThanhHoa!R31 -> 92.671215 | I28: =ThaiNguyen!R32 -> 97.429016 | J28: =ThaiBinh!R26 -> 63.716182 | K28: =YetKieu!R33 -> 0 | L28: 0 | M28: 0 | N28: ='SocSon-1'!R31 -> 0 | Q28: =SUM(F28:P28) -> 332.49033 | R28: =IFERROR(Q28/Q$20,"") -> 0.0073186402
C29: Tổng- Biến phí | F29: =SUBTOTAL(9,F23:F28) -> 3241.5697 | G29: =SUBTOTAL(9,G23:G28) -> 1163.4467 | H29: =SUBTOTAL(9,H23:H28) -> 3405.2969 | I29: =SUBTOTAL(9,I23:I28) -> 990.11412 | J29: =SUBTOTAL(9,J23:J28) -> 693.4723 | K29: =SUBTOTAL(9,K23:K28) -> 2065.4937 | L29: =SUBTOTAL(9,L23:L28) -> 1582.4037 | M29: =SUBTOTAL(9,M23:M28) -> 231.586 | N29: =SUBTOTAL(9,N23:N28) -> 49.7073 | Q29: =SUM(Q23:Q28) -> 13423.09 | R29: =IFERROR(Q29/Q$20,"") -> 0.29546354
B30: Lãi trên biến phí | F30: =F20-F29-F21 -> 7856.2153 | G30: =G20-G29-G21 -> 4252.1733 | H30: =H20-H29-H21 -> 7498.4736 | I30: =I20-I29-I21 -> 1656.4559 | J30: =J20-J29-J21 -> 1252.9677 | K30: =K20-K29-K21 -> 4160.7649 | L30: =L20-L29-L21 -> 3950.3423 | M30: =M20-M29-M21 -> 461.714 | N30: =N20-N29-N21 -> 161.2827 | Q30: =Q20-Q29-Q21 -> 31250.39 | R30: =IFERROR(Q30/Q$20,"") -> 0.68787072
B31: Định phí | R31: =IFERROR(Q31/Q$20,"") -> 0
C32: Chi phí nhân sự | F32: =HaiDuong!R66-HO!R13 -> 1977.5054 | G32: =CaMau!R36 -> 762.02839 | H32: =ThanhHoa!R35 -> 1752.3483 | I32: =ThaiNguyen!R36 -> 1182.95 | J32: =ThaiBinh!R28 -> 829.78285 | K32: =YetKieu!R35 -> 1248.3208 | L32: =NhaTrang!R30 -> 973.1919 | M32: =ThachThat!R23 -> 176.54 | N32: ='SocSon-1'!R33 -> 106.049 | Q32: =SUM(F32:P32) -> 9008.7166 | R32: =IFERROR(Q32/Q$20,"") -> 0.19829616
C33: Chi phí thuê địa điểm | F33: =HaiDuong!R67 -> 362.6895 | G33: =CaMau!R37 -> 240 | H33: =ThanhHoa!R36 -> 738.41666 | I33: =ThaiNguyen!R37 -> 621.21911 | J33: =ThaiBinh!R29 -> 264 | K33: =SUM(YetKieu!R36:R38) -> 3102.6144 | L33: =SUM(NhaTrang!R31:R32) -> 1985.9138 | M33: =SUM(ThachThat!R24:R26) -> 74.638962 | N33: ='SocSon-1'!R34 -> 22 | Q33: =SUM(F33:P33) -> 7411.4925 | R33: =IFERROR(Q33/Q$20,"") -> 0.16313872
C34: Chi phí bảo dưỡng sửa chữa | F34: =HaiDuong!R68 -> 0 | G34: =CaMau!R38 -> 0 | H34: =ThanhHoa!R37 -> 0 | I34: =ThaiNguyen!R38 -> 0 | J34: =ThaiBinh!R30 -> 0 | K34: 0 | L34: 0 | M34: 0 | N34: ='SocSon-1'!R35 -> 0 | Q34: =SUM(F34:P34) -> 0
C35: Chi phí vận hành thường xuyên | F35: =HaiDuong!R69 -> 1079.6883 | G35: =CaMau!R39 -> 470.75663 | H35: =ThanhHoa!R38 -> 684.86413 | I35: =ThaiNguyen!R39 -> 772.58742 | J35: =ThaiBinh!R31 -> 539.18652 | K35: 0 | L35: 0 | M35: 0 | N35: ='SocSon-1'!R36 -> 20.219222 | Q35: =SUM(F35:P35) -> 3567.3022 | R35: =IFERROR(Q35/Q$20,"") -> 0.078521988
C36: Chi phí khác | F36: =HaiDuong!R70 -> 29.193604 | G36: =CaMau!R40 -> 184.40128 | H36: =ThanhHoa!R39 -> 318.65076 | I36: =ThaiNguyen!R40 -> 94.643845 | J36: =ThaiBinh!R32 -> 22.070896 | K36: =YetKieu!R39 -> 118.38815 | L36: =NhaTrang!R33 -> 60.796074 | M36: 0 | N36: ='SocSon-1'!R37 -> 76.23 | Q36: =SUM(F36:P36) -> 904.3746 | R36: =IFERROR(Q36/Q$20,"") -> 0.019906721
C37: Tổng- Định phí | F37: =SUBTOTAL(9,F32:F36) -> 3449.0767 | G37: =SUBTOTAL(9,G32:G36) -> 1657.1863 | H37: =SUBTOTAL(9,H32:H36) -> 3494.2799 | I37: =SUBTOTAL(9,I32:I36) -> 2671.4004 | J37: =SUBTOTAL(9,J32:J36) -> 1655.0403 | K37: =SUBTOTAL(9,K32:K36) -> 4469.3234 | L37: =SUBTOTAL(9,L32:L36) -> 3019.9018 | M37: =SUBTOTAL(9,M32:M36) -> 251.17896 | N37: =SUBTOTAL(9,N32:N36) -> 224.49822 | Q37: =SUBTOTAL(9,Q32:Q36) -> 20891.886 | R37: =IFERROR(Q37/Q$20,"") -> 0.45986359
B38: EBITDA tại chi nhánh | F38: =F30-F37 -> 4407.1386 | G38: =G30-G37 -> 2594.987 | H38: =H30-H37 -> 4004.1938 | I38: =I30-I37 -> -1014.9445 | J38: =J30-J37 -> -402.07256 | K38: =K30-K37 -> -308.55851 | L38: =L30-L37 -> 930.4405 | M38: =M30-M37 -> 210.53504 | N38: =N30-N37 -> -63.215522 | Q38: =Q30-Q37 -> 10358.504 | R38: =IFERROR(Q38/Q$20,"") -> 0.22800712
B39: Lợi nhuận từ site liên kết | P39: ='Site liên kết'!R20 -> 3442.2475 | Q39: =SUM(F39:P39) -> 3442.2475 | R39: =IFERROR(Q39/Q$20,"") -> 0.075769334
B40: Chi phí tại HO
C41: Chi phí nhân sự | O41: =SUM(HO!R18,HO!R26) -> 2889.3228 | Q41: =SUM(F41:P41) -> 2889.3228 | R41: =IFERROR(Q41/Q$20,"") -> 0.063598585
C42: Chi phí thuê văn mặt bằng, điện nước, viễn thông | O42: =SUM(HO!R19:R20,HO!R28) -> 741.07605 | Q42: =SUM(F42:P42) -> 741.07605 | R42: =IFERROR(Q42/Q$20,"") -> 0.016312261
C43: Chi phí văn phòng phẩm dụng cụ | O43: =SUM(HO!R21,HO!R29) -> 85.300047 | Q43: =SUM(F43:P43) -> 85.300047 | R43: =IFERROR(Q43/Q$20,"") -> 0.0018775895
C44: Chi phí đối ngoại tiếp khách | O44: =SUM(HO!R23,HO!R27) -> 103.96385 | Q44: =SUM(F44:P44) -> 103.96385 | R44: =IFERROR(Q44/Q$20,"") -> 0.0022884095
C45: Chi phí dịch vụ chuyên nghiệp | O45: =SUM(HO!R22) -> 122.21769 | Q45: =SUM(F45:P45) -> 122.21769 | R45: =IFERROR(Q45/Q$20,"") -> 0.0026902054
C46: Chi phí khác | O46: =SUM(HO!R24,HO!R30) -> 549.49356 | Q46: =SUM(F46:P46) -> 549.49356 | R46: =IFERROR(Q46/Q$20,"") -> 0.012095226
C47: Tổng - Chi phí HO | F47: =SUM(F41:F46) -> 0 | G47: =SUM(G41:G46) -> 0 | H47: =SUM(H41:H46) -> 0 | I47: =SUM(I41:I46) -> 0 | J47: =SUM(J41:J46) -> 0 | K47: =SUM(K41:K46) -> 0 | L47: =SUM(L41:L46) -> 0 | M47: =SUM(M41:M46) -> 0 | ... Q47: =SUM(Q41:Q46) -> 4491.374 | R47: =IFERROR(Q47/Q$20,"") -> 0.098862277
B48: EBITDA toàn công ty | F48: =SUM(F38:F39)-F47 -> 4407.1386 | G48: =SUM(G38:G39)-G47 -> 2594.987 | H48: =SUM(H38:H39)-H47 -> 4004.1938 | I48: =SUM(I38:I39)-I47 -> -1014.9445 | J48: =SUM(J38:J39)-J47 -> -402.07256 | K48: =SUM(K38:K39)-K47 -> -308.55851 | L48: =SUM(L38:L39)-L47 -> 930.4405 | M48: =SUM(M38:M39)-M47 -> 210.53504 | ... P48: =SUM(P38:P39)-P47 -> 3442.2475 | Q48: =SUM(Q42:Q47) -> 6093.4252 | R48: =IFERROR(Q48/Q$20,"") -> 0.13412597
C50: Chi phí lãi vay net/(Thu nhập tài chính) | F50: =-HaiDuong!R83 -> -134.82947 | G50: =-CaMau!R53 -> 772.86225 | H50: =ThanhHoa!R52 -> 921.72669 | I50: =ThaiNguyen!R52 -> 742.62767 | J50: =ThaiBinh!R37 -> 532.35914 | K50: =YetKieu!R46 -> 1174.616 | L50: =NhaTrang!R36 -> 1136.9911 | M50: =ThachThat!R29 -> 0 | N50: ='SocSon-1'!R44 -> 0 | O50: =-HO!R14 -> -5.376997 | Q50: =SUM(F50:P50) -> 5140.9764 | R50: =IFERROR(Q50/Q$20,"") -> 0.11316106
C51: Chi phí khấu hao máy móc Chẩn đoán hình ảnh | F51: =HaiDuong!R75 -> 2838 | G51: =CaMau!R45 -> 1920 | H51: =ThanhHoa!R44 -> 2133.2383 | I51: =ThaiNguyen!R44 -> 1851.7306 | J51: =ThaiBinh!R35 -> 1003.3333 | K51: =YetKieu!R41 -> 2397.7795 | L51: =NhaTrang!R37 -> 2379.1369 | M51: =ThachThat!R30 -> 133.33333 | N51: ='SocSon-1'!R40 -> 172.5 | Q51: =SUM(F51:P51) -> 14829.052 | R51: =IFERROR(Q51/Q$20,"") -> 0.32641099
C52: Chi phí khấu hao khác | F52: =HaiDuong!R81 -> 292.9854 | G52: =CaMau!R51 -> 296.35082 | H52: =ThanhHoa!R50 -> 360.17906 | I52: =ThaiNguyen!R50 -> 302.64452 | J52: =ThaiBinh!R36 -> 144.91631 | K52: =YetKieu!R45 -> 733.54406 | L52: =NhaTrang!R41 -> 1264.377 | M52: =ThachThat!R31 -> 0 | N52: =SUM('SocSon-1'!R41:R42) -> 702.5473 | Q52: =SUM(F52:P52) -> 4097.5444 | R52: =IFERROR(Q52/Q$20,"") -> 0.090193461
C53: (Lợi nhuận khác)/Lỗ khác | F53: =-HaiDuong!R82 -> -290.88225 | G53: =CaMau!R52 -> 0 | H53: =ThanhHoa!R51 -> 0 | I53: =ThaiNguyen!R51 -> 0 | J53: =ThaiBinh!R38 -> 0 | K53: =YetKieu!R47 -> 0 | L53: =NhaTrang!R42 -> 0 | M53: =ThachThat!R32 -> 0 | N53: ='SocSon-1'!R45 -> 0 | O53: =-HO!R39 -> -287.46979 | Q53: =SUM(F53:P53) -> -578.35204 | R53: =IFERROR(Q53/Q$20,"") -> -0.012730447
B54: Lợi nhuận trước thuế | F54: =F48-SUM(F50,F51,F52,F53) -> 1701.8649 | G54: =G48-SUM(G50,G51,G52,G53) -> -394.22607 | H54: =H48-SUM(H50,H51,H52,H53) -> 589.04977 | I54: =I48-SUM(I50,I51,I52,I53) -> -3911.9473 | J54: =J48-SUM(J50,J51,J52,J53) -> -2082.6813 | K54: =K48-SUM(K50,K51,K52,K53) -> -4614.4981 | L54: =L48-SUM(L50,L51,L52,L53) -> -3850.0645 | M54: =M48-SUM(M50,M51,M52,M53) -> 77.201706 | ... Q54: =Q48-SUM(Q50,Q51,Q52,Q53) -> -17395.796 | R54: =IFERROR(Q54/Q$20,"") -> -0.38290909
C55: Chi phí thuế TNDN (tạm tính) | F55: =HaiDuong!R85 -> 323.5855 | G55: =CaMau!R55 -> 45.429225 | H55: =ThanhHoa!R54 -> 421.95833 | I55: =ThaiNguyen!R54 -> 0 | J55: =ThaiBinh!R40 -> 0 | K55: =YetKieu!R49 -> 0 | L55: =NhaTrang!R44 -> 0 | M55: =ThachThat!R34 -> 21.055108 | N55: ='SocSon-1'!R47 -> 0 | Q55: =SUM(F55:P55) -> 812.02816 | R55: =IFERROR(Q55/Q$20,"") -> 0.01787403
B56: Lợi nhuận/(Lỗ) sau thuế | F56: =F54-F55 -> 1378.2794 | G56: =G54-G55 -> -439.6553 | H56: =H54-H55 -> 167.09143 | I56: =I54-I55 -> -3911.9473 | J56: =J54-J55 -> -2082.6813 | K56: =K54-K55 -> -4614.4981 | L56: =L54-L55 -> -3850.0645 | M56: =M54-M55 -> 56.146598 | ... Q56: =Q54-Q55 -> -18207.824 | R56: =IFERROR(Q56/Q$20,"") -> -0.40078312
C57: Cổ đông địa phương | R57: =IFERROR(Q57/Q$20,"") -> 0
B58: Lợi nhuận về công ty mẹ | F58: =SUM(F56:F57) -> 1378.2794 | G58: =SUM(G56:G57) -> -439.6553 | H58: =SUM(H56:H57) -> 167.09143 | I58: =SUM(I56:I57) -> -3911.9473 | J58: =SUM(J56:J57) -> -2082.6813 | K58: =SUM(K56:K57) -> -4614.4981 | L58: =SUM(L56:L57) -> -3850.0645 | M58: =SUM(M56:M57) -> 56.146598 | ... Q58: =SUM(Q56:Q57) -> -18207.824 | R58: =IFERROR(Q58/Q$20,"") -> -0.40078312
F60: =F56-HaiDuong!R86 -> 338.60762 | G60: =G56-CaMau!R56 -> 5.1159077e-13 | H60: =H56-ThanhHoa!R55 -> 4.5474735e-13 | I60: =I56-ThaiNguyen!R55 -> 0 | J60: =J56-ThaiBinh!R41 -> 0 | K60: =K56-YetKieu!R50 -> 0 | L60: =L56-NhaTrang!R45 -> 0 | M60: =M56-ThachThat!R35 -> 6.3948846e-14 | N60: =N56-'SocSon-1'!R48 -> 0 | R60: =IFERROR(Q60/Q$20,"") -> 0
B62: CÁC CHỈ TIÊU HIỆU QUẢ HOẠT ĐỘNG
C63: Số ca
E64: MRI | F64: =HaiDuong!R95 -> 4791 | G64: =CaMau!R94 -> 2786 | H64: =ThanhHoa!R94 -> 1695 | I64: =ThaiNguyen!R62 -> 1745 | J64: =ThaiBinh!R50 -> 1689 | K64: =YetKieu!R57 -> 2839 | L64: =NhaTrang!R52 -> 2684 | M64: 0 | N64: ='SocSon-1'!R14 -> 155 | Q64: =SUM(F64:P64) -> 18384
E65: CT | F65: =HaiDuong!R97 -> 1381 | H65: =ThanhHoa!R96 -> 8979 | I65: =ThaiNguyen!R63 -> 40 | J65: 0 | K65: =YetKieu!R59 -> 298 | L65: =NhaTrang!R53 -> 436 | M65: =ThachThat!R37 -> 816 | N65: 0 | Q65: =SUM(F65:P65) -> 11950
E66: Mammo X-Quang | F66: =HaiDuong!R96 -> 237 | G66: =CaMau!R95 -> 463 | H66: 0 | I66: 0 | J66: 0 | K66: =YetKieu!R58 -> 184 | L66: =NhaTrang!R54 -> 206 | M66: 0 | N66: 0 | Q66: =SUM(F66:P66) -> 1090
E67: X-Quang | F67: =HaiDuong!R98 -> 1878 | H67: 0 | I67: =ThaiNguyen!R64 -> 54 | J67: =ThaiBinh!R51 -> 37 | K67: =YetKieu!R60 -> 423 | L67: 0 | M67: 0 | N67: 0 | Q67: =SUM(F67:P67) -> 2392
E68: Siêu âm | F68: =HaiDuong!R99 -> 718 | H68: 0 | I68: 0 | J68: 0 | K68: =YetKieu!R61 -> 87 | L68: 0 | M68: 0 | N68: 0 | Q68: =SUM(F68:P68) -> 805
C70: Số máy
E71: MRI | F71: 1 | G71: 1 | H71: 1 | I71: 1 | J71: 1 | K71: 1 | L71: 1 | M71: 0 | N71: 1
E72: CT | F72: 1 | G72: 0 | H72: 1 | I72: 1 | J72: 0 | K72: 1 | L72: 1 | M72: 1 | N72: 0
E73: Mammo X-Quang | F73: 1 | G73: 1 | H73: 0 | I73: 0 | J73: 0 | K73: 1 | L73: 1 | M73: 0 | N73: 0
E74: X-Quang | F74: 1 | G74: 0 | H74: 0 | I74: 1 | J74: 1 | K74: 1 | L74: 0 | M74: 0 | N74: 0
E75: Siêu âm | F75: 1 | G75: 0 | H75: 0 | I75: 0 | J75: 0 | K75: 1 | L75: 0 | M75: 0 | N75: 0
C76: Maximum capacity (Công suất tối đa ca/tháng)
E77: MRI | F77: =(30*9*60/20)*12 -> 9720 | G77: =(30*9*60/20)*12 -> 9720 | H77: =(30*9*60/20)*12 -> 9720 | I77: =(30*9*60/20)*12 -> 9720 | J77: =(30*9*60/20)*12 -> 9720 | K77: =(30*9*60/20)*12 -> 9720 | L77: =(30*9*60/20)*12 -> 9720 | M77: 0 | N77: =(30*9*60/20)*12 -> 9720
E78: CT | F78: =(30*9*60/10)*12 -> 19440 | G78: 0 | H78: =(30*9*60/10)*12 -> 19440 | I78: =(30*9*60/10)*12 -> 19440 | J78: 0 | K78: =(30*9*60/10)*12 -> 19440 | L78: =(30*9*60/10)*12 -> 19440 | M78: =(30*9*60/10)*12 -> 19440 | N78: 0
E79: Mammo X-Quang | F79: =(30*9*60/15)*12 -> 12960 | G79: =(30*9*60/15)*12 -> 12960 | H79: 0 | I79: 0 | J79: 0 | K79: =(30*9*60/15)*12 -> 12960 | L79: =(30*9*60/15)*12 -> 12960 | M79: 0 | N79: 0
E80: X-Quang | F80: =(30*9*60/8)*12 -> 24300 | G80: 0 | H80: 0 | I80: =(30*9*60/8)*12 -> 24300 | J80: =(30*9*60/8)*12 -> 24300 | K80: =(30*9*60/8)*12 -> 24300 | L80: 0 | M80: 0 | N80: 0
E81: Siêu âm | F81: =(30*9*60/10)*12 -> 19440 | G81: 0 | H81: 0 | I81: 0 | J81: 0 | K81: =(30*9*60/10)*12 -> 19440 | L81: 0 | M81: 0 | N81: 0
C82: Utilization rate (Công suất sử dụng)
E83: MRI | F83: =IFERROR(F64/F77,"") -> 0.49290123 | G83: =IFERROR(G64/G77,"") -> 0.28662551 | H83: =IFERROR(H64/H77,"") -> 0.17438272 | I83: =IFERROR(I64/I77,"") -> 0.17952675 | J83: =IFERROR(J64/J77,"") -> 0.17376543 | K83: =IFERROR(K64/K77,"") -> 0.29207819 | L83: =IFERROR(L64/L77,"") -> 0.27613169 | M83: =IFERROR(M64/M77,"") | N83: =IFERROR(N64/N77,"") -> 0.015946502
E84: CT | F84: =IFERROR(F65/F78,"") -> 0.071039095 | G84: =IFERROR(G65/G78,"") | H84: =IFERROR(H65/H78,"") -> 0.46188272 | I84: =IFERROR(I65/I78,"") -> 0.0020576132 | J84: =IFERROR(J65/J78,"") | K84: =IFERROR(K65/K78,"") -> 0.015329218 | L84: =IFERROR(L65/L78,"") -> 0.022427984 | M84: =IFERROR(M65/M78,"") -> 0.041975309 | N84: =IFERROR(N65/N78,"")
E85: Mammo X-Quang | F85: =IFERROR(F66/F79,"") -> 0.018287037 | G85: =IFERROR(G66/G79,"") -> 0.035725309 | H85: =IFERROR(H66/H79,"") | I85: =IFERROR(I66/I79,"") | J85: =IFERROR(J66/J79,"") | K85: =IFERROR(K66/K79,"") -> 0.014197531 | L85: =IFERROR(L66/L79,"") -> 0.015895062 | M85: =IFERROR(M66/M79,"") | N85: =IFERROR(N66/N79,"")
E86: X-Quang | F86: =IFERROR(F67/F80,"") -> 0.077283951 | G86: =IFERROR(G67/G80,"") | H86: =IFERROR(H67/H80,"") | I86: =IFERROR(I67/I80,"") -> 0.0022222222 | J86: =IFERROR(J67/J80,"") -> 0.0015226337 | K86: =IFERROR(K67/K80,"") -> 0.017407407 | L86: =IFERROR(L67/L80,"") | M86: =IFERROR(M67/M80,"") | N86: =IFERROR(N67/N80,"")
E87: Siêu âm | F87: =IFERROR(F68/F81,"") -> 0.036934156 | G87: =IFERROR(G68/G81,"") | H87: =IFERROR(H68/H81,"") | I87: =IFERROR(I68/I81,"") | J87: =IFERROR(J68/J81,"") | K87: =IFERROR(K68/K81,"") -> 0.0044753086 | L87: =IFERROR(L68/L81,"") | M87: =IFERROR(M68/M81,"") | N87: =IFERROR(N68/N81,"")
C88: Giá trung bình
E89: MRI | F89: =IFERROR(F13*10^6/F64,"") -> 1876497.6 | G89: =IFERROR(G13*10^6/G64,"") -> 1864472.4 | H89: =IFERROR(H13*10^6/H64,"") -> 2068061.8 | I89: =IFERROR(I13*10^6/I64,"") -> 1879054.4 | J89: =IFERROR(J13*10^6/J64,"") -> 1148780.3 | K89: =IFERROR(K13*10^6/K64,"") -> 2023124.3 | L89: =IFERROR(L13*10^6/L64,"") -> 1902500.4 | M89: =IFERROR(M13*10^6/M64,"") | N89: =IFERROR(N13*10^6/N64,"") -> 1361225.8
E90: CT | F90: =IFERROR(F14*10^6/F65,"") -> 1189934.8 | G90: =IFERROR(G14*10^6/G65,"") | H90: =IFERROR(H14*10^6/H65,"") -> 824894.28 | I90: =IFERROR(I14*10^6/I65,"") -> 875000 | J90: =IFERROR(J14*10^6/J65,"") | K90: =IFERROR(K14*10^6/K65,"") -> 930691.28 | L90: =IFERROR(L14*10^6/L65,"") -> 810699.54 | M90: =IFERROR(M14*10^6/M65,"") -> 849632.35 | N90: =IFERROR(N14*10^6/N65,"")
E91: Mammo X-Quang | F91: =IFERROR(F15*10^6/F66,"") -> 524472.57 | G91: =IFERROR(G15*10^6/G66,"") -> 479697.62 | H91: =IFERROR(H15*10^6/H66,"") | I91: =IFERROR(I15*10^6/I66,"") | J91: =IFERROR(J15*10^6/J66,"") | K91: =IFERROR(K15*10^6/K66,"") -> 429704.35 | L91: =IFERROR(L15*10^6/L66,"") -> 340388.35 | M91: =IFERROR(M15*10^6/M66,"") | N91: =IFERROR(N15*10^6/N66,"")
E92: X-Quang | F92: =IFERROR(F15*10^6/F67,"") -> 66187.433 | G92: =IFERROR(G15*10^6/G67,"") | H92: =IFERROR(H15*10^6/H67,"") | I92: =IFERROR(I15*10^6/I67,"") -> 0 | J92: =IFERROR(J15*10^6/J67,"") -> 0 | K92: =IFERROR(K15*10^6/K67,"") -> 186916.31 | L92: =IFERROR(L15*10^6/L67,"") | M92: =IFERROR(M15*10^6/M67,"") | N92: =IFERROR(N15*10^6/N67,"")
E93: Siêu âm | F93: =IFERROR(F17*10^6/F68,"") -> 160027.86 | G93: =IFERROR(G17*10^6/G68,"") | H93: =IFERROR(H17*10^6/H68,"") | I93: =IFERROR(I17*10^6/I68,"") | J93: =IFERROR(J17*10^6/J68,"") | K93: =IFERROR(K17*10^6/K68,"") -> 191264.37 | L93: =IFERROR(L17*10^6/L68,"") | M93: =IFERROR(M17*10^6/M68,"") | N93: =IFERROR(N17*10^6/N68,"")

Sheet Monthly_PL conso
B6: BÁO CÁO KẾT QUẢ HOẠT ĐỘNG KINH DOANH HỢP NHẤT
F7: A | G7: A | H7: A | I7: A | J7: A | K7: A | L7: A | M7: A | N7: A | O7: A | P7: A | Q7: A
B8: Năm tài chính 2025 | F8: Tháng | R8: -------------------------Tổng-------------------------- | U8: ------%Doanh thu------- | X8: -----------vs-------------
B9: VND triệu | F9: 1 | G9: 2 | H9: 3 | I9: 4 | J9: 5 | K9: 6 | L9: 7 | M9: 8 | N9: 9 | O9: 10 | P9: 11 | Q9: 12 | R9: Year to date | S9: Year to go | T9: LATEST EST | U9: YTD | V9: YTG | W9: LE | X9: Last month | Y9: Last year
B11: Doanh thu
C12: Chẩn đoán hình ảnh
D13: MRI | F13: =SUBTOTAL(9,F14:F22) -> 1252.37 | G13: =SUBTOTAL(9,G14:G22) -> 2129.88 | H13: =SUBTOTAL(9,H14:H22) -> 2521.672 | I13: =SUBTOTAL(9,I14:I22) -> 2779.2616 | J13: =SUBTOTAL(9,J14:J22) -> 2952.0801 | K13: =SUBTOTAL(9,K14:K22) -> 3027.2768 | L13: =SUBTOTAL(9,L14:L22) -> 3317.85 | M13: =SUBTOTAL(9,M14:M22) -> 3450.45 | ... Q13: =SUBTOTAL(9,Q14:Q22) -> 3173.676 | R13: =SUMIFS($F13:$Q13,$F$7:$Q$7,"A") -> 33970.276 | S13: =SUMIFS($F13:$Q13,$F$7:$Q$7,"B") -> 0 | T13: =SUM(R13:S13) -> 33970.276 | U13: =IFERROR(R13/R$45,"") -> 0.74773973 | V13: =IFERROR(S13/S$45,"") | W13: =IFERROR(T13/T$45,"") -> 0.74773973
E14: Hải Dương | F14: =HaiDuong!F42 -> 480.4 | G14: =HaiDuong!G42 -> 766.6 | H14: =HaiDuong!H42 -> 864 | I14: =HaiDuong!I42 -> 1002.4 | J14: =HaiDuong!J42 -> 860.4 | K14: =HaiDuong!K42 -> 801.6 | L14: =HaiDuong!L42 -> 845.2 | M14: =HaiDuong!M42 -> 676.4 | ... Q14: =HaiDuong!Q42 -> 700.4 | R14: =SUMIFS($F14:$Q14,$F$7:$Q$7,"A") -> 8990.3 | S14: =SUMIFS($F14:$Q14,$F$7:$Q$7,"B") -> 0 | T14: =SUM(R14:S14) -> 8990.3 | U14: =IFERROR(R14/R$45,"") -> 0.19789078 | V14: =IFERROR(S14/S$45,"") | W14: =IFERROR(T14/T$45,"") -> 0.19789078
E15: Cà Mau | F15: =CaMau!F12 -> 185.58 | G15: =CaMau!G12 -> 339.3 | H15: =CaMau!H12 -> 407.7 | I15: =CaMau!I12 -> 500.4 | J15: =CaMau!J12 -> 477 | K15: =CaMau!K12 -> 592.83 | L15: =CaMau!L12 -> 457.65 | M15: =CaMau!M12 -> 463.5 | ... Q15: =CaMau!Q12 -> 353.65 | R15: =SUMIFS($F15:$Q15,$F$7:$Q$7,"A") -> 5194.42 | S15: =SUMIFS($F15:$Q15,$F$7:$Q$7,"B") -> 0 | T15: =SUM(R15:S15) -> 5194.42 | U15: =IFERROR(R15/R$45,"") -> 0.11433743 | V15: =IFERROR(S15/S$45,"") | W15: =IFERROR(T15/T$45,"") -> 0.11433743
E16: Thanh Hóa | F16: =ThanhHoa!F12 -> 177.8 | G16: =ThanhHoa!G12 -> 333.2 | H16: =ThanhHoa!H12 -> 304.672 | I16: =ThanhHoa!I12 -> 403.2716 | J16: =ThanhHoa!J12 -> 537.3301 | K16: =ThanhHoa!K12 -> 256.1668 | L16: =ThanhHoa!L12 -> 296.2 | M16: =ThanhHoa!M12 -> 376.5 | ... Q16: =ThanhHoa!Q12 -> 155.5 | R16: =SUMIFS($F16:$Q16,$F$7:$Q$7,"A") -> 3505.3648 | S16: =SUMIFS($F16:$Q16,$F$7:$Q$7,"B") -> 0 | T16: =SUM(R16:S16) -> 3505.3648 | U16: =IFERROR(R16/R$45,"") -> 0.077158647 | V16: =IFERROR(S16/S$45,"") | W16: =IFERROR(T16/T$45,"") -> 0.077158647
E17: Thái Nguyên | F17: =ThaiNguyen!F12 -> 75.6 | G17: =ThaiNguyen!G12 -> 127.9 | H17: =ThaiNguyen!H12 -> 206.55 | I17: =ThaiNguyen!I12 -> 173.9 | J17: =ThaiNguyen!J12 -> 239.2 | K17: =ThaiNguyen!K12 -> 249.2 | L17: =ThaiNguyen!L12 -> 272.4 | M17: =ThaiNguyen!M12 -> 344.6 | ... Q17: =ThaiNguyen!Q12 -> 448.3 | R17: =SUMIFS($F17:$Q17,$F$7:$Q$7,"A") -> 3278.95 | S17: =SUMIFS($F17:$Q17,$F$7:$Q$7,"B") -> 0 | T17: =SUM(R17:S17) -> 3278.95 | U17: =IFERROR(R17/R$45,"") -> 0.072174898 | V17: =IFERROR(S17/S$45,"") | W17: =IFERROR(T17/T$45,"") -> 0.072174898
E18: Thái Bình | F18: =ThaiBinh!F12 -> 0 | G18: =ThaiBinh!G12 -> 0 | H18: =ThaiBinh!H12 -> 0 | I18: =ThaiBinh!I12 -> 0 | J18: =ThaiBinh!J12 -> 0 | K18: =ThaiBinh!K12 -> 81.35 | L18: =ThaiBinh!L12 -> 311.85 | M18: =ThaiBinh!M12 -> 503.9 | ... Q18: =ThaiBinh!Q12 -> 225.57 | R18: =SUMIFS($F18:$Q18,$F$7:$Q$7,"A") -> 1940.29 | S18: =SUMIFS($F18:$Q18,$F$7:$Q$7,"B") -> 0 | T18: =SUM(R18:S18) -> 1940.29 | U18: =IFERROR(R18/R$45,"") -> 0.042708865 | V18: =IFERROR(S18/S$45,"") | W18: =IFERROR(T18/T$45,"") -> 0.042708865
E19: Yết Kiêu | F19: =YetKieu!F12 -> 156.35 | G19: =YetKieu!G12 -> 265.34 | H19: =YetKieu!H12 -> 331.05 | I19: =YetKieu!I12 -> 299.79 | J19: =YetKieu!J12 -> 461 | K19: =YetKieu!K12 -> 563.95 | L19: =YetKieu!L12 -> 637.81 | M19: =YetKieu!M12 -> 589.05 | ... Q19: =YetKieu!Q12 -> 647.876 | R19: =SUMIFS($F19:$Q19,$F$7:$Q$7,"A") -> 5743.65 | S19: =SUMIFS($F19:$Q19,$F$7:$Q$7,"B") -> 0 | T19: =SUM(R19:S19) -> 5743.65 | U19: =IFERROR(R19/R$45,"") -> 0.12642686 | V19: =IFERROR(S19/S$45,"") | W19: =IFERROR(T19/T$45,"") -> 0.12642686
E20: Nha Trang | F20: =NhaTrang!F12 -> 176.64 | G20: =NhaTrang!G12 -> 297.54 | H20: =NhaTrang!H12 -> 407.7 | I20: =NhaTrang!I12 -> 399.5 | J20: =NhaTrang!J12 -> 377.15 | K20: =NhaTrang!K12 -> 482.18 | L20: =NhaTrang!L12 -> 496.74 | M20: =NhaTrang!M12 -> 496.5 | ... Q20: =NhaTrang!Q12 -> 530.14 | R20: =SUMIFS($F20:$Q20,$F$7:$Q$7,"A") -> 5106.311 | S20: =SUMIFS($F20:$Q20,$F$7:$Q$7,"B") -> 0 | T20: =SUM(R20:S20) -> 5106.311 | U20: =IFERROR(R20/R$45,"") -> 0.11239802 | V20: =IFERROR(S20/S$45,"") | W20: =IFERROR(T20/T$45,"") -> 0.11239802
E21: Thạch Thất | F21: =0 -> 0 | G21: =0 -> 0 | H21: =0 -> 0 | I21: =0 -> 0 | J21: =0 -> 0 | K21: =0 -> 0 | L21: =0 -> 0 | M21: =0 -> 0 | ... Q21: =0 -> 0 | R21: =SUMIFS($F21:$Q21,$F$7:$Q$7,"A") -> 0 | S21: =SUMIFS($F21:$Q21,$F$7:$Q$7,"B") -> 0 | T21: =SUM(R21:S21) -> 0 | U21: =IFERROR(R21/R$45,"") -> 0 | V21: =IFERROR(S21/S$45,"") | W21: =IFERROR(T21/T$45,"") -> 0
E22: Sóc Sơn | F22: ='SocSon-1'!F22 -> 0 | G22: ='SocSon-1'!G22 -> 0 | H22: ='SocSon-1'!H22 -> 0 | I22: ='SocSon-1'!I22 -> 0 | J22: ='SocSon-1'!J22 -> 0 | K22: ='SocSon-1'!K22 -> 0 | L22: ='SocSon-1'!L22 -> 0 | M22: ='SocSon-1'!M22 -> 0 | ... Q22: ='SocSon-1'!Q22 -> 112.24 | R22: =SUMIFS($F22:$Q22,$F$7:$Q$7,"A") -> 210.99 | S22: =SUMIFS($F22:$Q22,$F$7:$Q$7,"B") -> 0 | T22: =SUM(R22:S22) -> 210.99 | U22: =IFERROR(R22/R$45,"") -> 0.004644225 | V22: =IFERROR(S22/S$45,"") | W22: =IFERROR(T22/T$45,"") -> 0.004644225
D23: CT | F23: =SUBTOTAL(9,F24:F29) -> 198.65 | G23: =SUBTOTAL(9,G24:G29) -> 892.385 | H23: =SUBTOTAL(9,H24:H29) -> 1292.59 | I23: =SUBTOTAL(9,I24:I29) -> 1093.3588 | J23: =SUBTOTAL(9,J24:J29) -> 1199.2536 | K23: =SUBTOTAL(9,K24:K29) -> 1422.221 | L23: =SUBTOTAL(9,L24:L29) -> 996.996 | M23: =SUBTOTAL(9,M24:M29) -> 470.641 | ... T23: =SUBTOTAL(9,T24:T29) -> 10409.137 | U23: =IFERROR(R23/R$45,"") -> 0.22912163 | V23: =IFERROR(S23/S$45,"") | W23: =IFERROR(T23/T$45,"") -> 0.22912163
E24: Hải Dương | F24: =HaiDuong!F44 -> 125.8 | G24: =HaiDuong!G44 -> 171 | H24: =HaiDuong!H44 -> 199.5 | I24: =HaiDuong!I44 -> 239.5 | J24: =HaiDuong!J44 -> 155.5 | K24: =HaiDuong!K44 -> 118.5 | L24: =HaiDuong!L44 -> 94.5 | M24: =HaiDuong!M44 -> 93 | ... Q24: =HaiDuong!Q44 -> 134.9 | R24: =SUMIFS($F24:$Q24,$F$7:$Q$7,"A") -> 1643.3 | S24: =SUMIFS($F24:$Q24,$F$7:$Q$7,"B") -> 0 | T24: =SUM(R24:S24) -> 1643.3 | U24: =IFERROR(R24/R$45,"") -> 0.036171643 | V24: =IFERROR(S24/S$45,"") | W24: =IFERROR(T24/T$45,"") -> 0.036171643
E25: Thanh Hóa | F25: =ThanhHoa!F14 -> 54.6 | G25: =ThanhHoa!G14 -> 690 | H25: =ThanhHoa!H14 -> 1059.2 | I25: =ThanhHoa!I14 -> 810.2388 | J25: =ThanhHoa!J14 -> 1010.7436 | K25: =ThanhHoa!K14 -> 1263.131 | L25: =ThanhHoa!L14 -> 862.961 | M25: =ThanhHoa!M14 -> 342.006 | ... Q25: =ThanhHoa!Q14 -> 38.4 | R25: =SUMIFS($F25:$Q25,$F$7:$Q$7,"A") -> 7406.7257 | S25: =SUMIFS($F25:$Q25,$F$7:$Q$7,"B") -> 0 | T25: =SUM(R25:S25) -> 7406.7257 | U25: =IFERROR(R25/R$45,"") -> 0.1630338 | V25: =IFERROR(S25/S$45,"") | W25: =IFERROR(T25/T$45,"") -> 0.1630338
E26: Thái Nguyên | F26: =ThaiNguyen!F14 -> 0 | G26: =ThaiNguyen!G14 -> 0 | H26: =ThaiNguyen!H14 -> 0 | I26: =ThaiNguyen!I14 -> 0 | J26: =ThaiNguyen!J14 -> 0 | K26: =ThaiNguyen!K14 -> 0 | L26: =ThaiNguyen!L14 -> 1.5 | M26: =ThaiNguyen!M14 -> 1 | ... Q26: =ThaiNguyen!Q14 -> 15 | R26: =SUMIFS($F26:$Q26,$F$7:$Q$7,"A") -> 35 | S26: =SUMIFS($F26:$Q26,$F$7:$Q$7,"B") -> 0 | T26: =SUM(R26:S26) -> 35 | U26: =IFERROR(R26/R$45,"") -> 0.00077040559 | V26: =IFERROR(S26/S$45,"") | W26: =IFERROR(T26/T$45,"") -> 0.00077040559
E27: Yết Kiêu | F27: =YetKieu!F14 -> 10.95 | G27: =YetKieu!G14 -> 16.85 | H27: =YetKieu!H14 -> 16.34 | I27: =YetKieu!I14 -> 16.22 | J27: =YetKieu!J14 -> 19.56 | K27: =YetKieu!K14 -> 26.14 | L27: =YetKieu!L14 -> 23.61 | M27: =YetKieu!M14 -> 19.11 | ... Q27: =YetKieu!Q14 -> 47.3 | R27: =SUMIFS($F27:$Q27,$F$7:$Q$7,"A") -> 277.346 | S27: =SUMIFS($F27:$Q27,$F$7:$Q$7,"B") -> 0 | T27: =SUM(R27:S27) -> 277.346 | U27: =IFERROR(R27/R$45,"") -> 0.006104826 | V27: =IFERROR(S27/S$45,"") | W27: =IFERROR(T27/T$45,"") -> 0.006104826
E28: Nha Trang | F28: =NhaTrang!F13 -> 7.3 | G28: =NhaTrang!G13 -> 14.535 | H28: =NhaTrang!H13 -> 17.55 | I28: =NhaTrang!I13 -> 27.4 | J28: =NhaTrang!J13 -> 13.45 | K28: =NhaTrang!K13 -> 14.45 | L28: =NhaTrang!L13 -> 14.425 | M28: =NhaTrang!M13 -> 15.525 | ... Q28: =NhaTrang!Q13 -> 40.65 | R28: =SUMIFS($F28:$Q28,$F$7:$Q$7,"A") -> 353.465 | S28: =SUMIFS($F28:$Q28,$F$7:$Q$7,"B") -> 0 | T28: =SUM(R28:S28) -> 353.465 | U28: =IFERROR(R28/R$45,"") -> 0.0077803261 | V28: =IFERROR(S28/S$45,"") | W28: =IFERROR(T28/T$45,"") -> 0.0077803261
E29: Thạch Thất | F29: =ThachThat!F12 -> 0 | G29: =ThachThat!G12 -> 0 | H29: =ThachThat!H12 -> 0 | I29: =ThachThat!I12 -> 0 | J29: =ThachThat!J12 -> 0 | K29: =ThachThat!K12 -> 0 | L29: =ThachThat!L12 -> 0 | M29: =ThachThat!M12 -> 0 | ... Q29: =ThachThat!Q12 -> 84 | R29: =SUMIFS($F29:$Q29,$F$7:$Q$7,"A") -> 693.3 | S29: =SUMIFS($F29:$Q29,$F$7:$Q$7,"B") -> 0 | T29: =SUM(R29:S29) -> 693.3 | U29: =IFERROR(R29/R$45,"") -> 0.015260634 | V29: =IFERROR(S29/S$45,"") | W29: =IFERROR(T29/T$45,"") -> 0.015260634
D30: Mammo X-Quang | F30: =SUBTOTAL(9,F31:F34) -> 14.64 | G30: =SUBTOTAL(9,G31:G34) -> 20.525 | H30: =SUBTOTAL(9,H31:H34) -> 40.05 | I30: =SUBTOTAL(9,I31:I34) -> 39.3 | J30: =SUBTOTAL(9,J31:J34) -> 72.315 | K30: =SUBTOTAL(9,K31:K34) -> 57.515 | L30: =SUBTOTAL(9,L31:L34) -> 43.1 | M30: =SUBTOTAL(9,M31:M34) -> 42.3 | ... Q30: =SUBTOTAL(9,Q31:Q34) -> 27.225 | R30: =SUMIFS($F30:$Q30,$F$7:$Q$7,"A") -> 495.5856 | S30: =SUMIFS($F30:$Q30,$F$7:$Q$7,"B") -> 0 | T30: =SUM(R30:S30) -> 495.5856 | U30: =IFERROR(R30/R$45,"") -> 0.010908626 | V30: =IFERROR(S30/S$45,"") | W30: =IFERROR(T30/T$45,"") -> 0.010908626
E31: Hải Dương | F31: =HaiDuong!F43 -> 4 | G31: =HaiDuong!G43 -> 9.5 | H31: =HaiDuong!H43 -> 8.5 | I31: =HaiDuong!I43 -> 20.5 | J31: =HaiDuong!J43 -> 11 | K31: =HaiDuong!K43 -> 10.8 | L31: =HaiDuong!L43 -> 10.5 | M31: =HaiDuong!M43 -> 14 | ... Q31: =HaiDuong!Q43 -> 8 | R31: =SUMIFS($F31:$Q31,$F$7:$Q$7,"A") -> 124.3 | S31: =SUMIFS($F31:$Q31,$F$7:$Q$7,"B") -> 0 | T31: =SUM(R31:S31) -> 124.3 | U31: =IFERROR(R31/R$45,"") -> 0.0027360404 | V31: =IFERROR(S31/S$45,"") | W31: =IFERROR(T31/T$45,"") -> 0.0027360404
E32: Cà Mau | F32: =CaMau!F13 -> 8 | G32: =CaMau!G13 -> 8 | H32: =CaMau!H13 -> 25.5 | I32: =CaMau!I13 -> 15.5 | J32: =CaMau!J13 -> 16.8 | K32: =CaMau!K13 -> 39.3 | L32: =CaMau!L13 -> 19.4 | M32: =CaMau!M13 -> 24.5 | ... Q32: =CaMau!Q13 -> 13.4 | R32: =SUMIFS($F32:$Q32,$F$7:$Q$7,"A") -> 222.1 | S32: =SUMIFS($F32:$Q32,$F$7:$Q$7,"B") -> 0 | T32: =SUM(R32:S32) -> 222.1 | U32: =IFERROR(R32/R$45,"") -> 0.0048887738 | V32: =IFERROR(S32/S$45,"") | W32: =IFERROR(T32/T$45,"") -> 0.0048887738
E33: Yết Kiêu | F33: =YetKieu!F13 -> 0.55 | G33: =YetKieu!G13 -> 1.925 | H33: =YetKieu!H13 -> 2.75 | I33: =YetKieu!I13 -> 0.55 | J33: =YetKieu!J13 -> 43.14 | K33: =YetKieu!K13 -> 5.49 | L33: =YetKieu!L13 -> 8.8 | M33: =YetKieu!M13 -> 1.05 | ... Q33: =YetKieu!Q13 -> 2.315 | R33: =SUMIFS($F33:$Q33,$F$7:$Q$7,"A") -> 79.0656 | S33: =SUMIFS($F33:$Q33,$F$7:$Q$7,"B") -> 0 | T33: =SUM(R33:S33) -> 79.0656 | U33: =IFERROR(R33/R$45,"") -> 0.0017403594 | V33: =IFERROR(S33/S$45,"") | W33: =IFERROR(T33/T$45,"") -> 0.0017403594
E34: Nha Trang | F34: =NhaTrang!F14 -> 2.09 | G34: =NhaTrang!G14 -> 1.1 | H34: =NhaTrang!H14 -> 3.3 | I34: =NhaTrang!I14 -> 2.75 | J34: =NhaTrang!J14 -> 1.375 | K34: =NhaTrang!K14 -> 1.925 | L34: =NhaTrang!L14 -> 4.4 | M34: =NhaTrang!M14 -> 2.75 | ... Q34: =NhaTrang!Q14 -> 3.51 | R34: =SUMIFS($F34:$Q34,$F$7:$Q$7,"A") -> 70.12 | S34: =SUMIFS($F34:$Q34,$F$7:$Q$7,"B") -> 0 | T34: =SUM(R34:S34) -> 70.12 | U34: =IFERROR(R34/R$45,"") -> 0.0015434526 | V34: =IFERROR(S34/S$45,"") | W34: =IFERROR(T34/T$45,"") -> 0.0015434526
D35: X-Quang | F35: =SUBTOTAL(9,F36:F39) -> 10.225 | G35: =SUBTOTAL(9,G36:G39) -> 15.75 | H35: =SUBTOTAL(9,H36:H39) -> 29.157 | I35: =SUBTOTAL(9,I36:I39) -> 35.855 | J35: =SUBTOTAL(9,J36:J39) -> 29.24 | K35: =SUBTOTAL(9,K36:K39) -> 33.59 | L35: =SUBTOTAL(9,L36:L39) -> 38.19 | M35: =SUBTOTAL(9,M36:M39) -> 28.62 | ... Q35: =SUBTOTAL(9,Q36:Q39) -> 28.77 | R35: =SUMIFS($F35:$Q35,$F$7:$Q$7,"A") -> 360.407 | S35: =SUMIFS($F35:$Q35,$F$7:$Q$7,"B") -> 0 | T35: =SUM(R35:S35) -> 360.407 | U35: =IFERROR(R35/R$45,"") -> 0.0079331305 | V35: =IFERROR(S35/S$45,"") | W35: =IFERROR(T35/T$45,"") -> 0.0079331305
E36: Hải Dương | F36: =HaiDuong!F45 -> 8.35 | G36: =HaiDuong!G45 -> 11 | H36: =HaiDuong!H45 -> 23.6 | I36: =HaiDuong!I45 -> 30.75 | J36: =HaiDuong!J45 -> 23.1 | K36: =HaiDuong!K45 -> 25.15 | L36: =HaiDuong!L45 -> 31.35 | M36: =HaiDuong!M45 -> 23.75 | ... Q36: =HaiDuong!Q45 -> 22.5 | R36: =SUMIFS($F36:$Q36,$F$7:$Q$7,"A") -> 278.5 | S36: =SUMIFS($F36:$Q36,$F$7:$Q$7,"B") -> 0 | T36: =SUM(R36:S36) -> 278.5 | U36: =IFERROR(R36/R$45,"") -> 0.0061302274 | V36: =IFERROR(S36/S$45,"") | W36: =IFERROR(T36/T$45,"") -> 0.0061302274
E37: Thái Nguyên | F37: =ThaiNguyen!F15 -> 0 | G37: =ThaiNguyen!G15 -> 0 | H37: =ThaiNguyen!H15 -> 0 | I37: =ThaiNguyen!I15 -> 0 | J37: =ThaiNguyen!J15 -> 0 | K37: =ThaiNguyen!K15 -> 0 | L37: =ThaiNguyen!L15 -> 0 | M37: =ThaiNguyen!M15 -> 0 | ... Q37: =ThaiNguyen!Q15 -> 1.65 | R37: =SUMIFS($F37:$Q37,$F$7:$Q$7,"A") -> 8.1 | S37: =SUMIFS($F37:$Q37,$F$7:$Q$7,"B") -> 0 | T37: =SUM(R37:S37) -> 8.1 | U37: =IFERROR(R37/R$45,"") -> 0.00017829387 | V37: =IFERROR(S37/S$45,"") | W37: =IFERROR(T37/T$45,"") -> 0.00017829387
E38: Thái Bình | F38: =ThaiBinh!F15 -> 0 | G38: =ThaiBinh!G15 -> 0 | H38: =ThaiBinh!H15 -> 0 | I38: =ThaiBinh!I15 -> 0 | J38: =ThaiBinh!J15 -> 0 | K38: =ThaiBinh!K15 -> 0 | L38: =ThaiBinh!L15 -> 0 | M38: =ThaiBinh!M15 -> 0 | ... Q38: =ThaiBinh!Q15 -> 2.2 | R38: =SUMIFS($F38:$Q38,$F$7:$Q$7,"A") -> 6.15 | S38: =SUMIFS($F38:$Q38,$F$7:$Q$7,"B") -> 0 | T38: =SUM(R38:S38) -> 6.15 | U38: =IFERROR(R38/R$45,"") -> 0.00013537127 | V38: =IFERROR(S38/S$45,"") | W38: =IFERROR(T38/T$45,"") -> 0.00013537127
E39: Yết Kiêu | F39: =YetKieu!F15 -> 1.875 | G39: =YetKieu!G15 -> 4.75 | H39: =YetKieu!H15 -> 5.557 | I39: =YetKieu!I15 -> 5.105 | J39: =YetKieu!J15 -> 6.14 | K39: =YetKieu!K15 -> 8.44 | L39: =YetKieu!L15 -> 6.84 | M39: =YetKieu!M15 -> 4.87 | ... Q39: =YetKieu!Q15 -> 2.42 | R39: =SUMIFS($F39:$Q39,$F$7:$Q$7,"A") -> 67.657 | S39: =SUMIFS($F39:$Q39,$F$7:$Q$7,"B") -> 0 | T39: =SUM(R39:S39) -> 67.657 | U39: =IFERROR(R39/R$45,"") -> 0.001489238 | V39: =IFERROR(S39/S$45,"") | W39: =IFERROR(T39/T$45,"") -> 0.001489238
D40: Siêu âm | F40: =SUBTOTAL(9,F41:F42) -> 5.7 | G40: =SUBTOTAL(9,G41:G42) -> 11.1 | H40: =SUBTOTAL(9,H41:H42) -> 11.3 | I40: =SUBTOTAL(9,I41:I42) -> 9.3 | J40: =SUBTOTAL(9,J41:J42) -> 7.25 | K40: =SUBTOTAL(9,K41:K42) -> 6.55 | L40: =SUBTOTAL(9,L41:L42) -> 13.9 | M40: =SUBTOTAL(9,M41:M42) -> 7.45 | ... Q40: =SUBTOTAL(9,Q41:Q42) -> 15.95 | R40: =SUMIFS($F40:$Q40,$F$7:$Q$7,"A") -> 131.54 | S40: =SUMIFS($F40:$Q40,$F$7:$Q$7,"B") -> 0 | T40: =SUM(R40:S40) -> 131.54 | U40: =IFERROR(R40/R$45,"") -> 0.0028954043 | V40: =IFERROR(S40/S$45,"") | W40: =IFERROR(T40/T$45,"") -> 0.0028954043
E41: Hải Dương | F41: =HaiDuong!F46 -> 5 | G41: =HaiDuong!G46 -> 11.1 | H41: =HaiDuong!H46 -> 10.6 | I41: =HaiDuong!I46 -> 9.05 | J41: =HaiDuong!J46 -> 7.15 | K41: =HaiDuong!K46 -> 6.55 | L41: =HaiDuong!L46 -> 13.9 | M41: =HaiDuong!M46 -> 7.45 | ... Q41: =HaiDuong!Q46 -> 11.3 | R41: =SUMIFS($F41:$Q41,$F$7:$Q$7,"A") -> 114.9 | S41: =SUMIFS($F41:$Q41,$F$7:$Q$7,"B") -> 0 | T41: =SUM(R41:S41) -> 114.9 | U41: =IFERROR(R41/R$45,"") -> 0.0025291315 | V41: =IFERROR(S41/S$45,"") | W41: =IFERROR(T41/T$45,"") -> 0.0025291315
E42: Yết Kiêu | F42: =YetKieu!F16 -> 0.7 | G42: =YetKieu!G16 -> 0 | H42: =YetKieu!H16 -> 0.7 | I42: =YetKieu!I16 -> 0.25 | J42: =YetKieu!J16 -> 0.1 | K42: =YetKieu!K16 -> 0 | L42: =YetKieu!L16 -> 0 | M42: =YetKieu!M16 -> 0 | ... Q42: =YetKieu!Q16 -> 4.65 | R42: =SUMIFS($F42:$Q42,$F$7:$Q$7,"A") -> 16.64 | S42: =SUMIFS($F42:$Q42,$F$7:$Q$7,"B") -> 0 | T42: =SUM(R42:S42) -> 16.64 | U42: =IFERROR(R42/R$45,"") -> 0.00036627283 | V42: =IFERROR(S42/S$45,"") | W42: =IFERROR(T42/T$45,"") -> 0.00036627283
C43: Tổng- Chẩn đoán hình ảnh | F43: =SUBTOTAL(9,F13:F42) -> 1481.585 | G43: =SUBTOTAL(9,G13:G42) -> 3069.64 | H43: =SUBTOTAL(9,H13:H42) -> 3894.769 | I43: =SUBTOTAL(9,I13:I42) -> 3957.0754 | J43: =SUBTOTAL(9,J13:J42) -> 4260.1387 | K43: =SUBTOTAL(9,K13:K42) -> 4547.1528 | L43: =SUBTOTAL(9,L13:L42) -> 4410.036 | M43: =SUBTOTAL(9,M13:M42) -> 3999.461 | ... Q43: =SUBTOTAL(9,Q13:Q42) -> 3605.871 | R43: =SUMIFS($F43:$Q43,$F$7:$Q$7,"A") -> 45366.945 | S43: =SUMIFS($F43:$Q43,$F$7:$Q$7,"B") -> 0 | T43: =SUM(R43:S43) -> 45366.945 | U43: =IFERROR(R43/R$45,"") -> 0.99859852 | V43: =IFERROR(S43/S$45,"") | W43: =IFERROR(T43/T$45,"") -> 0.99859852
C44: Tổng- Khác | F44: =SUM(HaiDuong!F48,CaMau!F18,ThanhHoa!F18,ThaiNguyen!F18,YetKieu!F17,NhaTrang!F15) -> 0 | G44: =SUM(HaiDuong!G48,CaMau!G18,ThanhHoa!G18,ThaiNguyen!G18,YetKieu!G17,NhaTrang!G15) -> 1.85 | H44: =SUM(HaiDuong!H48,CaMau!H18,ThanhHoa!H18,ThaiNguyen!H18,YetKieu!H17,NhaTrang!H15) -> 1.05 | I44: =SUM(HaiDuong!I48,CaMau!I18,ThanhHoa!I18,ThaiNguyen!I18,YetKieu!I17,NhaTrang!I15) -> 6.6 | J44: =SUM(HaiDuong!J48,CaMau!J18,ThanhHoa!J18,ThaiNguyen!J18,YetKieu!J17,NhaTrang!J15) -> 4.9 | K44: =SUM(HaiDuong!K48,CaMau!K18,ThanhHoa!K18,ThaiNguyen!K18,YetKieu!K17,NhaTrang!K15) -> 9.3 | L44: =SUM(HaiDuong!L48,CaMau!L18,ThanhHoa!L18,ThaiNguyen!L18,YetKieu!L17,NhaTrang!L15) -> 6.8 | M44: =SUM(HaiDuong!M48,CaMau!M18,ThanhHoa!M18,ThaiNguyen!M18,YetKieu!M17,NhaTrang!M15) -> 5.95 | ... Q44: =SUM(HaiDuong!Q48,CaMau!Q18,ThanhHoa!Q18,ThaiNguyen!Q18,YetKieu!Q17,NhaTrang!Q15) -> 5.65 | R44: =SUMIFS($F44:$Q44,$F$7:$Q$7,"A") -> 63.67 | S44: =SUMIFS($F44:$Q44,$F$7:$Q$7,"B") -> 0 | T44: =SUM(R44:S44) -> 63.67 | U44: =IFERROR(R44/R$45,"") -> 0.0014014778 | V44: =IFERROR(S44/S$45,"") | W44: =IFERROR(T44/T$45,"") -> 0.0014014778
B45: Tổng- Doanh thu | F45: =SUM(F43:F44) -> 1481.585 | G45: =SUM(G43,G44) -> 3071.49 | H45: =SUM(H43,H44) -> 3895.819 | I45: =SUM(I43,I44) -> 3963.6754 | J45: =SUM(J43,J44) -> 4265.0387 | K45: =SUM(K43,K44) -> 4556.4528 | L45: =SUM(L43,L44) -> 4416.836 | M45: =SUM(M43,M44) -> 4005.411 | N45: =SUM(N43,N44) -> 4807.8152 | ... Q45: =SUM(Q43,Q44) -> 3611.521 | R45: =SUMIFS($F45:$Q45,$F$7:$Q$7,"A") -> 45430.615 | S45: =SUMIFS($F45:$Q45,$F$7:$Q$7,"B") -> 0 | T45: =SUM(R45:S45) -> 45430.615 | U45: =IFERROR(R45/R$45,"") -> 1 | V45: =IFERROR(S45/S$45,"") | W45: =IFERROR(T45/T$45,"") -> 1
B46: Giảm trừ doanh thu | F46: =SUM(HaiDuong!F50,CaMau!F20,ThanhHoa!F20,ThaiNguyen!F20) -> 0.1 | G46: =SUM(HaiDuong!G50,CaMau!G20,ThanhHoa!G20,ThaiNguyen!G20) -> 26.36 | H46: =SUM(HaiDuong!H50,CaMau!H20,ThanhHoa!H20,ThaiNguyen!H20) -> 49.46 | I46: =SUM(HaiDuong!I50,CaMau!I20,ThanhHoa!I20,ThaiNguyen!I20) -> 43.69 | J46: =SUM(HaiDuong!J50,CaMau!J20,ThanhHoa!J20,ThaiNguyen!J20) -> 65.38 | K46: =SUM(HaiDuong!K50,CaMau!K20,ThanhHoa!K20,ThaiNguyen!K20) -> 57.76 | L46: =SUM(HaiDuong!L50,CaMau!L20,ThanhHoa!L20,ThaiNguyen!L20) -> 54.66 | M46: =SUM(HaiDuong!M50,CaMau!M20,ThanhHoa!M20,ThaiNguyen!M20) -> 83.46 | ... Q46: =SUM(HaiDuong!Q50,CaMau!Q20,ThanhHoa!Q20,ThaiNguyen!Q20) -> 111.6 | R46: =SUMIFS($F46:$Q46,$F$7:$Q$7,"A") -> 757.135 | S46: =SUMIFS($F46:$Q46,$F$7:$Q$7,"B") -> 0 | T46: =SUM(R46:S46) -> 757.135 | U46: =IFERROR(R46/R$45,"") -> 0.016665744 | V46: =IFERROR(S46/S$45,"") | W46: =IFERROR(T46/T$45,"") -> 0.016665744
B47: Biến phí | U47: =IFERROR(R47/R$45,"") -> 0 | V47: =IFERROR(S47/S$45,"") | W47: =IFERROR(T47/T$45,"") -> 0
C48: Vật tư tiêu hao | F48: =SUBTOTAL(9,F49:F57) -> 63.45103 | G48: =SUBTOTAL(9,G49:G57) -> 131.0551 | H48: =SUBTOTAL(9,H49:H57) -> 151.59247 | I48: =SUBTOTAL(9,I49:I57) -> 156.25849 | J48: =SUBTOTAL(9,J49:J57) -> 179.39332 | K48: =SUBTOTAL(9,K49:K57) -> 174.63695 | L48: =SUBTOTAL(9,L49:L57) -> 177.38941 | M48: =SUBTOTAL(9,M49:M57) -> 174.39065 | ... Q48: =SUBTOTAL(9,Q49:Q57) -> 155.67431 | R48: =SUMIFS($F48:$Q48,$F$7:$Q$7,"A") -> 1903.5951 | S48: =SUMIFS($F48:$Q48,$F$7:$Q$7,"B") -> 0 | T48: =SUM(R48:S48) -> 1903.5951 | U48: =IFERROR(R48/R$45,"") -> 0.041901152 | V48: =IFERROR(S48/S$45,"") | W48: =IFERROR(T48/T$45,"") -> 0.041901152
D49: Hải Dương | F49: =HaiDuong!F57 -> 25.903983 | G49: =HaiDuong!G57 -> 42.191047 | H49: =HaiDuong!H57 -> 48.855017 | I49: =HaiDuong!I57 -> 51.247995 | J49: =HaiDuong!J57 -> 49.248269 | K49: =HaiDuong!K57 -> 40.210769 | L49: =HaiDuong!L57 -> 40.563081 | M49: =HaiDuong!M57 -> 33.949967 | ... Q49: =HaiDuong!Q57 -> 39.015565 | R49: =SUMIFS($F49:$Q49,$F$7:$Q$7,"A") -> 479.98592 | S49: =SUMIFS($F49:$Q49,$F$7:$Q$7,"B") -> 0 | T49: =SUM(R49:S49) -> 479.98592 | U49: =IFERROR(R49/R$45,"") -> 0.010565253 | V49: =IFERROR(S49/S$45,"") | W49: =IFERROR(T49/T$45,"") -> 0.010565253
D50: Cà Mau | F50: =CaMau!F27 -> 0.89703358 | G50: =CaMau!G27 -> 1.5717934 | H50: =CaMau!H27 -> 2.1354162 | I50: =CaMau!I27 -> 2.35769 | J50: =CaMau!J27 -> 2.3021216 | K50: =CaMau!K27 -> 3.2547236 | L50: =CaMau!L27 -> 2.2862449 | M50: =CaMau!M27 -> 2.3735667 | ... Q50: =CaMau!Q27 -> 1.7146837 | R50: =SUMIFS($F50:$Q50,$F$7:$Q$7,"A") -> 25.7917 | S50: =SUMIFS($F50:$Q50,$F$7:$Q$7,"B") -> 0 | T50: =SUM(R50:S50) -> 25.7917 | U50: =IFERROR(R50/R$45,"") -> 0.00056771628 | V50: =IFERROR(S50/S$45,"") | W50: =IFERROR(T50/T$45,"") -> 0.00056771628
D51: Thanh Hóa | F51: =ThanhHoa!F26 -> 3.982581 | G51: =ThanhHoa!G26 -> 34.967991 | H51: =ThanhHoa!H26 -> 43.656483 | I51: =ThanhHoa!I26 -> 38.436353 | J51: =ThanhHoa!J26 -> 55.687973 | K51: =ThanhHoa!K26 -> 38.616177 | L51: =ThanhHoa!L26 -> 31.979 | M51: =ThanhHoa!M26 -> 19.227959 | ... Q51: =ThanhHoa!Q26 -> 1.350152 | R51: =SUMIFS($F51:$Q51,$F$7:$Q$7,"A") -> 316.33424 | S51: =SUMIFS($F51:$Q51,$F$7:$Q$7,"B") -> 0 | T51: =SUM(R51:S51) -> 316.33424 | U51: =IFERROR(R51/R$45,"") -> 0.0069630192 | V51: =IFERROR(S51/S$45,"") | W51: =IFERROR(T51/T$45,"") -> 0.0069630192
D52: Thái Nguyên | F52: =ThaiNguyen!F27 -> 2.4795 | G52: =ThaiNguyen!G27 -> 4.0755 | H52: =ThaiNguyen!H27 -> 6.9825 | I52: =ThaiNguyen!I27 -> 5.6715 | J52: =ThaiNguyen!J27 -> 7.6095 | K52: =ThaiNguyen!K27 -> 13.025049 | L52: =ThaiNguyen!L27 -> 9.199623 | M52: =ThaiNguyen!M27 -> 11.153324 | ... Q52: =ThaiNguyen!Q27 -> 14.599018 | R52: =SUMIFS($F52:$Q52,$F$7:$Q$7,"A") -> 111.4161 | S52: =SUMIFS($F52:$Q52,$F$7:$Q$7,"B") -> 0 | T52: =SUM(R52:S52) -> 111.4161 | U52: =IFERROR(R52/R$45,"") -> 0.0024524453 | V52: =IFERROR(S52/S$45,"") | W52: =IFERROR(T52/T$45,"") -> 0.0024524453
D53: Thái Bình | F53: =ThaiBinh!F21 -> 0 | G53: =ThaiBinh!G21 -> 0 | H53: =ThaiBinh!H21 -> 0 | I53: =ThaiBinh!I21 -> 0 | J53: =ThaiBinh!J21 -> 0 | K53: =ThaiBinh!K21 -> 5.13 | L53: =ThaiBinh!L21 -> 19.3515 | M53: =ThaiBinh!M21 -> 35.169 | ... Q53: =ThaiBinh!Q21 -> 8.8655 | R53: =SUMIFS($F53:$Q53,$F$7:$Q$7,"A") -> 109.8095 | S53: =SUMIFS($F53:$Q53,$F$7:$Q$7,"B") -> 0 | T53: =SUM(R53:S53) -> 109.8095 | U53: =IFERROR(R53/R$45,"") -> 0.0024170815 | V53: =IFERROR(S53/S$45,"") | W53: =IFERROR(T53/T$45,"") -> 0.0024170815
D54: Yết Kiêu | F54: =YetKieu!F28 -> 22.65886 | G54: =YetKieu!G28 -> 36.383829 | H54: =YetKieu!H28 -> 41.245697 | I54: =YetKieu!I28 -> 42.079651 | J54: =YetKieu!J28 -> 49.376165 | K54: =YetKieu!K28 -> 55.89194 | L54: =YetKieu!L28 -> 54.326172 | M54: =YetKieu!M28 -> 53.441055 | ... Q54: =YetKieu!Q28 -> 59.399268 | R54: =SUMIFS($F54:$Q54,$F$7:$Q$7,"A") -> 608.01031 | S54: =SUMIFS($F54:$Q54,$F$7:$Q$7,"B") -> 0 | T54: =SUM(R54:S54) -> 608.01031 | U54: =IFERROR(R54/R$45,"") -> 0.013383273 | V54: =IFERROR(S54/S$45,"") | W54: =IFERROR(T54/T$45,"") -> 0.013383273
D55: Nha Trang | F55: =NhaTrang!F24 -> 7.529072 | G55: =NhaTrang!G24 -> 11.864944 | H55: =NhaTrang!H24 -> 8.71736 | I55: =NhaTrang!I24 -> 16.465296 | J55: =NhaTrang!J24 -> 15.169296 | K55: =NhaTrang!K24 -> 18.508288 | L55: =NhaTrang!L24 -> 19.683792 | M55: =NhaTrang!M24 -> 19.075776 | ... Q55: =NhaTrang!Q24 -> 20.343223 | R55: =SUMIFS($F55:$Q55,$F$7:$Q$7,"A") -> 206.72404 | S55: =SUMIFS($F55:$Q55,$F$7:$Q$7,"B") -> 0 | T55: =SUM(R55:S55) -> 206.72404 | U55: =IFERROR(R55/R$45,"") -> 0.0045503245 | V55: =IFERROR(S55/S$45,"") | W55: =IFERROR(T55/T$45,"") -> 0.0045503245
D56: Thạch Thất | F56: =ThachThat!F17 -> 0 | G56: =ThachThat!G17 -> 0 | H56: =ThachThat!H17 -> 0 | I56: =ThachThat!I17 -> 0 | J56: =ThachThat!J17 -> 0 | K56: =ThachThat!K17 -> 0 | L56: =ThachThat!L17 -> 0 | M56: =ThachThat!M17 -> 0 | ... Q56: =ThachThat!Q17 -> 3.9615 | R56: =SUMIFS($F56:$Q56,$F$7:$Q$7,"A") -> 34.056 | S56: =SUMIFS($F56:$Q56,$F$7:$Q$7,"B") -> 0 | T56: =SUM(R56:S56) -> 34.056 | U56: =IFERROR(R56/R$45,"") -> 0.00074962665 | V56: =IFERROR(S56/S$45,"") | W56: =IFERROR(T56/T$45,"") -> 0.00074962665
D57: Sóc Sơn | F57: ='SocSon-1'!F26 -> 0 | G57: ='SocSon-1'!G26 -> 0 | H57: ='SocSon-1'!H26 -> 0 | I57: ='SocSon-1'!I26 -> 0 | J57: ='SocSon-1'!J26 -> 0 | K57: ='SocSon-1'!K26 -> 0 | L57: ='SocSon-1'!L26 -> 0 | M57: ='SocSon-1'!M26 -> 0 | ... Q57: ='SocSon-1'!Q26 -> 6.4254 | R57: =SUMIFS($F57:$Q57,$F$7:$Q$7,"A") -> 11.4673 | S57: =SUMIFS($F57:$Q57,$F$7:$Q$7,"B") -> 0 | T57: =SUM(R57:S57) -> 11.4673 | U57: =IFERROR(R57/R$45,"") -> 0.00025241349 | V57: =IFERROR(S57/S$45,"") | W57: =IFERROR(T57/T$45,"") -> 0.00025241349
C58: Chi phí đọc kết quả online | F58: =SUBTOTAL(9,F59:F67) -> 100.57 | G58: =SUBTOTAL(9,G59:G67) -> 209.795 | H58: =SUBTOTAL(9,H59:H67) -> 276.175 | I58: =SUBTOTAL(9,I59:I67) -> 267.495 | J58: =SUBTOTAL(9,J59:J67) -> 352.455 | K58: =SUBTOTAL(9,K59:K67) -> 338.67 | L58: =SUBTOTAL(9,L59:L67) -> 326.6 | M58: =SUBTOTAL(9,M59:M67) -> 290.165 | ... Q58: =SUBTOTAL(9,Q59:Q67) -> 244.251 | R58: =SUMIFS($F58:$Q58,$F$7:$Q$7,"A") -> 3295.236 | S58: =SUMIFS($F58:$Q58,$F$7:$Q$7,"B") -> 0 | T58: =SUM(R58:S58) -> 3295.236 | U58: =IFERROR(R58/R$45,"") -> 0.072533378 | V58: =IFERROR(S58/S$45,"") | W58: =IFERROR(T58/T$45,"") -> 0.072533378
D59: Hải Dương | F59: =HaiDuong!F58 -> 45.22 | G59: =HaiDuong!G58 -> 64.95 | H59: =HaiDuong!H58 -> 73.75 | I59: =HaiDuong!I58 -> 87.965 | J59: =HaiDuong!J58 -> 70.765 | K59: =HaiDuong!K58 -> 67.405 | L59: =HaiDuong!L58 -> 67.39 | M59: =HaiDuong!M58 -> 50.83 | ... Q59: =HaiDuong!Q58 -> 56.793 | R59: =SUMIFS($F59:$Q59,$F$7:$Q$7,"A") -> 742.834 | S59: =SUMIFS($F59:$Q59,$F$7:$Q$7,"B") -> 0 | T59: =SUM(R59:S59) -> 742.834 | U59: =IFERROR(R59/R$45,"") -> 0.016350956 | V59: =IFERROR(S59/S$45,"") | W59: =IFERROR(T59/T$45,"") -> 0.016350956
D60: Cà Mau | F60: =CaMau!F28 -> 12.345 | G60: =CaMau!G28 -> 21.89 | H60: =CaMau!H28 -> 28.13 | I60: =CaMau!I28 -> 32.45 | J60: =CaMau!J28 -> 31.425 | K60: =CaMau!K28 -> 42.255 | L60: =CaMau!L28 -> 30.92 | M60: =CaMau!M28 -> 32.18 | ... Q60: =CaMau!Q28 -> 23.695 | R60: =SUMIFS($F60:$Q60,$F$7:$Q$7,"A") -> 350.505 | S60: =SUMIFS($F60:$Q60,$F$7:$Q$7,"B") -> 0 | T60: =SUM(R60:S60) -> 350.505 | U60: =IFERROR(R60/R$45,"") -> 0.0077151718 | V60: =IFERROR(S60/S$45,"") | W60: =IFERROR(T60/T$45,"") -> 0.0077151718
D61: Thanh Hóa | F61: =ThanhHoa!F27 -> 15.41 | G61: =ThanhHoa!G27 -> 75.555 | H61: =ThanhHoa!H27 -> 108.79 | I61: =ThanhHoa!I27 -> 88.535 | J61: =ThanhHoa!J27 -> 176.32 | K61: =ThanhHoa!K27 -> 136.37 | L61: =ThanhHoa!L27 -> 100.83 | M61: =ThanhHoa!M27 -> 50.93 | ... Q61: =ThanhHoa!Q27 -> 13.685 | R61: =SUMIFS($F61:$Q61,$F$7:$Q$7,"A") -> 929.12 | S61: =SUMIFS($F61:$Q61,$F$7:$Q$7,"B") -> 0 | T61: =SUM(R61:S61) -> 929.12 | U61: =IFERROR(R61/R$45,"") -> 0.020451407 | V61: =IFERROR(S61/S$45,"") | W61: =IFERROR(T61/T$45,"") -> 0.020451407
D62: Thái Nguyên | F62: =ThaiNguyen!F28 -> 4.95 | G62: =ThaiNguyen!G28 -> 7.705 | H62: =ThaiNguyen!H28 -> 13.11 | I62: =ThaiNguyen!I28 -> 11.04 | J62: =ThaiNguyen!J28 -> 14.145 | K62: =ThaiNguyen!K28 -> 14.95 | L62: =ThaiNguyen!L28 -> 16.79 | M62: =ThaiNguyen!M28 -> 20.93 | ... Q62: =ThaiNguyen!Q28 -> 29.89 | R62: =SUMIFS($F62:$Q62,$F$7:$Q$7,"A") -> 207.191 | S62: =SUMIFS($F62:$Q62,$F$7:$Q$7,"B") -> 0 | T62: =SUM(R62:S62) -> 207.191 | U62: =IFERROR(R62/R$45,"") -> 0.004560603 | V62: =IFERROR(S62/S$45,"") | W62: =IFERROR(T62/T$45,"") -> 0.004560603
D63: Thái Bình | F63: =ThaiBinh!F22 -> 0 | G63: =ThaiBinh!G22 -> 0 | H63: =ThaiBinh!H22 -> 0 | I63: =ThaiBinh!I22 -> 0 | J63: =ThaiBinh!J22 -> 0 | K63: =ThaiBinh!K22 -> 8.97 | L63: =ThaiBinh!L22 -> 36.915 | M63: =ThaiBinh!M22 -> 68.08 | ... Q63: =ThaiBinh!Q22 -> 17.44 | R63: =SUMIFS($F63:$Q63,$F$7:$Q$7,"A") -> 198.598 | S63: =SUMIFS($F63:$Q63,$F$7:$Q$7,"B") -> 0 | T63: =SUM(R63:S63) -> 198.598 | U63: =IFERROR(R63/R$45,"") -> 0.0043714574 | V63: =IFERROR(S63/S$45,"") | W63: =IFERROR(T63/T$45,"") -> 0.0043714574
D64: Yết Kiêu | F64: =YetKieu!F29 -> 10.555 | G64: =YetKieu!G29 -> 19.275 | H64: =YetKieu!H29 -> 24.6 | I64: =YetKieu!I29 -> 19.945 | J64: =YetKieu!J29 -> 34.605 | K64: =YetKieu!K29 -> 38.005 | L64: =YetKieu!L29 -> 40.49 | M64: =YetKieu!M29 -> 36.095 | ... Q64: =YetKieu!Q29 -> 41.888 | R64: =SUMIFS($F64:$Q64,$F$7:$Q$7,"A") -> 378.943 | S64: =SUMIFS($F64:$Q64,$F$7:$Q$7,"B") -> 0 | T64: =SUM(R64:S64) -> 378.943 | U64: =IFERROR(R64/R$45,"") -> 0.0083411373 | V64: =IFERROR(S64/S$45,"") | W64: =IFERROR(T64/T$45,"") -> 0.0083411373
D65: Nha Trang | F65: =NhaTrang!F27 -> 12.09 | G65: =NhaTrang!G27 -> 20.42 | H65: =NhaTrang!H27 -> 27.795 | I65: =NhaTrang!I27 -> 27.56 | J65: =NhaTrang!J27 -> 25.195 | K65: =NhaTrang!K27 -> 30.715 | L65: =NhaTrang!L27 -> 33.265 | M65: =NhaTrang!M27 -> 31.12 | ... Q65: =NhaTrang!Q27 -> 38.09 | R65: =SUMIFS($F65:$Q65,$F$7:$Q$7,"A") -> 373.505 | S65: =SUMIFS($F65:$Q65,$F$7:$Q$7,"B") -> 0 | T65: =SUM(R65:S65) -> 373.505 | U65: =IFERROR(R65/R$45,"") -> 0.0082214383 | V65: =IFERROR(S65/S$45,"") | W65: =IFERROR(T65/T$45,"") -> 0.0082214383
D66: Thạch Thất | F66: =ThachThat!F20 -> 0 | G66: =ThachThat!G20 -> 0 | H66: =ThachThat!H20 -> 0 | I66: =ThachThat!I20 -> 0 | J66: =ThachThat!J20 -> 0 | K66: =ThachThat!K20 -> 0 | L66: =ThachThat!L20 -> 0 | M66: =ThachThat!M20 -> 0 | ... Q66: =ThachThat!Q20 -> 11.845 | R66: =SUMIFS($F66:$Q66,$F$7:$Q$7,"A") -> 94.53 | S66: =SUMIFS($F66:$Q66,$F$7:$Q$7,"B") -> 0 | T66: =SUM(R66:S66) -> 94.53 | U66: =IFERROR(R66/R$45,"") -> 0.0020807555 | V66: =IFERROR(S66/S$45,"") | W66: =IFERROR(T66/T$45,"") -> 0.0020807555
D67: Sóc Sơn | F67: ='SocSon-1'!F27 -> 0 | G67: ='SocSon-1'!G27 -> 0 | H67: ='SocSon-1'!H27 -> 0 | I67: ='SocSon-1'!I27 -> 0 | J67: ='SocSon-1'!J27 -> 0 | K67: ='SocSon-1'!K27 -> 0 | L67: ='SocSon-1'!L27 -> 0 | M67: ='SocSon-1'!M27 -> 0 | ... Q67: ='SocSon-1'!Q27 -> 10.925 | R67: =SUMIFS($F67:$Q67,$F$7:$Q$7,"A") -> 20.01 | S67: =SUMIFS($F67:$Q67,$F$7:$Q$7,"B") -> 0 | T67: =SUM(R67:S67) -> 20.01 | U67: =IFERROR(R67/R$45,"") -> 0.00044045188 | V67: =IFERROR(S67/S$45,"") | W67: =IFERROR(T67/T$45,"") -> 0.00044045188
C68: Tiền thuốc | F68: =SUBTOTAL(9,F69:F77) -> 34.441652 | G68: =SUBTOTAL(9,G69:G77) -> 179.17272 | H68: =SUBTOTAL(9,H69:H77) -> 230.6608 | I68: =SUBTOTAL(9,I69:I77) -> 151.90022 | J68: =SUBTOTAL(9,J69:J77) -> 42.167564 | K68: =SUBTOTAL(9,K69:K77) -> 34.239853 | L68: =SUBTOTAL(9,L69:L77) -> 54.791784 | M68: =SUBTOTAL(9,M69:M77) -> 109.35598 | ... Q68: =SUBTOTAL(9,Q69:Q77) -> 29.402736 | R68: =SUMIFS($F68:$Q68,$F$7:$Q$7,"A") -> 979.35384 | S68: =SUMIFS($F68:$Q68,$F$7:$Q$7,"B") -> 0 | T68: =SUM(R68:S68) -> 979.35384 | U68: =IFERROR(R68/R$45,"") -> 0.021557134 | V68: =IFERROR(S68/S$45,"") | W68: =IFERROR(T68/T$45,"") -> 0.021557134
D69: Hải Dương | F69: =HaiDuong!F59 -> 19.077652 | G69: =HaiDuong!G59 -> 37.56472 | H69: =HaiDuong!H59 -> 33.844803 | I69: =HaiDuong!I59 -> 35.630216 | J69: =HaiDuong!J59 -> 25.877564 | K69: =HaiDuong!K59 -> 14.219853 | L69: =HaiDuong!L59 -> 26.795784 | M69: =HaiDuong!M59 -> 27.845976 | ... Q69: =HaiDuong!Q59 -> 21.862736 | R69: =SUMIFS($F69:$Q69,$F$7:$Q$7,"A") -> 322.55584 | S69: =SUMIFS($F69:$Q69,$F$7:$Q$7,"B") -> 0 | T69: =SUM(R69:S69) -> 322.55584 | U69: =IFERROR(R69/R$45,"") -> 0.0070999664 | V69: =IFERROR(S69/S$45,"") | W69: =IFERROR(T69/T$45,"") -> 0.0070999664
D70: Cà Mau | F70: =CaMau!F29 -> 0 | G70: =CaMau!G29 -> 0 | H70: =CaMau!H29 -> 0 | I70: =CaMau!I29 -> 0 | J70: =CaMau!J29 -> 0 | K70: =CaMau!K29 -> 0 | L70: =CaMau!L29 -> 0 | M70: =CaMau!M29 -> 0 | ... Q70: =CaMau!Q29 -> 0 | R70: =SUMIFS($F70:$Q70,$F$7:$Q$7,"A") -> 0 | S70: =SUMIFS($F70:$Q70,$F$7:$Q$7,"B") -> 0 | T70: =SUM(R70:S70) -> 0 | U70: =IFERROR(R70/R$45,"") -> 0 | V70: =IFERROR(S70/S$45,"") | W70: =IFERROR(T70/T$45,"") -> 0
D71: Thanh Hóa | F71: =ThanhHoa!F28 -> 15.364 | G71: =ThanhHoa!G28 -> 141.608 | H71: =ThanhHoa!H28 -> 196.816 | I71: =ThanhHoa!I28 -> 116.27 | J71: =ThanhHoa!J28 -> 16.29 | K71: =ThanhHoa!K28 -> 20.02 | L71: =ThanhHoa!L28 -> 21.704 | M71: =ThanhHoa!M28 -> 75.218 | ... Q71: =ThanhHoa!Q28 -> 4.108 | R71: =SUMIFS($F71:$Q71,$F$7:$Q$7,"A") -> 623.05 | S71: =SUMIFS($F71:$Q71,$F$7:$Q$7,"B") -> 0 | T71: =SUM(R71:S71) -> 623.05 | U71: =IFERROR(R71/R$45,"") -> 0.01371432 | V71: =IFERROR(S71/S$45,"") | W71: =IFERROR(T71/T$45,"") -> 0.01371432
D72: Thái Nguyên | F72: =ThaiNguyen!F29 -> 0 | G72: =ThaiNguyen!G29 -> 0 | H72: =ThaiNguyen!H29 -> 0 | I72: =ThaiNguyen!I29 -> 0 | J72: =ThaiNguyen!J29 -> 0 | K72: =ThaiNguyen!K29 -> 0 | L72: =ThaiNguyen!L29 -> 6.292 | M72: =ThaiNguyen!M29 -> 6.292 | ... Q72: =ThaiNguyen!Q29 -> 3.432 | R72: =SUMIFS($F72:$Q72,$F$7:$Q$7,"A") -> 33.748 | S72: =SUMIFS($F72:$Q72,$F$7:$Q$7,"B") -> 0 | T72: =SUM(R72:S72) -> 33.748 | U72: =IFERROR(R72/R$45,"") -> 0.00074284709 | V72: =IFERROR(S72/S$45,"") | W72: =IFERROR(T72/T$45,"") -> 0.00074284709
D73: Thái Bình | F73: 0 | G73: =$F73 -> 0 | H73: =$F73 -> 0 | I73: =$F73 -> 0 | J73: =$F73 -> 0 | K73: =$F73 -> 0 | L73: =$F73 -> 0 | M73: =$F73 -> 0 | N73: =$F73 -> 0 | ... Q73: =$F73 -> 0 | R73: =SUMIFS($F73:$Q73,$F$7:$Q$7,"A") -> 0 | S73: =SUMIFS($F73:$Q73,$F$7:$Q$7,"B") -> 0 | T73: =SUM(R73:S73) -> 0 | U73: =IFERROR(R73/R$45,"") -> 0 | V73: =IFERROR(S73/S$45,"") | W73: =IFERROR(T73/T$45,"") -> 0
D74: Yết Kiêu | F74: =0 -> 0 | G74: =$F74 -> 0 | H74: =$F74 -> 0 | I74: =$F74 -> 0 | J74: =$F74 -> 0 | K74: =$F74 -> 0 | L74: =$F74 -> 0 | M74: =$F74 -> 0 | N74: =$F74 -> 0 | ... Q74: =$F74 -> 0 | R74: =SUMIFS($F74:$Q74,$F$7:$Q$7,"A") -> 0 | S74: =SUMIFS($F74:$Q74,$F$7:$Q$7,"B") -> 0 | T74: =SUM(R74:S74) -> 0 | U74: =IFERROR(R74/R$45,"") -> 0 | V74: =IFERROR(S74/S$45,"") | W74: =IFERROR(T74/T$45,"") -> 0
D75: Nha Trang | F75: 0 | G75: =$F75 -> 0 | H75: =$F75 -> 0 | I75: =$F75 -> 0 | J75: =$F75 -> 0 | K75: =$F75 -> 0 | L75: =$F75 -> 0 | M75: =$F75 -> 0 | N75: =$F75 -> 0 | ... Q75: =$F75 -> 0 | R75: =SUMIFS($F75:$Q75,$F$7:$Q$7,"A") -> 0 | S75: =SUMIFS($F75:$Q75,$F$7:$Q$7,"B") -> 0 | T75: =SUM(R75:S75) -> 0 | U75: =IFERROR(R75/R$45,"") -> 0 | V75: =IFERROR(S75/S$45,"") | W75: =IFERROR(T75/T$45,"") -> 0
D76: Thạch Thất | F76: 0 | G76: =$F76 -> 0 | H76: =$F76 -> 0 | I76: =$F76 -> 0 | J76: =$F76 -> 0 | K76: =$F76 -> 0 | L76: =$F76 -> 0 | M76: =$F76 -> 0 | N76: =$F76 -> 0 | ... Q76: =$F76 -> 0 | R76: =SUMIFS($F76:$Q76,$F$7:$Q$7,"A") -> 0 | S76: =SUMIFS($F76:$Q76,$F$7:$Q$7,"B") -> 0 | T76: =SUM(R76:S76) -> 0 | U76: =IFERROR(R76/R$45,"") -> 0 | V76: =IFERROR(S76/S$45,"") | W76: =IFERROR(T76/T$45,"") -> 0
D77: Sóc Sơn | F77: =0 -> 0 | G77: =$F77 -> 0 | H77: =$F77 -> 0 | I77: =$F77 -> 0 | J77: =$F77 -> 0 | K77: =$F77 -> 0 | L77: =$F77 -> 0 | M77: =$F77 -> 0 | N77: =$F77 -> 0 | ... Q77: =$F77 -> 0 | R77: =SUMIFS($F77:$Q77,$F$7:$Q$7,"A") -> 0 | S77: =SUMIFS($F77:$Q77,$F$7:$Q$7,"B") -> 0 | T77: =SUM(R77:S77) -> 0 | U77: =IFERROR(R77/R$45,"") -> 0 | V77: =IFERROR(S77/S$45,"") | W77: =IFERROR(T77/T$45,"") -> 0
C78: Tư vấn chuyên môn | F78: =SUBTOTAL(9,F79:F87) -> 218.66 | G78: =SUBTOTAL(9,G79:G87) -> 419.298 | H78: =SUBTOTAL(9,H79:H87) -> 547.369 | I78: =SUBTOTAL(9,I79:I87) -> 556.412 | J78: =SUBTOTAL(9,J79:J87) -> 499.158 | K78: =SUBTOTAL(9,K79:K87) -> 492.713 | L78: =SUBTOTAL(9,L79:L87) -> 604.548 | M78: =SUBTOTAL(9,M79:M87) -> 597.039 | ... Q78: =SUBTOTAL(9,Q79:Q87) -> 481.752 | R78: =SUMIFS($F78:$Q78,$F$7:$Q$7,"A") -> 5943.604 | S78: =SUMIFS($F78:$Q78,$F$7:$Q$7,"B") -> 0 | T78: =SUM(R78:S78) -> 5943.604 | U78: =IFERROR(R78/R$45,"") -> 0.13082816 | V78: =IFERROR(S78/S$45,"") | W78: =IFERROR(T78/T$45,"") -> 0.13082816
D79: Hải Dương | F79: =HaiDuong!F60 -> 82.3 | G79: =HaiDuong!G60 -> 111.7 | H79: =HaiDuong!H60 -> 138.7 | I79: =HaiDuong!I60 -> 167.4 | J79: =HaiDuong!J60 -> 127 | K79: =HaiDuong!K60 -> 114.2 | L79: =HaiDuong!L60 -> 116.3 | M79: =HaiDuong!M60 -> 99.6 | ... Q79: =HaiDuong!Q60 -> 100.4 | R79: =SUMIFS($F79:$Q79,$F$7:$Q$7,"A") -> 1339.1 | S79: =SUMIFS($F79:$Q79,$F$7:$Q$7,"B") -> 0 | T79: =SUM(R79:S79) -> 1339.1 | U79: =IFERROR(R79/R$45,"") -> 0.029475718 | V79: =IFERROR(S79/S$45,"") | W79: =IFERROR(T79/T$45,"") -> 0.029475718
D80: Cà Mau | F80: =CaMau!F30 -> 31.3 | G80: =CaMau!G30 -> 55.9 | H80: =CaMau!H30 -> 69.9 | I80: =CaMau!I30 -> 82.7 | J80: =CaMau!J30 -> 76 | K80: =CaMau!K30 -> 75.35 | L80: =CaMau!L30 -> 64.94 | M80: =CaMau!M30 -> 69.93 | ... Q80: =CaMau!Q30 -> 52.35 | R80: =SUMIFS($F80:$Q80,$F$7:$Q$7,"A") -> 787.15 | S80: =SUMIFS($F80:$Q80,$F$7:$Q$7,"B") -> 0 | T80: =SUM(R80:S80) -> 787.15 | U80: =IFERROR(R80/R$45,"") -> 0.017326422 | V80: =IFERROR(S80/S$45,"") | W80: =IFERROR(T80/T$45,"") -> 0.017326422
D81: Thanh Hóa | F81: =ThanhHoa!F29 -> 34.8 | G81: =ThanhHoa!G29 -> 142.3 | H81: =ThanhHoa!H29 -> 193.4 | I81: =ThanhHoa!I29 -> 165.01 | J81: =ThanhHoa!J29 -> 123.725 | K81: =ThanhHoa!K29 -> 71.17 | L81: =ThanhHoa!L29 -> 112.58 | M81: =ThanhHoa!M29 -> 90.6 | ... Q81: =ThanhHoa!Q29 -> 27.5 | R81: =SUMIFS($F81:$Q81,$F$7:$Q$7,"A") -> 1112.695 | S81: =SUMIFS($F81:$Q81,$F$7:$Q$7,"B") -> 0 | T81: =SUM(R81:S81) -> 1112.695 | U81: =IFERROR(R81/R$45,"") -> 0.024492184 | V81: =IFERROR(S81/S$45,"") | W81: =IFERROR(T81/T$45,"") -> 0.024492184
D82: Thái Nguyên | F82: =ThaiNguyen!F30 -> 12.6 | G82: =ThaiNguyen!G30 -> 19.95 | H82: =ThaiNguyen!H30 -> 32.2 | I82: =ThaiNguyen!I30 -> 26.85 | J82: =ThaiNguyen!J30 -> 32.65 | K82: =ThaiNguyen!K30 -> 35.95 | L82: =ThaiNguyen!L30 -> 41 | M82: =ThaiNguyen!M30 -> 50.1 | ... Q82: =ThaiNguyen!Q30 -> 61.85 | R82: =SUMIFS($F82:$Q82,$F$7:$Q$7,"A") -> 466.4 | S82: =SUMIFS($F82:$Q82,$F$7:$Q$7,"B") -> 0 | T82: =SUM(R82:S82) -> 466.4 | U82: =IFERROR(R82/R$45,"") -> 0.010266205 | V82: =IFERROR(S82/S$45,"") | W82: =IFERROR(T82/T$45,"") -> 0.010266205
D83: Thái Bình | F83: =ThaiBinh!F24 -> 0 | G83: =ThaiBinh!G24 -> 0 | H83: =ThaiBinh!H24 -> 0 | I83: =ThaiBinh!I24 -> 0 | J83: =ThaiBinh!J24 -> 0 | K83: =ThaiBinh!K24 -> 16.75 | L83: =ThaiBinh!L24 -> 60 | M83: =ThaiBinh!M24 -> 85.75 | ... Q83: =ThaiBinh!Q24 -> 31.75 | R83: =SUMIFS($F83:$Q83,$F$7:$Q$7,"A") -> 306.5 | S83: =SUMIFS($F83:$Q83,$F$7:$Q$7,"B") -> 0 | T83: =SUM(R83:S83) -> 306.5 | U83: =IFERROR(R83/R$45,"") -> 0.0067465518 | V83: =IFERROR(S83/S$45,"") | W83: =IFERROR(T83/T$45,"") -> 0.0067465518
D84: Yết Kiêu | F84: =YetKieu!F31 -> 24.27 | G84: =YetKieu!G31 -> 34.448 | H84: =YetKieu!H31 -> 41.804 | I84: =YetKieu!I31 -> 41.392 | J84: =YetKieu!J31 -> 74.418 | K84: =YetKieu!K31 -> 95.498 | L84: =YetKieu!L31 -> 121.928 | M84: =YetKieu!M31 -> 111.934 | ... Q84: =YetKieu!Q31 -> 88.832 | R84: =SUMIFS($F84:$Q84,$F$7:$Q$7,"A") -> 898.654 | S84: =SUMIFS($F84:$Q84,$F$7:$Q$7,"B") -> 0 | T84: =SUM(R84:S84) -> 898.654 | U84: =IFERROR(R84/R$45,"") -> 0.019780802 | V84: =IFERROR(S84/S$45,"") | W84: =IFERROR(T84/T$45,"") -> 0.019780802
D85: Nha Trang | F85: =NhaTrang!F26 -> 33.39 | G85: =NhaTrang!G26 -> 55 | H85: =NhaTrang!H26 -> 71.365 | I85: =NhaTrang!I26 -> 73.06 | J85: =NhaTrang!J26 -> 65.365 | K85: =NhaTrang!K26 -> 83.795 | L85: =NhaTrang!L26 -> 87.8 | M85: =NhaTrang!M26 -> 89.125 | ... Q85: =NhaTrang!Q26 -> 93.92 | R85: =SUMIFS($F85:$Q85,$F$7:$Q$7,"A") -> 911.875 | S85: =SUMIFS($F85:$Q85,$F$7:$Q$7,"B") -> 0 | T85: =SUM(R85:S85) -> 911.875 | U85: =IFERROR(R85/R$45,"") -> 0.020071817 | V85: =IFERROR(S85/S$45,"") | W85: =IFERROR(T85/T$45,"") -> 0.020071817
D86: Thạch Thất | F86: =ThachThat!F19 -> 0 | G86: =ThachThat!G19 -> 0 | H86: =ThachThat!H19 -> 0 | I86: =ThachThat!I19 -> 0 | J86: =ThachThat!J19 -> 0 | K86: =ThachThat!K19 -> 0 | L86: =ThachThat!L19 -> 0 | M86: =ThachThat!M19 -> 0 | ... Q86: =ThachThat!Q19 -> 14.55 | R86: =SUMIFS($F86:$Q86,$F$7:$Q$7,"A") -> 103 | S86: =SUMIFS($F86:$Q86,$F$7:$Q$7,"B") -> 0 | T86: =SUM(R86:S86) -> 103 | U86: =IFERROR(R86/R$45,"") -> 0.0022671936 | V86: =IFERROR(S86/S$45,"") | W86: =IFERROR(T86/T$45,"") -> 0.0022671936
D87: Sóc Sơn | F87: ='SocSon-1'!F29 -> 0 | G87: ='SocSon-1'!G29 -> 0 | H87: ='SocSon-1'!H29 -> 0 | I87: ='SocSon-1'!I29 -> 0 | J87: ='SocSon-1'!J29 -> 0 | K87: ='SocSon-1'!K29 -> 0 | L87: ='SocSon-1'!L29 -> 0 | M87: ='SocSon-1'!M29 -> 0 | ... Q87: ='SocSon-1'!Q29 -> 10.6 | R87: =SUMIFS($F87:$Q87,$F$7:$Q$7,"A") -> 18.23 | S87: =SUMIFS($F87:$Q87,$F$7:$Q$7,"B") -> 0 | T87: =SUM(R87:S87) -> 18.23 | U87: =IFERROR(R87/R$45,"") -> 0.00040127126 | V87: =IFERROR(S87/S$45,"") | W87: =IFERROR(T87/T$45,"") -> 0.00040127126
C88: Hoa hồng nhân viên | F88: =SUBTOTAL(9,F89:F97) -> #REF! | G88: =SUBTOTAL(9,G89:G97) -> 33.9709 | H88: =SUBTOTAL(9,H89:H97) -> 68.3225 | I88: =SUBTOTAL(9,I89:I97) -> 89.821265 | J88: =SUBTOTAL(9,J89:J97) -> 61.647415 | K88: =SUBTOTAL(9,K89:K97) -> 169.1476 | L88: =SUBTOTAL(9,L89:L97) -> 117.3903 | M88: =SUBTOTAL(9,M89:M97) -> 75.444 | ... Q88: =SUBTOTAL(9,Q89:Q97) -> 72.0643 | R88: =SUMIFS($F88:$Q88,$F$7:$Q$7,"A") -> #REF! | S88: =SUMIFS($F88:$Q88,$F$7:$Q$7,"B") -> 0 | T88: =SUM(R88:S88) -> #REF! | U88: =IFERROR(R88/R$45,"") | V88: =IFERROR(S88/S$45,"") | W88: =IFERROR(T88/T$45,"")
D89: Hải Dương | F89: =HaiDuong!F61 -> 12.5 | G89: =HaiDuong!G61 -> 19.07 | H89: =HaiDuong!H61 -> 29.2575 | I89: =HaiDuong!I61 -> 36.6225 | J89: =HaiDuong!J61 -> 28.85 | K89: =HaiDuong!K61 -> 25.795 | L89: =HaiDuong!L61 -> 25.635 | M89: =HaiDuong!M61 -> 19.815 | ... Q89: =HaiDuong!Q61 -> 21.0675 | R89: =SUMIFS($F89:$Q89,$F$7:$Q$7,"A") -> 278.42 | S89: =SUMIFS($F89:$Q89,$F$7:$Q$7,"B") -> 0 | T89: =SUM(R89:S89) -> 278.42 | U89: =IFERROR(R89/R$45,"") -> 0.0061284664 | V89: =IFERROR(S89/S$45,"") | W89: =IFERROR(T89/T$45,"") -> 0.0061284664
D90: Cà Mau | F90: =CaMau!F31 -> 0 | G90: =CaMau!G31 -> 0 | H90: =CaMau!H31 -> 0 | I90: =CaMau!I31 -> 0 | J90: =CaMau!J31 -> 0 | K90: =CaMau!K31 -> 0 | L90: =CaMau!L31 -> 0 | M90: =CaMau!M31 -> 0 | ... Q90: =CaMau!Q31 -> 0 | R90: =SUMIFS($F90:$Q90,$F$7:$Q$7,"A") -> 0 | S90: =SUMIFS($F90:$Q90,$F$7:$Q$7,"B") -> 0 | T90: =SUM(R90:S90) -> 0 | U90: =IFERROR(R90/R$45,"") -> 0 | V90: =IFERROR(S90/S$45,"") | W90: =IFERROR(T90/T$45,"") -> 0
D91: Thanh Hóa | F91: =ThanhHoa!F30 -> 4.34 | G91: =ThanhHoa!G30 -> 8.16 | H91: =ThanhHoa!H30 -> 20.48 | I91: =ThanhHoa!I30 -> 39.9644 | J91: =ThanhHoa!J30 -> 16.49 | K91: =ThanhHoa!K30 -> 113.316 | L91: =ThanhHoa!L30 -> 53 | M91: =ThanhHoa!M30 -> 17.66 | ... Q91: =ThanhHoa!Q30 -> 4.08 | R91: =SUMIFS($F91:$Q91,$F$7:$Q$7,"A") -> 331.4264 | S91: =SUMIFS($F91:$Q91,$F$7:$Q$7,"B") -> 0 | T91: =SUM(R91:S91) -> 331.4264 | U91: =IFERROR(R91/R$45,"") -> 0.0072952215 | V91: =IFERROR(S91/S$45,"") | W91: =IFERROR(T91/T$45,"") -> 0.0072952215
D92: Thái Nguyên | F92: =ThaiNguyen!F31 -> 0 | G92: =ThaiNguyen!G31 -> 0 | H92: =ThaiNguyen!H31 -> 4.44 | I92: =ThaiNguyen!I31 -> 3.7 | J92: =ThaiNguyen!J31 -> 4.58 | K92: =ThaiNguyen!K31 -> 5.16 | L92: =ThaiNguyen!L31 -> 6.28 | M92: =ThaiNguyen!M31 -> 7.6 | ... Q92: =ThaiNguyen!Q31 -> 12.29 | R92: =SUMIFS($F92:$Q92,$F$7:$Q$7,"A") -> 73.93 | S92: =SUMIFS($F92:$Q92,$F$7:$Q$7,"B") -> 0 | T92: =SUM(R92:S92) -> 73.93 | U92: =IFERROR(R92/R$45,"") -> 0.0016273167 | V92: =IFERROR(S92/S$45,"") | W92: =IFERROR(T92/T$45,"") -> 0.0016273167
D93: Thái Bình | F93: =ThaiBinh!F25 -> 0 | G93: =ThaiBinh!G25 -> 0 | H93: =ThaiBinh!H25 -> 0 | I93: =ThaiBinh!I25 -> 0 | J93: =ThaiBinh!J25 -> 0 | K93: =ThaiBinh!K25 -> 0 | L93: =ThaiBinh!L25 -> 0 | M93: =ThaiBinh!M25 -> 0 | ... Q93: =ThaiBinh!Q25 -> 6 | R93: =SUMIFS($F93:$Q93,$F$7:$Q$7,"A") -> 12.04 | S93: =SUMIFS($F93:$Q93,$F$7:$Q$7,"B") -> 0 | T93: =SUM(R93:S93) -> 12.04 | U93: =IFERROR(R93/R$45,"") -> 0.00026501952 | V93: =IFERROR(S93/S$45,"") | W93: =IFERROR(T93/T$45,"") -> 0.00026501952
D94: Yết Kiêu | F94: =YetKieu!F32 -> 10.861699 | G94: =YetKieu!G32 -> 1.3856 | H94: =YetKieu!H32 -> 14.145 | I94: =YetKieu!I32 -> 1.738665 | J94: =YetKieu!J32 -> 2.725415 | K94: =YetKieu!K32 -> 16.1 | L94: =YetKieu!L32 -> 22.427 | M94: =YetKieu!M32 -> 21.275 | ... Q94: =YetKieu!Q32 -> 19.068 | R94: =SUMIFS($F94:$Q94,$F$7:$Q$7,"A") -> 179.88638 | S94: =SUMIFS($F94:$Q94,$F$7:$Q$7,"B") -> 0 | T94: =SUM(R94:S94) -> 179.88638 | U94: =IFERROR(R94/R$45,"") -> 0.0039595849 | V94: =IFERROR(S94/S$45,"") | W94: =IFERROR(T94/T$45,"") -> 0.0039595849
D95: Nha Trang | F95: =NhaTrang!F25 -> 12.4721 | G95: =NhaTrang!G25 -> 5.3553 | H95: =NhaTrang!H25 -> 0 | I95: =NhaTrang!I25 -> 7.7957 | J95: =NhaTrang!J25 -> 9.002 | K95: =NhaTrang!K25 -> 8.7766 | L95: =NhaTrang!L25 -> 10.0483 | M95: =NhaTrang!M25 -> 9.094 | ... Q95: =NhaTrang!Q25 -> 9.5588 | R95: =SUMIFS($F95:$Q95,$F$7:$Q$7,"A") -> 90.2997 | S95: =SUMIFS($F95:$Q95,$F$7:$Q$7,"B") -> 0 | T95: =SUM(R95:S95) -> 90.2997 | U95: =IFERROR(R95/R$45,"") -> 0.0019876398 | V95: =IFERROR(S95/S$45,"") | W95: =IFERROR(T95/T$45,"") -> 0.0019876398
D96: Thạch Thất | F96: =ThachThat!F18 -> 0 | G96: =ThachThat!G18 -> 0 | H96: =ThachThat!H18 -> 0 | I96: =ThachThat!I18 -> 0 | J96: =ThachThat!J18 -> 0 | K96: =ThachThat!K18 -> 0 | L96: =ThachThat!L18 -> 0 | M96: =ThachThat!M18 -> 0 | ... Q96: =ThachThat!Q18 -> 0 | R96: =SUMIFS($F96:$Q96,$F$7:$Q$7,"A") -> 0 | S96: =SUMIFS($F96:$Q96,$F$7:$Q$7,"B") -> 0 | T96: =SUM(R96:S96) -> 0 | U96: =IFERROR(R96/R$45,"") -> 0 | V96: =IFERROR(S96/S$45,"") | W96: =IFERROR(T96/T$45,"") -> 0
D97: Sóc Sơn | F97: ='SocSon-1'!#REF! -> #REF! | G97: ='SocSon-1'!F30 -> 0 | H97: ='SocSon-1'!G30 -> 0 | I97: ='SocSon-1'!H30 -> 0 | J97: ='SocSon-1'!I30 -> 0 | K97: ='SocSon-1'!J30 -> 0 | L97: ='SocSon-1'!K30 -> 0 | M97: ='SocSon-1'!L30 -> 0 | N97: ='SocSon-1'!M30 -> 0 | ... Q97: ='SocSon-1'!P30 -> 0 | R97: =SUMIFS($F97:$Q97,$F$7:$Q$7,"A") -> #REF! | S97: =SUMIFS($F97:$Q97,$F$7:$Q$7,"B") -> 0 | T97: =SUM(R97:S97) -> #REF! | U97: =IFERROR(R97/R$45,"") | V97: =IFERROR(S97/S$45,"") | W97: =IFERROR(T97/T$45,"")
C98: Truyền thông marketing | F98: =SUBTOTAL(9,F99:F107) -> 43.883202 | G98: =SUBTOTAL(9,G99:G107) -> 18.438282 | H98: =SUBTOTAL(9,H99:H107) -> 13.486756 | I98: =SUBTOTAL(9,I99:I107) -> 16.975611 | J98: =SUBTOTAL(9,J99:J107) -> 11.933333 | K98: =SUBTOTAL(9,K99:K107) -> 1.433334 | L98: =SUBTOTAL(9,L99:L107) -> 5.784817 | M98: =SUBTOTAL(9,M99:M107) -> 39.56266 | ... Q98: =SUBTOTAL(9,Q99:Q107) -> 11.966 | R98: =SUMIFS($F98:$Q98,$F$7:$Q$7,"A") -> 345.00414 | S98: =SUMIFS($F98:$Q98,$F$7:$Q$7,"B") -> 0 | T98: =SUM(R98:S98) -> 345.00414 | U98: =IFERROR(R98/R$45,"") -> 0.0075940892 | V98: =IFERROR(S98/S$45,"") | W98: =IFERROR(T98/T$45,"") -> 0.0075940892
D99: Hải Dương | F99: =HaiDuong!F62 -> 24.85732 | G99: =HaiDuong!G62 -> 3.35 | H99: =HaiDuong!H62 -> 0.2592 | I99: =HaiDuong!I62 -> 0 | J99: =HaiDuong!J62 -> 0 | K99: =HaiDuong!K62 -> 0 | L99: =HaiDuong!L62 -> 1.048817 | M99: =HaiDuong!M62 -> 9.07128 | ... Q99: =HaiDuong!Q62 -> 0 | R99: =SUMIFS($F99:$Q99,$F$7:$Q$7,"A") -> 78.673914 | S99: =SUMIFS($F99:$Q99,$F$7:$Q$7,"B") -> 0 | T99: =SUM(R99:S99) -> 78.673914 | U99: =IFERROR(R99/R$45,"") -> 0.0017317378 | V99: =IFERROR(S99/S$45,"") | W99: =IFERROR(T99/T$45,"") -> 0.0017317378
D100: Cà Mau | F100: =CaMau!F32 -> 0 | G100: =CaMau!G32 -> 0 | H100: =CaMau!H32 -> 0 | I100: =CaMau!I32 -> 0 | J100: =CaMau!J32 -> 0 | K100: =CaMau!K32 -> 0 | L100: =CaMau!L32 -> 0 | M100: =CaMau!M32 -> 0 | ... Q100: =CaMau!Q32 -> 0 | R100: =SUMIFS($F100:$Q100,$F$7:$Q$7,"A") -> 0 | S100: =SUMIFS($F100:$Q100,$F$7:$Q$7,"B") -> 0 | T100: =SUM(R100:S100) -> 0 | U100: =IFERROR(R100/R$45,"") -> 0 | V100: =IFERROR(S100/S$45,"") | W100: =IFERROR(T100/T$45,"") -> 0
D101: Thanh Hóa | F101: =ThanhHoa!F31 -> 17.886282 | G101: =ThanhHoa!G31 -> 14.938282 | H101: =ThanhHoa!H31 -> 13.227556 | I101: =ThanhHoa!I31 -> 12.788278 | J101: =ThanhHoa!J31 -> 0 | K101: =ThanhHoa!K31 -> 0 | L101: =ThanhHoa!L31 -> 2.9 | M101: =ThanhHoa!M31 -> 2.1 | ... Q101: =ThanhHoa!Q31 -> 7.836 | R101: =SUMIFS($F101:$Q101,$F$7:$Q$7,"A") -> 92.671215 | S101: =SUMIFS($F101:$Q101,$F$7:$Q$7,"B") -> 0 | T101: =SUM(R101:S101) -> 92.671215 | U101: =IFERROR(R101/R$45,"") -> 0.0020398406 | V101: =IFERROR(S101/S$45,"") | W101: =IFERROR(T101/T$45,"") -> 0.0020398406
D102: Thái Nguyên | F102: =ThaiNguyen!F32 -> 1.1396 | G102: =ThaiNguyen!G32 -> 0.15 | H102: =ThaiNguyen!H32 -> 0 | I102: =ThaiNguyen!I32 -> 4.187333 | J102: =ThaiNguyen!J32 -> 11.933333 | K102: =ThaiNguyen!K32 -> 1.433334 | L102: =ThaiNguyen!L32 -> 1.836 | M102: =ThaiNguyen!M32 -> 28.39138 | ... Q102: =ThaiNguyen!Q32 -> 2.25 | R102: =SUMIFS($F102:$Q102,$F$7:$Q$7,"A") -> 97.429016 | S102: =SUMIFS($F102:$Q102,$F$7:$Q$7,"B") -> 0 | T102: =SUM(R102:S102) -> 97.429016 | U102: =IFERROR(R102/R$45,"") -> 0.0021445674 | V102: =IFERROR(S102/S$45,"") | W102: =IFERROR(T102/T$45,"") -> 0.0021445674
D103: Thái Bình | F103: =0 -> 0 | G103: =0 -> 0 | H103: =0 -> 0 | I103: =0 -> 0 | J103: =0 -> 0 | K103: =0 -> 0 | L103: =0 -> 0 | M103: =0 -> 0 | ... Q103: =0 -> 0 | R103: =SUMIFS($F103:$Q103,$F$7:$Q$7,"A") -> 0 | S103: =SUMIFS($F103:$Q103,$F$7:$Q$7,"B") -> 0 | T103: =SUM(R103:S103) -> 0 | U103: =IFERROR(R103/R$45,"") -> 0 | V103: =IFERROR(S103/S$45,"") | W103: =IFERROR(T103/T$45,"") -> 0
D104: Yết Kiêu | F104: =0 -> 0 | G104: =0 -> 0 | H104: =0 -> 0 | I104: =0 -> 0 | J104: =0 -> 0 | K104: =0 -> 0 | L104: =0 -> 0 | M104: =0 -> 0 | ... Q104: =0 -> 0 | R104: =SUMIFS($F104:$Q104,$F$7:$Q$7,"A") -> 0 | S104: =SUMIFS($F104:$Q104,$F$7:$Q$7,"B") -> 0 | T104: =SUM(R104:S104) -> 0 | U104: =IFERROR(R104/R$45,"") -> 0 | V104: =IFERROR(S104/S$45,"") | W104: =IFERROR(T104/T$45,"") -> 0
D105: Nha Trang | F105: =0 -> 0 | G105: =0 -> 0 | H105: =0 -> 0 | I105: =0 -> 0 | J105: =0 -> 0 | K105: =0 -> 0 | L105: =0 -> 0 | M105: =0 -> 0 | ... Q105: =0 -> 0 | R105: =SUMIFS($F105:$Q105,$F$7:$Q$7,"A") -> 0 | S105: =SUMIFS($F105:$Q105,$F$7:$Q$7,"B") -> 0 | T105: =SUM(R105:S105) -> 0 | U105: =IFERROR(R105/R$45,"") -> 0 | V105: =IFERROR(S105/S$45,"") | W105: =IFERROR(T105/T$45,"") -> 0
D106: Thạch Thất | F106: =0 -> 0 | G106: =0 -> 0 | H106: =0 -> 0 | I106: =0 -> 0 | J106: =0 -> 0 | K106: =0 -> 0 | L106: =0 -> 0 | M106: =0 -> 0 | ... Q106: =0 -> 0 | R106: =SUMIFS($F106:$Q106,$F$7:$Q$7,"A") -> 0 | S106: =SUMIFS($F106:$Q106,$F$7:$Q$7,"B") -> 0 | T106: =SUM(R106:S106) -> 0 | U106: =IFERROR(R106/R$45,"") -> 0 | V106: =IFERROR(S106/S$45,"") | W106: =IFERROR(T106/T$45,"") -> 0
...

Sheet Conso BS
B5: BÁO CÁO TÌNH HÌNH TÀI CHÍNH HỢP NHẤT
B6: Tại | C6: 31.12.2025
E8: Cuối tháng
B9: VND triệu | E9: 1 | F9: 2 | G9: 3 | H9: 4 | I9: 5 | J9: 6 | K9: 7 | L9: 8 | M9: 9 | N9: 10 | O9: 11 | P9: 12
C10: Tài sản ngắn hạn
D11: Tiền và tương đương tiền
D12: Phải thu khách hàng | E12: =SUBTOTAL(9,E13:E14) -> 0 | F12: =SUBTOTAL(9,F13:F14) -> 0 | G12: =SUBTOTAL(9,G13:G14) -> 0 | H12: =SUBTOTAL(9,H13:H14) -> 0 | I12: =SUBTOTAL(9,I13:I14) -> 0 | J12: =SUBTOTAL(9,J13:J14) -> 0 | K12: =SUBTOTAL(9,K13:K14) -> 0 | L12: =SUBTOTAL(9,L13:L14) -> 0 | ... P12: =SUBTOTAL(9,P13:P14) -> 0
D13: Trong hạn thanh toán
D14: Quá hạn thanh toán
D15: Ứng trước cho nhà cung cấp
D16: Chi phí chờ phân bổ
D17: Thuế GTGT được khấu trừ
C18: Tổng tài sản ngắn hạn | E18: =SUBTOTAL(9,E11:E17) -> 0 | F18: =SUBTOTAL(9,F11:F17) -> 0 | G18: =SUBTOTAL(9,G11:G17) -> 0 | H18: =SUBTOTAL(9,H11:H17) -> 0 | I18: =SUBTOTAL(9,I11:I17) -> 0 | J18: =SUBTOTAL(9,J11:J17) -> 0 | K18: =SUBTOTAL(9,K11:K17) -> 0 | L18: =SUBTOTAL(9,L11:L17) -> 0 | ... P18: =SUBTOTAL(9,P11:P17) -> 0
C19: Tài sản dài hạn
D20: Tài sản cố định
D21: Chi phí chờ phân bổ
C22: Tổng tài sản dài hạn | E22: =SUBTOTAL(9,E20:E21) -> 0 | F22: =SUBTOTAL(9,F20:F21) -> 0 | G22: =SUBTOTAL(9,G20:G21) -> 0 | H22: =SUBTOTAL(9,H20:H21) -> 0 | I22: =SUBTOTAL(9,I20:I21) -> 0 | J22: =SUBTOTAL(9,J20:J21) -> 0 | K22: =SUBTOTAL(9,K20:K21) -> 0 | L22: =SUBTOTAL(9,L20:L21) -> 0 | ... P22: =SUBTOTAL(9,P20:P21) -> 0
B23: TỔNG TÀI SẢN | E23: =SUBTOTAL(9,E11:E22) -> 0 | F23: =SUBTOTAL(9,F11:F22) -> 0 | G23: =SUBTOTAL(9,G11:G22) -> 0 | H23: =SUBTOTAL(9,H11:H22) -> 0 | I23: =SUBTOTAL(9,I11:I22) -> 0 | J23: =SUBTOTAL(9,J11:J22) -> 0 | K23: =SUBTOTAL(9,K11:K22) -> 0 | L23: =SUBTOTAL(9,L11:L22) -> 0 | ... P23: =SUBTOTAL(9,P11:P22) -> 0
C24: Nợ ngắn hạn
D25: Phải trả nhà cung cấp | E25: =SUBTOTAL(9,E26:E27) -> 0 | F25: =SUBTOTAL(9,F26:F27) -> 0 | G25: =SUBTOTAL(9,G26:G27) -> 0 | H25: =SUBTOTAL(9,H26:H27) -> 0 | I25: =SUBTOTAL(9,I26:I27) -> 0 | J25: =SUBTOTAL(9,J26:J27) -> 0 | K25: =SUBTOTAL(9,K26:K27) -> 0 | L25: =SUBTOTAL(9,L26:L27) -> 0 | ... P25: =SUBTOTAL(9,P26:P27) -> 0
D26: Trong hạn thanh toán
D27: Quá hạn thanh toán
D28: Thuế GTGT & thuế khác phải trả
D29: Phải trả khác
D30: Vay và nợ ngắn hạn
C31: Tổng nợ ngắn hạn | E31: =SUBTOTAL(9,E25:E30) -> 0 | F31: =SUBTOTAL(9,F25:F30) -> 0 | G31: =SUBTOTAL(9,G25:G30) -> 0 | H31: =SUBTOTAL(9,H25:H30) -> 0 | I31: =SUBTOTAL(9,I25:I30) -> 0 | J31: =SUBTOTAL(9,J25:J30) -> 0 | K31: =SUBTOTAL(9,K25:K30) -> 0 | L31: =SUBTOTAL(9,L25:L30) -> 0 | ... P31: =SUBTOTAL(9,P25:P30) -> 0
C32: Nợ dài hạn
D33: Vay và nợ dài hạn
C34: Tổng nợ dài hạn | E34: =SUBTOTAL(9,E33) -> 0 | F34: =SUBTOTAL(9,F33) -> 0 | G34: =SUBTOTAL(9,G33) -> 0 | H34: =SUBTOTAL(9,H33) -> 0 | I34: =SUBTOTAL(9,I33) -> 0 | J34: =SUBTOTAL(9,J33) -> 0 | K34: =SUBTOTAL(9,K33) -> 0 | L34: =SUBTOTAL(9,L33) -> 0 | ... P34: =SUBTOTAL(9,P33) -> 0
B35: TỔNG NỢ | E35: =SUBTOTAL(9,E25:E34) -> 0 | F35: =SUBTOTAL(9,F25:F34) -> 0 | G35: =SUBTOTAL(9,G25:G34) -> 0 | H35: =SUBTOTAL(9,H25:H34) -> 0 | I35: =SUBTOTAL(9,I25:I34) -> 0 | J35: =SUBTOTAL(9,J25:J34) -> 0 | K35: =SUBTOTAL(9,K25:K34) -> 0 | L35: =SUBTOTAL(9,L25:L34) -> 0 | ... P35: =SUBTOTAL(9,P25:P34) -> 0
C36: Vốn chủ sở hữu
C37: Thặng dư vốn góp
C38: Lợi nhuận giữ lại | E38: =SUBTOTAL(9,E39:E40) -> 0 | F38: =SUBTOTAL(9,F39:F40) -> 0 | G38: =SUBTOTAL(9,G39:G40) -> 0 | H38: =SUBTOTAL(9,H39:H40) -> 0 | I38: =SUBTOTAL(9,I39:I40) -> 0 | J38: =SUBTOTAL(9,J39:J40) -> 0 | K38: =SUBTOTAL(9,K39:K40) -> 0 | L38: =SUBTOTAL(9,L39:L40) -> 0 | ... P38: =SUBTOTAL(9,P39:P40) -> 0
D39: Lợi nhuận giữ lại các năm trước
D40: Lợi nhuận giữ lại năm hiện tại
B41: TỔNG VỐN CHỦ SỞ HỮU | E41: =SUBTOTAL(9,E36:E40) -> 0 | F41: =SUBTOTAL(9,F36:F40) -> 0 | G41: =SUBTOTAL(9,G36:G40) -> 0 | H41: =SUBTOTAL(9,H36:H40) -> 0 | I41: =SUBTOTAL(9,I36:I40) -> 0 | J41: =SUBTOTAL(9,J36:J40) -> 0 | K41: =SUBTOTAL(9,K36:K40) -> 0 | L41: =SUBTOTAL(9,L36:L40) -> 0 | ... P41: =SUBTOTAL(9,P36:P40) -> 0
B42: TỔNG NGUỒN VỐN | E42: =E41+E35 -> 0 | F42: =F41+F35 -> 0 | G42: =G41+G35 -> 0 | H42: =H41+H35 -> 0 | I42: =I41+I35 -> 0 | J42: =J41+J35 -> 0 | K42: =K41+K35 -> 0 | L42: =L41+L35 -> 0 | ... P42: =P41+P35 -> 0
E43: =E23-E42 -> 0 | F43: =F23-F42 -> 0 | G43: =G23-G42 -> 0 | H43: =H23-H42 -> 0 | I43: =I23-I42 -> 0 | J43: =J23-J42 -> 0 | K43: =K23-K42 -> 0 | L43: =L23-L42 -> 0 | ... P43: =P23-P42 -> 0

Sheet HaiDuong
B6: BÁO CÁO KẾT QUẢ HOẠT ĐỘNG KINH DOANH CHI NHÁNH
B7: HẢI DƯƠNG | F7: A | G7: A | H7: A | I7: A | J7: A | K7: A | L7: A | M7: A | N7: A | O7: A | P7: A | Q7: A
B8: Năm tài chính 2025 | F8: Tháng | R8: ------------------Tổng-------------------- | U8: ------%Doanh thu------- | X8: ------------vs-------------- | Z8: ----------------Forecast--------------------
B9: VND triệu | F9: 1 | G9: 2 | H9: 3 | I9: 4 | J9: 5 | K9: 6 | L9: 7 | M9: 8 | N9: 9 | O9: 10 | P9: 11 | Q9: 12 | R9: Year to date | S9: Year to go | T9: LATEST ESTIMATE | U9: YTD | V9: YTG | W9: LE | X9: Last month | Y9: Last year | Z9: Assumption | AA9: Note | AB9: 2026F
B11: Đơn giá bán trung bình
E12: MRI | F12: =F42*10^6/F18 -> 1869260.7 | G12: =G42*10^6/G18 -> 1906965.2 | H12: =H42*10^6/H18 -> 1878260.9 | I12: =I42*10^6/I18 -> 1863197 | J12: =J42*10^6/J18 -> 1858315.3 | K12: =K42*10^6/K18 -> 1834324.9 | L12: =L42*10^6/L18 -> 1882405.3 | M12: =M42*10^6/M18 -> 1889385.5 | ... P12: =P42*10^6/P18 -> 1913761.5 | Q12: 1827593.6 | T12: =T42*10^6/T18 -> 1876497.6 | AB12: =T12 -> 1876497.6
E13: Mammo X-Quang | F13: =F43*10^6/F19 -> 571428.57 | G13: =G43*10^6/G19 -> 593750 | H13: =H43*10^6/H19 -> 500000 | I13: =I43*10^6/I19 -> 554054.05 | J13: =J43*10^6/J19 -> 500000 | K13: =K43*10^6/K19 -> 600000 | L13: =L43*10^6/L19 -> 500000 | M13: =M43*10^6/M19 -> 500000 | ... P13: =P43*10^6/P19 -> 500000 | Q13: 500000 | T13: =T43*10^6/T19 -> 524472.57 | AB13: =T13 -> 524472.57
E14: CT | F14: =F44*10^6/F20 -> 1164814.8 | G14: =G44*10^6/G20 -> 1195804.2 | H14: =H44*10^6/H20 -> 1201807.2 | I14: =I44*10^6/I20 -> 1191542.3 | J14: =J44*10^6/J20 -> 1160447.8 | K14: =K44*10^6/K20 -> 1117924.5 | L14: =L44*10^6/L20 -> 1166666.7 | M14: =M44*10^6/M20 -> 1223684.2 | ... P14: =P44*10^6/P20 -> 1286747 | Q14: 1224770.6 | T14: =T44*10^6/T20 -> 1189934.8 | AB14: =T14 -> 1189934.8
E15: X-Quang | F15: =F45*10^6/F21 -> 143965.52 | G15: =G45*10^6/G21 -> 132530.12 | H15: =H45*10^6/H21 -> 160544.22 | I15: =I45*10^6/I21 -> 134868.42 | J15: =J45*10^6/J21 -> 137500 | K15: =K45*10^6/K21 -> 133776.6 | L15: =L45*10^6/L21 -> 154433.5 | M15: =M45*10^6/M21 -> 153225.81 | ... P15: =P45*10^6/P21 -> 148395.72 | Q15: 150000 | T15: =T45*10^6/T21 -> 148296.06 | AB15: =T15 -> 148296.06
E16: Siêu âm | F16: =F46*10^6/F22 -> 138888.89 | G16: =G46*10^6/G22 -> 154166.67 | H16: =H46*10^6/H22 -> 158208.96 | I16: =I46*10^6/I22 -> 158771.93 | J16: =J46*10^6/J22 -> 170238.1 | K16: =K46*10^6/K22 -> 172368.42 | L16: =L46*10^6/L22 -> 163529.41 | M16: =M46*10^6/M22 -> 161956.52 | ... P16: =P46*10^6/P22 -> 159090.91 | Q16: 161428.57 | T16: =T46*10^6/T22 -> 160027.86 | AB16: =T16 -> 160027.86
B17: Số ca
E18: MRI | F18: 257 | G18: 402 | H18: 460 | I18: 538 | J18: 463 | K18: 437 | L18: 449 | M18: 358 | N18: 373 | O18: 353 | P18: 327 | Q18: 374 | T18: =SUM(F18:Q18) -> 4791 | AB18: =AB95 -> 5440
E19: Mammo X-Quang | F19: 7 | G19: 16 | H19: 17 | I19: 37 | J19: 22 | K19: 18 | L19: 21 | M19: 28 | N19: 20 | O19: 18 | P19: 17 | Q19: 16 | T19: =SUM(F19:Q19) -> 237 | AB19: =AB96 -> 444
E20: CT | F20: 108 | G20: 143 | H20: 166 | I20: 201 | J20: 134 | K20: 106 | L20: 81 | M20: 76 | N20: 82 | O20: 92 | P20: 83 | Q20: 109 | T20: =SUM(F20:Q20) -> 1381 | AB20: =AB97 -> 2332.8
E21: X-Quang | F21: 58 | G21: 83 | H21: 147 | I21: 228 | J21: 168 | K21: 188 | L21: 203 | M21: 155 | N21: 167 | O21: 144 | P21: 187 | Q21: 150 | T21: =SUM(F21:Q21) -> 1878 | AB21: =AB98 -> 2736
E22: Siêu âm | F22: 36 | G22: 72 | H22: 67 | I22: 57 | J22: 42 | K22: 38 | L22: 85 | M22: 46 | N22: 79 | O22: 82 | P22: 44 | Q22: 70 | T22: =SUM(F22:Q22) -> 718 | AB22: =AB99 -> 1020
B23: Đơn giá chi phí trung bình
D24: Vật tư tiêu hao
E25: MRI | R25: 66943.206
E26: Mammo X-Quang | R26: 32967.486
E27: CT | R27: 73748.968
E28: X-Quang | R28: 22816.038
E29: Siêu âm | R29: 7348.1512
D30: Chi phí đọc kết quả online
E31: MRI
E32: Mammo X-Quang
E33: CT
E34: X-Quang
E35: Siêu âm
D36: Tiền thuốc
D37: Hoa hồng cho bác sĩ
D38: Hoa hồng nhân viên
D39: Truyền thông marketing
B40: Doanh thu
D41: Chẩn đoán hình ảnh
E42: MRI | F42: =480400000/(10^6) -> 480.4 | G42: =766600000/(10^6) -> 766.6 | H42: =864000000/(10^6) -> 864 | I42: =1002400000/(10^6) -> 1002.4 | J42: =860400000/(10^6) -> 860.4 | K42: =801600000/(10^6) -> 801.6 | L42: =845200000/(10^6) -> 845.2 | M42: =676400000/(10^6) -> 676.4 | N42: =707300000/(10^6) -> 707.3 | O42: =659800000/(10^6) -> 659.8 | P42: =625800000/(10^6) -> 625.8 | Q42: 700.4 | R42: =SUMIFS($F42:$Q42,$F$7:$Q$7,"A") -> 8990.3 | S42: =SUMIFS($F42:$Q42,$F$7:$Q$7,"B") -> 0 | T42: =SUM(R42:S42) -> 8990.3 | U42: =IFERROR(R42/R$47,"") -> 0.80621094 | V42: =IFERROR(S42/S$47,"") | W42: =IFERROR(T42/T$47,"") -> 0.80621094 | Z42: 0.05 | AA42: vs 2025 | AB42: =AB12*AB18/10^6 -> 10208.147
E43: Mammo X-Quang | F43: 4 | G43: 9.5 | H43: 8.5 | I43: 20.5 | J43: 11 | K43: 10.8 | L43: 10.5 | M43: 14 | N43: 10 | O43: 9 | P43: 8.5 | Q43: 8 | R43: =SUMIFS($F43:$Q43,$F$7:$Q$7,"A") -> 124.3 | S43: =SUMIFS($F43:$Q43,$F$7:$Q$7,"B") -> 0 | T43: =SUM(R43:S43) -> 124.3 | U43: =IFERROR(R43/R$47,"") -> 0.011146682 | V43: =IFERROR(S43/S$47,"") | W43: =IFERROR(T43/T$47,"") -> 0.011146682 | Z43: 0.05 | AA43: vs 2025 | AB43: =AB13*AB19/10^6 -> 232.86582
E44: CT | F44: =125800000/(10^6) -> 125.8 | G44: =171000000/(10^6) -> 171 | H44: =199500000/(10^6) -> 199.5 | I44: =239500000/(10^6) -> 239.5 | J44: =155500000/(10^6) -> 155.5 | K44: =118500000/(10^6) -> 118.5 | L44: =94500000/(10^6) -> 94.5 | M44: =93000000/(10^6) -> 93 | N44: =91000000/(10^6) -> 91 | O44: =113300000/(10^6) -> 113.3 | P44: =106800000/(10^6) -> 106.8 | Q44: 134.9 | R44: =SUMIFS($F44:$Q44,$F$7:$Q$7,"A") -> 1643.3 | S44: =SUMIFS($F44:$Q44,$F$7:$Q$7,"B") -> 0 | T44: =SUM(R44:S44) -> 1643.3 | U44: =IFERROR(R44/R$47,"") -> 0.14736398 | V44: =IFERROR(S44/S$47,"") | W44: =IFERROR(T44/T$47,"") -> 0.14736398 | Z44: 0.05 | AA44: vs 2025 | AB44: =AB14*AB20/10^6 -> 2775.88
E45: X-Quang | F45: =8350000/(10^6) -> 8.35 | G45: =11000000/(10^6) -> 11 | H45: =23600000/(10^6) -> 23.6 | I45: =30750000/(10^6) -> 30.75 | J45: =23100000/(10^6) -> 23.1 | K45: =25150000/(10^6) -> 25.15 | L45: =31350000/(10^6) -> 31.35 | M45: =23750000/(10^6) -> 23.75 | N45: =28500000/(10^6) -> 28.5 | O45: =22700000/(10^6) -> 22.7 | P45: =27750000/(10^6) -> 27.75 | Q45: 22.5 | R45: =SUMIFS($F45:$Q45,$F$7:$Q$7,"A") -> 278.5 | S45: =SUMIFS($F45:$Q45,$F$7:$Q$7,"B") -> 0 | T45: =SUM(R45:S45) -> 278.5 | U45: =IFERROR(R45/R$47,"") -> 0.024974667 | V45: =IFERROR(S45/S$47,"") | W45: =IFERROR(T45/T$47,"") -> 0.024974667 | Z45: 0.05 | AA45: vs 2025 | AB45: =AB15*AB21/10^6 -> 405.73802
E46: Siêu âm | F46: =5000000/(10^6) -> 5 | G46: =11100000/(10^6) -> 11.1 | H46: =10600000/(10^6) -> 10.6 | I46: =9050000/(10^6) -> 9.05 | J46: =7150000/(10^6) -> 7.15 | K46: =6550000/(10^6) -> 6.55 | L46: =13900000/(10^6) -> 13.9 | M46: =7450000/(10^6) -> 7.45 | N46: =12300000/(10^6) -> 12.3 | O46: =13500000/(10^6) -> 13.5 | P46: =7000000/(10^6) -> 7 | Q46: 11.3 | R46: =SUMIFS($F46:$Q46,$F$7:$Q$7,"A") -> 114.9 | S46: =SUMIFS($F46:$Q46,$F$7:$Q$7,"B") -> 0 | T46: =SUM(R46:S46) -> 114.9 | U46: =IFERROR(R46/R$47,"") -> 0.010303731 | V46: =IFERROR(S46/S$47,"") | W46: =IFERROR(T46/T$47,"") -> 0.010303731 | Z46: 0.05 | AA46: vs 2025 | AB46: =AB16*AB22/10^6 -> 163.22841
D47: Tổng- Chẩn đoán hình ảnh | F47: =SUM(F42:F46) -> 623.55 | G47: =SUM(G42:G46) -> 969.2 | H47: =SUM(H42:H46) -> 1106.2 | I47: =SUM(I42:I46) -> 1302.2 | J47: =SUM(J42:J46) -> 1057.15 | K47: =SUM(K42:K46) -> 962.6 | L47: =SUM(L42:L46) -> 995.45 | M47: =SUM(M42:M46) -> 814.6 | ... Q47: =SUM(Q42:Q46) -> 877.1 | R47: =SUMIFS($F47:$Q47,$F$7:$Q$7,"A") -> 11151.3 | S47: =SUMIFS($F47:$Q47,$F$7:$Q$7,"B") -> 0 | T47: =SUM(R47:S47) -> 11151.3 | U47: =IFERROR(R47/R$47,"") -> 1 | V47: =IFERROR(S47/S$47,"") | W47: =IFERROR(T47/T$47,"") -> 1 | AB47: =SUM(AB42:AB46) -> 13785.859
D48: Tổng- Khác | F48: 0 | G48: 0.5 | H48: 1.05 | I48: 1.6 | J48: 0.5 | K48: 0.5 | L48: 0.5 | M48: 2.15 | N48: 3.65 | O48: 7.92 | P48: 0 | Q48: 0.55 | R48: =SUMIFS($F48:$Q48,$F$7:$Q$7,"A") -> 18.92 | S48: =SUMIFS($F48:$Q48,$F$7:$Q$7,"B") -> 0 | T48: =SUM(R48:S48) -> 18.92 | U48: =IFERROR(R48/R$47,"") -> 0.0016966632 | V48: =IFERROR(S48/S$47,"") | W48: =IFERROR(T48/T$47,"") -> 0.0016966632 | AB48: 0
B49: Tổng- Doanh thu | F49: =SUM(F47,F48) -> 623.55 | G49: =SUM(G47,G48) -> 969.7 | H49: =SUM(H47,H48) -> 1107.25 | I49: =SUM(I47,I48) -> 1303.8 | J49: =SUM(J47,J48) -> 1057.65 | K49: =SUM(K47,K48) -> 963.1 | L49: =SUM(L47,L48) -> 995.95 | M49: =SUM(M47,M48) -> 816.75 | ... Q49: =SUM(Q47,Q48) -> 877.65 | R49: =SUMIFS($F49:$Q49,$F$7:$Q$7,"A") -> 11170.22 | S49: =SUMIFS($F49:$Q49,$F$7:$Q$7,"B") -> 0 | T49: =SUM(R49:S49) -> 11170.22 | U49: =IFERROR(R49/R$47,"") -> 1.0016967 | V49: =IFERROR(S49/S$47,"") | W49: =IFERROR(T49/T$47,"") -> 1.0016967 | AB49: =SUM(AB47,AB48) -> 13785.859
B50: Giảm trừ doanh thu | F50: =SUM(F51:F55) -> 0 | G50: =SUM(G51:G55) -> 0 | H50: =SUM(H51:H55) -> 4.25 | I50: =SUM(I51:I55) -> 7.59 | J50: =SUM(J51:J55) -> 8.27 | K50: =SUM(K51:K55) -> 6.72 | L50: =SUM(L51:L55) -> 0 | M50: =SUM(M51:M55) -> 6.96 | ... Q50: =SUM(Q51:Q55) -> 18.28 | R50: =SUMIFS($F50:$Q50,$F$7:$Q$7,"A") -> 72.435 | S50: =SUMIFS($F50:$Q50,$F$7:$Q$7,"B") -> 0 | T50: =SUM(R50:S50) -> 72.435 | U50: =IFERROR(R50/R$47,"") -> 0.0064956552 | V50: =IFERROR(S50/S$47,"") | W50: =IFERROR(T50/T$47,"") -> 0.0064956552 | AB50: 0
E51: MRI | F51: =0/(10^6) -> 0 | G51: =0/(10^6) -> 0 | H51: =4250000/(10^6) -> 4.25 | I51: =7590000/(10^6) -> 7.59 | J51: =8270000/(10^6) -> 8.27 | K51: =6720000/(10^6) -> 6.72 | L51: =0/(10^6) -> 0 | M51: =6960000/(10^6) -> 6.96 | N51: =4825000/(10^6) -> 4.825 | O51: =2300000/(10^6) -> 2.3 | P51: =13240000/(10^6) -> 13.24 | Q51: =18280000/(10^6) -> 18.28 | R51: =SUMIFS($F51:$Q51,$F$7:$Q$7,"A") -> 72.435 | S51: =SUMIFS($F51:$Q51,$F$7:$Q$7,"B") -> 0 | T51: =SUM(R51:S51) -> 72.435 | U51: =IFERROR(R51/R42,"") -> 0.008057017 | V51: =IFERROR(S51/S42,"") | W51: =IFERROR(T51/T42,"") -> 0.008057017
E52: Mammo X-Quang | R52: =SUMIFS($F52:$Q52,$F$7:$Q$7,"A") -> 0 | S52: =SUMIFS($F52:$Q52,$F$7:$Q$7,"B") -> 0 | T52: =SUM(R52:S52) -> 0 | U52: =IFERROR(R52/R43,"") -> 0 | V52: =IFERROR(S52/S43,"") | W52: =IFERROR(T52/T43,"") -> 0
E53: CT | R53: =SUMIFS($F53:$Q53,$F$7:$Q$7,"A") -> 0 | S53: =SUMIFS($F53:$Q53,$F$7:$Q$7,"B") -> 0 | T53: =SUM(R53:S53) -> 0 | U53: =IFERROR(R53/R44,"") -> 0 | V53: =IFERROR(S53/S44,"") | W53: =IFERROR(T53/T44,"") -> 0
E54: X-Quang | R54: =SUMIFS($F54:$Q54,$F$7:$Q$7,"A") -> 0 | S54: =SUMIFS($F54:$Q54,$F$7:$Q$7,"B") -> 0 | T54: =SUM(R54:S54) -> 0 | U54: =IFERROR(R54/R45,"") -> 0 | V54: =IFERROR(S54/S45,"") | W54: =IFERROR(T54/T45,"") -> 0
E55: Siêu âm | R55: =SUMIFS($F55:$Q55,$F$7:$Q$7,"A") -> 0 | S55: =SUMIFS($F55:$Q55,$F$7:$Q$7,"B") -> 0 | T55: =SUM(R55:S55) -> 0 | U55: =IFERROR(R55/R46,"") -> 0 | V55: =IFERROR(S55/S46,"") | W55: =IFERROR(T55/T46,"") -> 0
B56: Biến phí
C57: Vật tư tiêu hao | F57: =25903983/(10^6) -> 25.903983 | G57: =42191047/(10^6) -> 42.191047 | H57: =48855017/(10^6) -> 48.855017 | I57: =51247995/(10^6) -> 51.247995 | J57: =49248269/(10^6) -> 49.248269 | K57: =40210769/(10^6) -> 40.210769 | L57: =40563081/(10^6) -> 40.563081 | M57: =33949967/(10^6) -> 33.949967 | N57: =38389676/(10^6) -> 38.389676 | O57: =36456761/(10^6) -> 36.456761 | P57: =33953794/(10^6) -> 33.953794 | Q57: 39.015565 | R57: =SUMIFS($F57:$Q57,$F$7:$Q$7,"A") -> 479.98592 | S57: =SUMIFS($F57:$Q57,$F$7:$Q$7,"B") -> 0 | T57: =SUM(R57:S57) -> 479.98592 | U57: =IFERROR(R57/R$47,"") -> 0.043043046 | V57: =IFERROR(S57/S$47,"") | W57: =IFERROR(T57/T$47,"") -> 0.043043046 | Z57: =U57 -> 0.043043046 | AA57: % doanh thu | AB57: =Z57*$AB$47 -> 593.38538
C58: Đọc kết quả online | F58: 45.22 | G58: 64.95 | H58: 73.75 | I58: 87.965 | J58: 70.765 | K58: 67.405 | L58: 67.39 | M58: 50.83 | N58: 55.847 | O58: 52.925 | P58: 48.994 | Q58: 56.793 | R58: =SUMIFS($F58:$Q58,$F$7:$Q$7,"A") -> 742.834 | S58: =SUMIFS($F58:$Q58,$F$7:$Q$7,"B") -> 0 | T58: =SUM(R58:S58) -> 742.834 | U58: =IFERROR(R58/R$47,"") -> 0.066614117 | V58: =IFERROR(S58/S$47,"") | W58: =IFERROR(T58/T$47,"") -> 0.066614117 | Z58: =U58 -> 0.066614117 | AA58: % doanh thu | AB58: =Z58*$AB$47 -> 918.33283
C59: Thuốc | F59: 19.077652 | G59: 37.56472 | H59: 33.844803 | I59: 35.630216 | J59: 25.877564 | K59: 14.219853 | L59: 26.795784 | M59: 27.845976 | N59: 23.262359 | O59: 27.724573 | P59: 28.849607 | Q59: 21.862736 | R59: =SUMIFS($F59:$Q59,$F$7:$Q$7,"A") -> 322.55584 | S59: =SUMIFS($F59:$Q59,$F$7:$Q$7,"B") -> 0 | T59: =SUM(R59:S59) -> 322.55584 | U59: =IFERROR(R59/R$47,"") -> 0.028925403 | V59: =IFERROR(S59/S$47,"") | W59: =IFERROR(T59/T$47,"") -> 0.028925403 | Z59: =U59 -> 0.028925403 | AA59: % doanh thu | AB59: =Z59*$AB$47 -> 398.76153
C60: Tư vấn chuyên môn | F60: 82.3 | G60: 111.7 | H60: 138.7 | I60: 167.4 | J60: 127 | K60: 114.2 | L60: 116.3 | M60: 99.6 | N60: 91.9 | O60: 93.1 | P60: 96.5 | Q60: 100.4 | R60: =SUMIFS($F60:$Q60,$F$7:$Q$7,"A") -> 1339.1 | S60: =SUMIFS($F60:$Q60,$F$7:$Q$7,"B") -> 0 | T60: =SUM(R60:S60) -> 1339.1 | U60: =IFERROR(R60/R$47,"") -> 0.12008465 | V60: =IFERROR(S60/S$47,"") | W60: =IFERROR(T60/T$47,"") -> 0.12008465 | Z60: =U60 -> 0.12008465 | AA60: % doanh thu | AB60: =Z60*$AB$47 -> 1655.4701
C61: Hoa hồng và thưởng kinh doanh | F61: 12.5 | G61: 19.07 | H61: 29.2575 | I61: 36.6225 | J61: 28.85 | K61: 25.795 | L61: 25.635 | M61: 19.815 | N61: 21.345 | O61: 19.9525 | P61: 18.51 | Q61: 21.0675 | R61: =SUMIFS($F61:$Q61,$F$7:$Q$7,"A") -> 278.42 | S61: =SUMIFS($F61:$Q61,$F$7:$Q$7,"B") -> 0 | T61: =SUM(R61:S61) -> 278.42 | U61: =IFERROR(R61/R$47,"") -> 0.024967493 | V61: =IFERROR(S61/S$47,"") | W61: =IFERROR(T61/T$47,"") -> 0.024967493 | Z61: =U61 -> 0.024967493 | AA61: % doanh thu | AB61: =Z61*$AB$47 -> 344.19834
C62: Truyền thông marketing | F62: 24.85732 | G62: 3.35 | H62: 0.2592 | I62: 0 | J62: 0 | K62: 0 | L62: 1.048817 | M62: 9.07128 | N62: 18.040551 | O62: 15.979797 | P62: 6.066949 | Q62: 0 | R62: =SUMIFS($F62:$Q62,$F$7:$Q$7,"A") -> 78.673914 | S62: =SUMIFS($F62:$Q62,$F$7:$Q$7,"B") -> 0 | T62: =SUM(R62:S62) -> 78.673914 | U62: =IFERROR(R62/R$47,"") -> 0.0070551338 | V62: =IFERROR(S62/S$47,"") | W62: =IFERROR(T62/T$47,"") -> 0.0070551338 | Z62: 0.01 | AA62: % doanh thu | AB62: =Z62*$AB$47 -> 137.85859
B63: Tổng- Biến phí | F63: =SUBTOTAL(9,F57:F62) -> 209.85896 | G63: =SUBTOTAL(9,G57:G62) -> 278.82577 | H63: =SUBTOTAL(9,H57:H62) -> 324.66652 | I63: =SUBTOTAL(9,I57:I62) -> 378.86571 | J63: =SUBTOTAL(9,J57:J62) -> 301.74083 | K63: =SUBTOTAL(9,K57:K62) -> 261.83062 | L63: =SUBTOTAL(9,L57:L62) -> 277.73268 | M63: =SUBTOTAL(9,M57:M62) -> 241.11222 | ... Q63: =SUBTOTAL(9,Q57:Q62) -> 239.1388 | R63: =SUMIFS($F63:$Q63,$F$7:$Q$7,"A") -> 3241.5697 | S63: =SUMIFS($F63:$Q63,$F$7:$Q$7,"B") -> 0 | T63: =SUM(R63:S63) -> 3241.5697 | U63: =IFERROR(R63/R$47,"") -> 0.29068985 | V63: =IFERROR(S63/S$47,"") | W63: =IFERROR(T63/T$47,"") -> 0.29068985 | AB63: =SUM(AB57:AB62) -> 4048.0068
B64: Lãi trên biến phí | F64: =F49-F50-F63 -> 413.69104 | G64: =G49-G50-G63 -> 690.87423 | H64: =H49-H50-H63 -> 778.33348 | I64: =I49-I50-I63 -> 917.34429 | J64: =J49-J50-J63 -> 747.63917 | K64: =K49-K50-K63 -> 694.54938 | L64: =L49-L50-L63 -> 718.21732 | M64: =M49-M50-M63 -> 568.67778 | ... Q64: =Q49-Q50-Q63 -> 620.2312 | R64: =SUMIFS($F64:$Q64,$F$7:$Q$7,"A") -> 7856.2153 | S64: =SUMIFS($F64:$Q64,$F$7:$Q$7,"B") -> 0 | T64: =SUM(R64:S64) -> 7856.2153 | U64: =IFERROR(R64/R$47,"") -> 0.70451116 | V64: =IFERROR(S64/S$47,"") | W64: =IFERROR(T64/T$47,"") -> 0.70451116 | AB64: =AB49-AB63-AB50 -> 9737.8524
B65: Định phí | R65: =SUMIFS($F65:$Q65,$F$7:$Q$7,"A") -> 0 | S65: =SUMIFS($F65:$Q65,$F$7:$Q$7,"B") -> 0 | T65: =SUM(R65:S65) -> 0 | U65: =IFERROR(R65/R$47,"") -> 0 | V65: =IFERROR(S65/S$47,"") | W65: =IFERROR(T65/T$47,"") -> 0
C66: Chi phí nhân viên | F66: 274.18009 | G66: 205.97764 | H66: 187.27723 | I66: 201.65765 | J66: 162.82997 | K66: 163.4835 | L66: 189.40059 | M66: 203.96723 | N66: 180.37997 | O66: 175.96568 | P66: 180.101 | Q66: 190.89241 | R66: =SUMIFS($F66:$Q66,$F$7:$Q$7,"A") -> 2316.113 | S66: =SUMIFS($F66:$Q66,$F$7:$Q$7,"B") -> 0 | T66: =SUM(R66:S66) -> 2316.113 | U66: =IFERROR(R66/R$47,"") -> 0.20769892 | V66: =IFERROR(S66/S$47,"") | W66: =IFERROR(T66/T$47,"") -> 0.20769892 | Z66: 0.02 | AA66: vs 2025 | AB66: =T66*(1+Z66) -> 2362.4352
C67: Chi phí thuê địa điểm | F67: 30 | G67: =30244500/10^6 -> 30.2445 | H67: =30244500/10^6 -> 30.2445 | I67: =30244500/10^6 -> 30.2445 | J67: =30244500/10^6 -> 30.2445 | K67: =30244500/10^6 -> 30.2445 | L67: =30244500/10^6 -> 30.2445 | M67: =30244500/10^6 -> 30.2445 | N67: =30244500/10^6 -> 30.2445 | ... Q67: =30244500/10^6 -> 30.2445 | R67: =SUMIFS($F67:$Q67,$F$7:$Q$7,"A") -> 362.6895 | S67: =SUMIFS($F67:$Q67,$F$7:$Q$7,"B") -> 0 | T67: =SUM(R67:S67) -> 362.6895 | U67: =IFERROR(R67/R$47,"") -> 0.032524414 | V67: =IFERROR(S67/S$47,"") | W67: =IFERROR(T67/T$47,"") -> 0.032524414 | Z67: =S67 -> 0 | AA67: TB t9-11/2025 | AB67: =Z67*12*(1+5%) -> 0
C68: Chi phí bảo dưỡng bảo trì sửa chữa | R68: =SUMIFS($F68:$Q68,$F$7:$Q$7,"A") -> 0 | S68: =SUMIFS($F68:$Q68,$F$7:$Q$7,"B") -> 0 | T68: =SUM(R68:S68) -> 0 | U68: =IFERROR(R68/R$47,"") -> 0 | V68: =IFERROR(S68/S$47,"") | W68: =IFERROR(T68/T$47,"") -> 0 | AA68: Đề xuất PKT | AB68: ='Site list'!Q4 -> 320.30125
C69: Chi phí thường xuyên | F69: 107.79407 | G69: 85.134097 | H69: 100.21069 | I69: 93.381509 | J69: 108.09657 | K69: 123.98365 | L69: 117.41875 | M69: 78.40763 | N69: 65.057236 | O69: 70.645699 | P69: 54.74411 | Q69: 74.814259 | R69: =SUMIFS($F69:$Q69,$F$7:$Q$7,"A") -> 1079.6883 | S69: =SUMIFS($F69:$Q69,$F$7:$Q$7,"B") -> 0 | T69: =SUM(R69:S69) -> 1079.6883 | U69: =IFERROR(R69/R$47,"") -> 0.09682174 | V69: =IFERROR(S69/S$47,"") | W69: =IFERROR(T69/T$47,"") -> 0.09682174 | AA69: không đổi | AB69: =T69 -> 1079.6883
C70: Chi phí khác | F70: 1.1719 | G70: 0.4435 | H70: 1.0435 | I70: 4.214974 | J70: 0.3935 | K70: 2.1935 | L70: 2.844997 | M70: 3.299929 | N70: 5.11802 | O70: 2.399929 | P70: 2.749929 | Q70: 3.319926 | R70: =SUMIFS($F70:$Q70,$F$7:$Q$7,"A") -> 29.193604 | S70: =SUMIFS($F70:$Q70,$F$7:$Q$7,"B") -> 0 | T70: =SUM(R70:S70) -> 29.193604 | U70: =IFERROR(R70/R$47,"") -> 0.0026179552 | V70: =IFERROR(S70/S$47,"") | W70: =IFERROR(T70/T$47,"") -> 0.0026179552 | AA70: không đổi | AB70: =T70 -> 29.193604
B71: Tổng- Định phí | F71: =SUM(F66:F70) -> 413.14606 | G71: =SUM(G66:G70) -> 321.79974 | H71: =SUM(H66:H70) -> 318.77592 | I71: =SUM(I66:I70) -> 329.49864 | J71: =SUM(J66:J70) -> 301.56454 | K71: =SUM(K66:K70) -> 319.90515 | L71: =SUM(L66:L70) -> 339.90884 | M71: =SUM(M66:M70) -> 315.91929 | ... Q71: =SUM(Q66:Q70) -> 299.27109 | R71: =SUMIFS($F71:$Q71,$F$7:$Q$7,"A") -> 3787.6843 | S71: =SUMIFS($F71:$Q71,$F$7:$Q$7,"B") -> 0 | T71: =SUM(R71:S71) -> 3787.6843 | U71: =IFERROR(R71/R$47,"") -> 0.33966303 | V71: =IFERROR(S71/S$47,"") | W71: =IFERROR(T71/T$47,"") -> 0.33966303 | AB71: =SUM(AB66:AB70) -> 3791.6184
B72: EBITDA | F72: =F64-F71 -> 0.544987 | G72: =G64-G71 -> 369.07449 | H72: =H64-H71 -> 459.55756 | I72: =I64-I71 -> 587.84565 | J72: =J64-J71 -> 446.07463 | K72: =K64-K71 -> 374.64423 | L72: =L64-L71 -> 378.30848 | M72: =M64-M71 -> 252.75849 | ... Q72: =Q64-Q71 -> 320.96011 | R72: =SUMIFS($F72:$Q72,$F$7:$Q$7,"A") -> 4068.531 | S72: =SUMIFS($F72:$Q72,$F$7:$Q$7,"B") -> 0 | T72: =SUM(R72:S72) -> 4068.531 | U72: =IFERROR(R72/R$47,"") -> 0.36484813 | V72: =IFERROR(S72/S$47,"") | W72: =IFERROR(T72/T$47,"") -> 0.36484813 | AB72: =AB64-AB71 -> 5946.234
B73: EBITDA về công ty mẹ | T73: =T72*Z73 -> 3539.6219 | U73: =IFERROR(R73/R$47,"") -> 0 | V73: =IFERROR(S73/S$47,"") | W73: =IFERROR(T73/T$47,"") -> 0.31741787 | Z73: ='Site list'!H4 -> 0.87 | AA73: Tỷ lệ sở hưu | AB73: =AB72*Z73 -> 5173.2236
U74: =IFERROR(R74/R$47,"") -> 0 | V74: =IFERROR(S74/S$47,"") | W74: =IFERROR(T74/T$47,"") -> 0
C75: Chi phí khấu hao máy chẩn đoán | F75: =SUM(F76:F80) -> 236.5 | G75: =SUM(G76:G80) -> 236.5 | H75: =SUM(H76:H80) -> 236.5 | I75: =SUM(I76:I80) -> 236.5 | J75: =SUM(J76:J80) -> 236.5 | K75: =SUM(K76:K80) -> 236.5 | L75: =SUM(L76:L80) -> 236.5 | M75: =SUM(M76:M80) -> 236.5 | ... P75: =SUM(P76:P80) -> 236.5 | Q75: =P75 -> 236.5 | R75: =SUM(R76:R80) -> 2838 | S75: =SUM(S76:S80) -> 0 | T75: =SUM(T76:T80) -> 2838 | U75: =IFERROR(R75/R$47,"") -> 0.25449948 | V75: =IFERROR(S75/S$47,"") | W75: =IFERROR(T75/T$47,"") -> 0.25449948 | AA75: không đổi | AB75: =T75 -> 2838
E76: MRI | F76: =133333333/(10^6) -> 133.33333 | G76: =133333333/(10^6) -> 133.33333 | H76: =133333333/(10^6) -> 133.33333 | I76: =133333333/(10^6) -> 133.33333 | J76: =133333333/(10^6) -> 133.33333 | K76: =133333333/(10^6) -> 133.33333 | L76: =133333333/(10^6) -> 133.33333 | M76: =133333333/(10^6) -> 133.33333 | ... P76: =133333333/(10^6) -> 133.33333 | Q76: =P76 -> 133.33333 | R76: =SUMIFS($F76:$Q76,$F$7:$Q$7,"A") -> 1600 | S76: =SUMIFS($F76:$Q76,$F$7:$Q$7,"B") -> 0 | T76: =SUM(R76:S76) -> 1600 | U76: =IFERROR(R76/R$47,"") -> 0.14348103 | V76: =IFERROR(S76/S$47,"") | W76: =IFERROR(T76/T$47,"") -> 0.14348103 | AA76: không đổi | AB76: =T76 -> 1600
E77: Mammo X-Quang | F77: =20000000/(10^6) -> 20 | G77: =20000000/(10^6) -> 20 | H77: =20000000/(10^6) -> 20 | I77: =20000000/(10^6) -> 20 | J77: =20000000/(10^6) -> 20 | K77: =20000000/(10^6) -> 20 | L77: =20000000/(10^6) -> 20 | M77: =20000000/(10^6) -> 20 | ... P77: =20000000/(10^6) -> 20 | Q77: =P77 -> 20 | R77: =SUMIFS($F77:$Q77,$F$7:$Q$7,"A") -> 240 | S77: =SUMIFS($F77:$Q77,$F$7:$Q$7,"B") -> 0 | T77: =SUM(R77:S77) -> 240 | U77: =IFERROR(R77/R$47,"") -> 0.021522154 | V77: =IFERROR(S77/S$47,"") | W77: =IFERROR(T77/T$47,"") -> 0.021522154 | AA77: không đổi | AB77: =T77 -> 240
E78: CT | F78: =70833333/(10^6) -> 70.833333 | G78: =70833333/(10^6) -> 70.833333 | H78: =70833333/(10^6) -> 70.833333 | I78: =70833333/(10^6) -> 70.833333 | J78: =70833333/(10^6) -> 70.833333 | K78: =70833333/(10^6) -> 70.833333 | L78: =70833333/(10^6) -> 70.833333 | M78: =70833333/(10^6) -> 70.833333 | ... P78: =70833333/(10^6) -> 70.833333 | Q78: =P78 -> 70.833333 | R78: =SUMIFS($F78:$Q78,$F$7:$Q$7,"A") -> 850 | S78: =SUMIFS($F78:$Q78,$F$7:$Q$7,"B") -> 0 | T78: =SUM(R78:S78) -> 850 | U78: =IFERROR(R78/R$47,"") -> 0.076224296 | V78: =IFERROR(S78/S$47,"") | W78: =IFERROR(T78/T$47,"") -> 0.076224296 | AA78: không đổi | AB78: =T78 -> 850
E79: X-Quang | F79: =5666667/(10^6) -> 5.666667 | G79: =5666667/(10^6) -> 5.666667 | H79: =5666667/(10^6) -> 5.666667 | I79: =5666667/(10^6) -> 5.666667 | J79: =5666667/(10^6) -> 5.666667 | K79: =5666667/(10^6) -> 5.666667 | L79: =5666667/(10^6) -> 5.666667 | M79: =5666667/(10^6) -> 5.666667 | ... P79: =5666667/(10^6) -> 5.666667 | Q79: =P79 -> 5.666667 | R79: =SUMIFS($F79:$Q79,$F$7:$Q$7,"A") -> 68.000004 | S79: =SUMIFS($F79:$Q79,$F$7:$Q$7,"B") -> 0 | T79: =SUM(R79:S79) -> 68.000004 | U79: =IFERROR(R79/R$47,"") -> 0.0060979441 | V79: =IFERROR(S79/S$47,"") | W79: =IFERROR(T79/T$47,"") -> 0.0060979441 | AA79: không đổi | AB79: =T79 -> 68.000004
E80: Siêu âm | F80: =6666667/(10^6) -> 6.666667 | G80: =6666667/(10^6) -> 6.666667 | H80: =6666667/(10^6) -> 6.666667 | I80: =6666667/(10^6) -> 6.666667 | J80: =6666667/(10^6) -> 6.666667 | K80: =6666667/(10^6) -> 6.666667 | L80: =6666667/(10^6) -> 6.666667 | M80: =6666667/(10^6) -> 6.666667 | ... P80: =6666667/(10^6) -> 6.666667 | Q80: =P80 -> 6.666667 | R80: =SUMIFS($F80:$Q80,$F$7:$Q$7,"A") -> 80.000004 | S80: =SUMIFS($F80:$Q80,$F$7:$Q$7,"B") -> 0 | T80: =SUM(R80:S80) -> 80.000004 | U80: =IFERROR(R80/R$47,"") -> 0.0071740518 | V80: =IFERROR(S80/S$47,"") | W80: =IFERROR(T80/T$47,"") -> 0.0071740518 | AA80: không đổi | AB80: =T80 -> 80.000004
C81: Chi phí khấu hao khác | F81: 24.41545 | G81: 24.41545 | H81: 24.41545 | I81: 24.41545 | J81: 24.41545 | K81: 24.41545 | L81: 24.41545 | M81: 24.41545 | N81: 24.41545 | O81: 24.41545 | P81: 24.41545 | Q81: =P81 -> 24.41545 | R81: =SUMIFS($F81:$Q81,$F$7:$Q$7,"A") -> 292.9854 | S81: =SUMIFS($F81:$Q81,$F$7:$Q$7,"B") -> 0 | T81: =SUM(R81:S81) -> 292.9854 | U81: =IFERROR(R81/R$47,"") -> 0.026273654 | V81: =IFERROR(S81/S$47,"") | W81: =IFERROR(T81/T$47,"") -> 0.026273654 | AA81: không đổi | AB81: =T81 -> 292.9854
C82: Lợi nhuận khác | F82: =0/(10^6) -> 0 | G82: =33998323/(10^6) -> 33.998323 | H82: =30020430/(10^6) -> 30.02043 | I82: 30.045972 | J82: =23868844/(10^6) -> 23.868844 | K82: =20099560/(10^6) -> 20.09956 | L82: =37639123/(10^6) -> 37.639123 | M82: =115210000/(10^6) -> 115.21 | N82: =0/(10^6) -> 0 | O82: =0/(10^6) -> 0 | P82: =0/(10^6) -> 0 | Q82: 0 | R82: =SUMIFS($F82:$Q82,$F$7:$Q$7,"A") -> 290.88225 | S82: =SUMIFS($F82:$Q82,$F$7:$Q$7,"B") -> 0 | T82: =SUM(R82:S82) -> 290.88225 | U82: =IFERROR(R82/R$47,"") -> 0.026085053 | V82: =IFERROR(S82/S$47,"") | W82: =IFERROR(T82/T$47,"") -> 0.026085053 | AB82: 0
C83: Lợi nhuận/Chi phí tài chính | F83: =5700276/(10^6) -> 5.700276 | G83: =5701054/(10^6) -> 5.701054 | H83: =5296570/(10^6) -> 5.29657 | I83: =5884609/(10^6) -> 5.884609 | J83: =5806723/(10^6) -> 5.806723 | K83: =6099365/(10^6) -> 6.099365 | L83: =98599457/(10^6) -> 98.599457 | M83: =29136/(10^6) -> 0.029136 | N83: =1535298/(10^6) -> 1.535298 | O83: =69331/(10^6) -> 0.069331 | P83: =83237/(10^6) -> 0.083237 | Q83: 0.024414 | R83: =SUMIFS($F83:$Q83,$F$7:$Q$7,"A") -> 134.82947 | S83: =SUMIFS($F83:$Q83,$F$7:$Q$7,"B") -> 0 | T83: =SUM(R83:S83) -> 134.82947 | U83: =IFERROR(R83/R$47,"") -> 0.012090919 | V83: =IFERROR(S83/S$47,"") | W83: =IFERROR(T83/T$47,"") -> 0.012090919 | Z83: 0.005 | AA83: % EBITDA | AB83: =Z83*AB72 -> 29.73117
B84: Lợi nhuận trước thuế | F84: =F72-F75-F81+SUM(F82:F83) -> -254.67019 | G84: =G72-G75-G81+SUM(G82:G83) -> 147.85842 | H84: =H72-H75-H81+SUM(H82:H83) -> 233.95911 | I84: =I72-I75-I81+SUM(I82:I83) -> 362.86078 | J84: =J72-J75-J81+SUM(J82:J83) -> 214.83475 | K84: =K72-K75-K81+SUM(K82:K83) -> 139.9277 | L84: =L72-L75-L81+SUM(L82:L83) -> 253.63161 | M84: =M72-M75-M81+SUM(M82:M83) -> 107.08217 | ... T84: =T72-T75-T81+SUM(T82:T83) -> 1363.2573 | U84: =IFERROR(R84/R$47,"") -> 0.12225097 | V84: =IFERROR(S84/S$47,"") | W84: =IFERROR(T84/T$47,"") -> 0.12225097 | AB84: =AB72-AB75-AB81+SUM(AB82:AB83) -> 2844.9798
C85: Chi phí thuế TNDN (ước tính) | F85: 0 | G85: 29.571684 | H85: 46.791822 | I85: 72.572157 | J85: 42.966949 | K85: 27.98554 | L85: 50.726322 | M85: 21.416435 | N85: 11.792107 | O85: 7.5358876 | P85: 0.2127796 | Q85: 12.013814 | R85: =SUMIFS($F85:$Q85,$F$7:$Q$7,"A") -> 323.5855 | S85: =SUMIFS($F85:$Q85,$F$7:$Q$7,"B") -> 0 | T85: =SUM(R85:S85) -> 323.5855 | U85: =IFERROR(R85/R$47,"") -> 0.029017738 | V85: =IFERROR(S85/S$47,"") | W85: =IFERROR(T85/T$47,"") -> 0.029017738 | AB85: =AB84*20% -> 568.99596
B86: Lợi nhuận sau thuế | F86: =F84-F85 -> -254.67019 | G86: =G84-G85 -> 118.28674 | H86: =H84-H85 -> 187.16729 | I86: =I84-I85 -> 290.28863 | J86: =J84-J85 -> 171.8678 | K86: =K84-K85 -> 111.94216 | L86: =L84-L85 -> 202.90529 | M86: =M84-M85 -> 85.665738 | ... Q86: =Q84-Q85 -> 48.055257 | R86: =SUMIFS($F86:$Q86,$F$7:$Q$7,"A") -> 1039.6718 | S86: =SUMIFS($F86:$Q86,$F$7:$Q$7,"B") -> 0 | T86: =SUM(R86:S86) -> 1039.6718 | U86: =IFERROR(R86/R$47,"") -> 0.093233237 | V86: =IFERROR(S86/S$47,"") | W86: =IFERROR(T86/T$47,"") -> 0.093233237 | AB86: =AB84-AB85 -> 2275.9838
C87: Cổ đông thiểu số | F87: =F86*(1-'Site list'!$H$4) -> -33.107124 | G87: =G86*(1-'Site list'!$H$4) -> 15.377276 | H87: =H86*(1-'Site list'!$H$4) -> 24.331747 | I87: =I86*(1-'Site list'!$H$4) -> 37.737521 | J87: =J86*(1-'Site list'!$H$4) -> 22.342813 | K87: =K86*(1-'Site list'!$H$4) -> 14.552481 | L87: =L86*(1-'Site list'!$H$4) -> 26.377687 | M87: =M86*(1-'Site list'!$H$4) -> 11.136546 | ... Q87: =Q86*(1-'Site list'!$H$4) -> 6.2471834 | R87: =SUMIFS($F87:$Q87,$F$7:$Q$7,"A") -> 135.15733 | S87: =SUMIFS($F87:$Q87,$F$7:$Q$7,"B") -> 0 | T87: =SUM(R87:S87) -> 135.15733 | U87: =IFERROR(R87/R$47,"") -> 0.012120321 | V87: =IFERROR(S87/S$47,"") | W87: =IFERROR(T87/T$47,"") -> 0.012120321 | Z87: =1-'Site list'!H4 -> 0.13 | AB87: =AB86*Z87 -> 295.8779
B88: Lợi nhuận về công ty mẹ | F88: =F86-F87 -> -221.56306 | G88: =G86-G87 -> 102.90946 | H88: =H86-H87 -> 162.83554 | I88: =I86-I87 -> 252.5511 | J88: =J86-J87 -> 149.52498 | K88: =K86-K87 -> 97.38968 | L88: =L86-L87 -> 176.5276 | M88: =M86-M87 -> 74.529192 | ... Q88: =Q86-Q87 -> 41.808073 | R88: =SUMIFS($F88:$Q88,$F$7:$Q$7,"A") -> 904.51446 | S88: =SUMIFS($F88:$Q88,$F$7:$Q$7,"B") -> 0 | T88: =SUM(R88:S88) -> 904.51446 | U88: =IFERROR(R88/R$47,"") -> 0.081112916 | V88: =IFERROR(S88/S$47,"") | W88: =IFERROR(T88/T$47,"") -> 0.081112916 | AB88: =AB86-AB87 -> 1980.1059
B90: Vốn góp | Z90: ='Site list'!G4 -> 40000
B91: Phải trả cổ đông hợp tác kinh doanh gốc | F91: ='Site list'!$G$4*(1-'Site list'!$H$4)/10/12 -> 43.333333 | G91: ='Site list'!$G$4*(1-'Site list'!$H$4)/10/12 -> 43.333333 | H91: ='Site list'!$G$4*(1-'Site list'!$H$4)/10/12 -> 43.333333 | I91: ='Site list'!$G$4*(1-'Site list'!$H$4)/10/12 -> 43.333333 | J91: ='Site list'!$G$4*(1-'Site list'!$H$4)/10/12 -> 43.333333 | K91: ='Site list'!$G$4*(1-'Site list'!$H$4)/10/12 -> 43.333333 | L91: ='Site list'!$G$4*(1-'Site list'!$H$4)/10/12 -> 43.333333 | M91: ='Site list'!$G$4*(1-'Site list'!$H$4)/10/12 -> 43.333333 | ... Q91: ='Site list'!$G$4*(1-'Site list'!$H$4)/10/12 -> 43.333333 | Z91: =Z87 -> 0.13 | AB91: =Z90*Z91/10 -> 520
B93: CÁC CHỈ TIÊU HIỆU QUẢ HOẠT ĐỘNG
C94: Số ca/tháng
E95: MRI | F95: 257 | G95: 402 | H95: 460 | I95: 538 | J95: 463 | K95: 437 | L95: 449 | M95: 358 | N95: 373 | O95: 353 | P95: 327 | Q95: =Q18 -> 374 | R95: =SUMIFS($F95:$Q95,$F$7:$Q$7,"A") -> 4791 | S95: =SUMIFS($F95:$Q95,$F$7:$Q$7,"B") -> 0 | T95: =SUM(R95:S95) -> 4791 | AB95: =AB109*T103 -> 5440
E96: Mammo X-Quang | F96: 7 | G96: 16 | H96: 17 | I96: 37 | J96: 22 | K96: 18 | L96: 21 | M96: 28 | N96: 20 | O96: 18 | P96: 17 | Q96: =Q19 -> 16 | R96: =SUMIFS($F96:$Q96,$F$7:$Q$7,"A") -> 237 | S96: =SUMIFS($F96:$Q96,$F$7:$Q$7,"B") -> 0 | T96: =SUM(R96:S96) -> 237 | AB96: =AB110*T104 -> 444
E97: CT | F97: 108 | G97: 143 | H97: 166 | I97: 201 | J97: 134 | K97: 106 | L97: 81 | M97: 76 | N97: 82 | O97: 92 | P97: 83 | Q97: =Q20 -> 109 | R97: =SUMIFS($F97:$Q97,$F$7:$Q$7,"A") -> 1381 | S97: =SUMIFS($F97:$Q97,$F$7:$Q$7,"B") -> 0 | T97: =SUM(R97:S97) -> 1381 | AB97: =AB111*T105 -> 2332.8
E98: X-Quang | F98: 58 | G98: 83 | H98: 147 | I98: 228 | J98: 168 | K98: 188 | L98: 203 | M98: 155 | N98: 167 | O98: 144 | P98: 187 | Q98: =Q21 -> 150 | R98: =SUMIFS($F98:$Q98,$F$7:$Q$7,"A") -> 1878 | S98: =SUMIFS($F98:$Q98,$F$7:$Q$7,"B") -> 0 | T98: =SUM(R98:S98) -> 1878 | AB98: =AB112*T106 -> 2736
E99: Siêu âm | F99: 36 | G99: 72 | H99: 67 | I99: 57 | J99: 42 | K99: 38 | L99: 85 | M99: 46 | N99: 79 | O99: 82 | P99: 44 | Q99: =Q22 -> 70 | R99: =SUMIFS($F99:$Q99,$F$7:$Q$7,"A") -> 718 | S99: =SUMIFS($F99:$Q99,$F$7:$Q$7,"B") -> 0 | T99: =SUM(R99:S99) -> 718 | AB99: =AB113*T107 -> 1020
D100: Toàn chi nhánh | F100: =SUM(F95:F99) -> 466 | G100: =SUM(G95:G99) -> 716 | H100: =SUM(H95:H99) -> 857 | I100: =SUM(I95:I99) -> 1061 | J100: =SUM(J95:J99) -> 829 | K100: =SUM(K95:K99) -> 787 | L100: =SUM(L95:L99) -> 839 | M100: =SUM(M95:M99) -> 663 | ... Q100: =SUM(Q95:Q99) -> 719 | R100: =SUMIFS($F100:$Q100,$F$7:$Q$7,"A") -> 9005 | S100: =SUMIFS($F100:$Q100,$F$7:$Q$7,"B") -> 0 | T100: =SUM(R100:S100) -> 9005 | AB100: =SUM(AB95:AB99) -> 11972.8
C102: Maximum capacity (Công suất tối đa ca/tháng)
E103: MRI | F103: =30*9*60/20 -> 810 | G103: =30*9*60/20 -> 810 | H103: =30*9*60/20 -> 810 | I103: =30*9*60/20 -> 810 | J103: =30*9*60/20 -> 810 | K103: =30*9*60/20 -> 810 | L103: =30*9*60/20 -> 810 | M103: =30*9*60/20 -> 810 | ... Q103: =30*9*60/20 -> 810 | T103: =SUM(F103:Q103) -> 9720
E104: Mammo X-Quang | F104: =30*9*60/15 -> 1080 | G104: =30*9*60/15 -> 1080 | H104: =30*9*60/15 -> 1080 | I104: =30*9*60/15 -> 1080 | J104: =30*9*60/15 -> 1080 | K104: =30*9*60/15 -> 1080 | L104: =30*9*60/15 -> 1080 | M104: =30*9*60/15 -> 1080 | ... Q104: =30*9*60/15 -> 1080 | T104: =SUM(F104:Q104) -> 12960
E105: CT | F105: =30*9*60/10 -> 1620 | G105: =30*9*60/10 -> 1620 | H105: =30*9*60/10 -> 1620 | I105: =30*9*60/10 -> 1620 | J105: =30*9*60/10 -> 1620 | K105: =30*9*60/10 -> 1620 | L105: =30*9*60/10 -> 1620 | M105: =30*9*60/10 -> 1620 | ... Q105: =30*9*60/10 -> 1620 | T105: =SUM(F105:Q105) -> 19440
E106: X-Quang | F106: =30*9*60/8 -> 2025 | G106: =30*9*60/8 -> 2025 | H106: =30*9*60/8 -> 2025 | I106: =30*9*60/8 -> 2025 | J106: =30*9*60/8 -> 2025 | K106: =30*9*60/8 -> 2025 | L106: =30*9*60/8 -> 2025 | M106: =30*9*60/8 -> 2025 | ... Q106: =30*9*60/8 -> 2025 | T106: =SUM(F106:Q106) -> 24300
E107: Siêu âm | F107: =30*9*60/10 -> 1620 | G107: =30*9*60/10 -> 1620 | H107: =30*9*60/10 -> 1620 | I107: =30*9*60/10 -> 1620 | J107: =30*9*60/10 -> 1620 | K107: =30*9*60/10 -> 1620 | L107: =30*9*60/10 -> 1620 | M107: =30*9*60/10 -> 1620 | ... Q107: =30*9*60/10 -> 1620 | T107: =SUM(F107:Q107) -> 19440
C108: Utilization rate (Công suất sử dụng)
E109: MRI | F109: =F95/F103 -> 0.31728395 | G109: =G95/G103 -> 0.4962963 | H109: =H95/H103 -> 0.56790123 | I109: =I95/I103 -> 0.66419753 | J109: =J95/J103 -> 0.57160494 | K109: =K95/K103 -> 0.53950617 | L109: =L95/L103 -> 0.55432099 | M109: =M95/M103 -> 0.44197531 | ... Q109: =Q95/Q103 -> 0.4617284 | T109: =T95/T103 -> 0.49290123 | AB109: =AVERAGE(H109:L109,N109) -> 0.55967078
...

Sheet CaMau
G4: =10^6 -> 1000000
B6: BÁO CÁO KẾT QUẢ HOẠT ĐỘNG KINH DOANH CHI NHÁNH
B7: CÀ MAU | F7: A | G7: A | H7: A | I7: A | J7: A | K7: A | L7: A | M7: A | N7: A | O7: A | P7: A | Q7: A
B8: Năm tài chính 2025 | F8: Tháng | R8: ------------------Tổng-------------------- | U8: ------%Doanh thu------- | X8: ------------vs--------------
B9: VND triệu | F9: 1 | G9: 2 | H9: 3 | I9: 4 | J9: 5 | K9: 6 | L9: 7 | M9: 8 | N9: 9 | O9: 10 | P9: 11 | Q9: 12 | R9: Year to date | S9: Year to go | T9: LATEST ESTIMATE | U9: YTD | V9: YTG | W9: LE | X9: Last month | Y9: Last year | Z9: Assumption | AA9: Note | AB9: 2026F
B10: Doanh thu
D11: Chẩn đoán hình ảnh
E12: MRI | F12: =185580000/(10^6) -> 185.58 | G12: =339300000/(10^6) -> 339.3 | H12: =407700000/(10^6) -> 407.7 | I12: =500400000/(10^6) -> 500.4 | J12: =477000000/(10^6) -> 477 | K12: =592830000/(10^6) -> 592.83 | L12: =457650000/(10^6) -> 457.65 | M12: =463500000/(10^6) -> 463.5 | N12: =436530000/(10^6) -> 436.53 | O12: =506580000/(10^6) -> 506.58 | P12: =473700000/(10^6) -> 473.7 | Q12: 353.65 | R12: =SUMIFS($F12:$Q12,$F$7:$Q$7,"A") -> 5194.42 | S12: =SUMIFS($F12:$Q12,$F$7:$Q$7,"B") -> 0 | T12: =SUM(R12:S12) -> 5194.42 | U12: =IFERROR(R12/R$17,"") -> 0.95899581 | V12: =IFERROR(S12/S$17,"") | W12: =IFERROR(T12/T$17,"") -> 0.95899581 | Z12: 0.05 | AA12: vs 2025 | AB12: =AB94*T105/10^6 -> 6413.7849
E13: Mammo X-Quang | F13: =8000000/(10^6) -> 8 | G13: =8000000/(10^6) -> 8 | H13: =25500000/(10^6) -> 25.5 | I13: =15500000/(10^6) -> 15.5 | J13: =16800000/(10^6) -> 16.8 | K13: =39300000/(10^6) -> 39.3 | L13: =19400000/(10^6) -> 19.4 | M13: =24500000/(10^6) -> 24.5 | N13: =14000000/(10^6) -> 14 | O13: =11500000/(10^6) -> 11.5 | P13: =26200000/(10^6) -> 26.2 | Q13: 13.4 | R13: =SUMIFS($F13:$Q13,$F$7:$Q$7,"A") -> 222.1 | S13: =SUMIFS($F13:$Q13,$F$7:$Q$7,"B") -> 0 | T13: =SUM(R13:S13) -> 222.1 | U13: =IFERROR(R13/R$17,"") -> 0.041004187 | V13: =IFERROR(S13/S$17,"") | W13: =IFERROR(T13/T$17,"") -> 0.041004187 | Z13: 0.05 | AA13: vs 2025 | AB13: =AB95*T106/10^6 -> 376.08294
E14: CT | Q14: =P14 -> 0 | R14: =SUMIFS($F14:$Q14,$F$7:$Q$7,"A") -> 0 | S14: =SUMIFS($F14:$Q14,$F$7:$Q$7,"B") -> 0 | T14: =SUM(R14:S14) -> 0 | U14: =IFERROR(R14/R$17,"") -> 0 | V14: =IFERROR(S14/S$17,"") | W14: =IFERROR(T14/T$17,"") -> 0 | Z14: 0.05 | AA14: vs 2025 | AB14: =T14*(1+Z14) -> 0
E15: X-Quang | Q15: =P15 -> 0 | R15: =SUMIFS($F15:$Q15,$F$7:$Q$7,"A") -> 0 | S15: =SUMIFS($F15:$Q15,$F$7:$Q$7,"B") -> 0 | T15: =SUM(R15:S15) -> 0 | U15: =IFERROR(R15/R$17,"") -> 0 | V15: =IFERROR(S15/S$17,"") | W15: =IFERROR(T15/T$17,"") -> 0 | Z15: 0.05 | AA15: vs 2025 | AB15: =T15*(1+Z15) -> 0
E16: Siêu âm | Q16: =P16 -> 0 | R16: =SUMIFS($F16:$Q16,$F$7:$Q$7,"A") -> 0 | S16: =SUMIFS($F16:$Q16,$F$7:$Q$7,"B") -> 0 | T16: =SUM(R16:S16) -> 0 | U16: =IFERROR(R16/R$17,"") -> 0 | V16: =IFERROR(S16/S$17,"") | W16: =IFERROR(T16/T$17,"") -> 0 | Z16: 0.05 | AA16: vs 2025 | AB16: =T16*(1+Z16) -> 0
D17: Tổng- Chẩn đoán hình ảnh | F17: =SUM(F12:F16) -> 193.58 | G17: =SUM(G12:G16) -> 347.3 | H17: =SUM(H12:H16) -> 433.2 | I17: =SUM(I12:I16) -> 515.9 | J17: =SUM(J12:J16) -> 493.8 | K17: =SUM(K12:K16) -> 632.13 | L17: =SUM(L12:L16) -> 477.05 | M17: =SUM(M12:M16) -> 488 | ... Q17: =SUM(Q12:Q16) -> 367.05 | R17: =SUMIFS($F17:$Q17,$F$7:$Q$7,"A") -> 5416.52 | S17: =SUMIFS($F17:$Q17,$F$7:$Q$7,"B") -> 0 | T17: =SUM(R17:S17) -> 5416.52 | U17: =IFERROR(R17/R$17,"") -> 1 | V17: =IFERROR(S17/S$17,"") | W17: =IFERROR(T17/T$17,"") -> 1 | AB17: =SUM(AB12:AB16) -> 6789.8679
D18: Tổng- Khác | R18: =SUMIFS($F18:$Q18,$F$7:$Q$7,"A") -> 0 | S18: =SUMIFS($F18:$Q18,$F$7:$Q$7,"B") -> 0 | T18: =SUM(R18:S18) -> 0 | U18: =IFERROR(R18/R$17,"") -> 0 | V18: =IFERROR(S18/S$17,"") | W18: =IFERROR(T18/T$17,"") -> 0 | AB18: 0
B19: Tổng- Doanh thu | F19: =SUM(F17,F18) -> 193.58 | G19: =SUM(G17,G18) -> 347.3 | H19: =SUM(H17,H18) -> 433.2 | I19: =SUM(I17,I18) -> 515.9 | J19: =SUM(J17,J18) -> 493.8 | K19: =SUM(K17,K18) -> 632.13 | L19: =SUM(L17,L18) -> 477.05 | M19: =SUM(M17,M18) -> 488 | ... Q19: =SUM(Q17,Q18) -> 367.05 | R19: =SUMIFS($F19:$Q19,$F$7:$Q$7,"A") -> 5416.52 | S19: =SUMIFS($F19:$Q19,$F$7:$Q$7,"B") -> 0 | T19: =SUM(R19:S19) -> 5416.52 | U19: =IFERROR(R19/R$17,"") -> 1 | V19: =IFERROR(S19/S$17,"") | W19: =IFERROR(T19/T$17,"") -> 1 | AB19: =SUM(AB17,AB18) -> 6789.8679
B20: Giảm trừ doanh thu | F20: =SUBTOTAL(9,F21:F25) -> 0 | G20: =SUBTOTAL(9,G21:G25) -> 0 | H20: =SUBTOTAL(9,H21:H25) -> 0 | I20: =SUBTOTAL(9,I21:I25) -> 0 | J20: =SUBTOTAL(9,J21:J25) -> 0.45 | K20: =SUBTOTAL(9,K21:K25) -> 0.45 | L20: =SUBTOTAL(9,L21:L25) -> 0 | M20: =SUBTOTAL(9,M21:M25) -> 0 | ... Q20: =SUBTOTAL(9,Q21:Q25) -> 0 | R20: =SUMIFS($F20:$Q20,$F$7:$Q$7,"A") -> 0.9 | S20: =SUMIFS($F20:$Q20,$F$7:$Q$7,"B") -> 0 | T20: =SUM(R20:S20) -> 0.9 | U20: =IFERROR(R20/R$17,"") -> 0.00016615835 | V20: =IFERROR(S20/S$17,"") | W20: =IFERROR(T20/T$17,"") -> 0.00016615835 | AB20: 0
E21: MRI | J21: 0.45 | K21: 0.45 | Q21: 0
E22: Mammo X-Quang
E23: CT
E24: X-Quang
E25: Siêu âm
B26: Biến phí
C27: Vật tư tiêu hao | F27: 0.89703358 | G27: 1.5717934 | H27: 2.1354162 | I27: 2.35769 | J27: 2.3021216 | K27: 3.2547236 | L27: 2.2862449 | M27: 2.3735667 | N27: 2.0639711 | O27: 2.3497517 | P27: 2.4847036 | Q27: 1.7146837 | R27: =SUMIFS($F27:$Q27,$F$7:$Q$7,"A") -> 25.7917 | S27: =SUMIFS($F27:$Q27,$F$7:$Q$7,"B") -> 0 | T27: =SUM(R27:S27) -> 25.7917 | U27: =IFERROR(R27/R$17,"") -> 0.0047616735 | V27: =IFERROR(S27/S$17,"") | W27: =IFERROR(T27/T$17,"") -> 0.0047616735 | Z27: =W27 -> 0.0047616735 | AA27: % doanh thu | AB27: =Z27*$AB$17 -> 32.331134
C28: Chi phí đọc kết quả online | F28: =12345000/(10^6) -> 12.345 | G28: =21890000/(10^6) -> 21.89 | H28: =28130000/(10^6) -> 28.13 | I28: =32450000/(10^6) -> 32.45 | J28: =31425000/(10^6) -> 31.425 | K28: =42255000/(10^6) -> 42.255 | L28: =30920000/(10^6) -> 30.92 | M28: =32180000/(10^6) -> 32.18 | N28: =28825000/(10^6) -> 28.825 | O28: =33005000/(10^6) -> 33.005 | P28: =33385000/(10^6) -> 33.385 | Q28: 23.695 | R28: =SUMIFS($F28:$Q28,$F$7:$Q$7,"A") -> 350.505 | S28: =SUMIFS($F28:$Q28,$F$7:$Q$7,"B") -> 0 | T28: =SUM(R28:S28) -> 350.505 | U28: =IFERROR(R28/R$17,"") -> 0.064710368 | V28: =IFERROR(S28/S$17,"") | W28: =IFERROR(T28/T$17,"") -> 0.064710368 | Z28: =W28 -> 0.064710368 | AA28: % doanh thu | AB28: =Z28*$AB$17 -> 439.37484
C29: Tiền thuốc | Q29: =P29 -> 0 | R29: =SUMIFS($F29:$Q29,$F$7:$Q$7,"A") -> 0 | S29: =SUMIFS($F29:$Q29,$F$7:$Q$7,"B") -> 0 | T29: =SUM(R29:S29) -> 0 | U29: =IFERROR(R29/R$17,"") -> 0 | V29: =IFERROR(S29/S$17,"") | W29: =IFERROR(T29/T$17,"") -> 0 | Z29: =W29 -> 0 | AA29: % doanh thu | AB29: =Z29*$AB$17 -> 0
C30: Tư vấn chuyên môn | F30: =31300000/(10^6) -> 31.3 | G30: =55900000/(10^6) -> 55.9 | H30: =69900000/(10^6) -> 69.9 | I30: =82700000/(10^6) -> 82.7 | J30: =76000000/(10^6) -> 76 | K30: =75350000/(10^6) -> 75.35 | L30: =64940000/(10^6) -> 64.94 | M30: =69930000/(10^6) -> 69.93 | N30: =63410000/(10^6) -> 63.41 | O30: =76000000/(10^6) -> 76 | P30: =69370000/(10^6) -> 69.37 | Q30: 52.35 | R30: =SUMIFS($F30:$Q30,$F$7:$Q$7,"A") -> 787.15 | S30: =SUMIFS($F30:$Q30,$F$7:$Q$7,"B") -> 0 | T30: =SUM(R30:S30) -> 787.15 | U30: =IFERROR(R30/R$17,"") -> 0.14532393 | V30: =IFERROR(S30/S$17,"") | W30: =IFERROR(T30/T$17,"") -> 0.14532393 | Z30: =W30 -> 0.14532393 | AA30: % doanh thu | AB30: =Z30*$AB$17 -> 986.73032
C31: Thưởng hiệu quả kinh doanh nhân viên | Q31: =P31 -> 0 | R31: =SUMIFS($F31:$Q31,$F$7:$Q$7,"A") -> 0 | S31: =SUMIFS($F31:$Q31,$F$7:$Q$7,"B") -> 0 | T31: =SUM(R31:S31) -> 0 | U31: =IFERROR(R31/R$17,"") -> 0 | V31: =IFERROR(S31/S$17,"") | W31: =IFERROR(T31/T$17,"") -> 0 | Z31: =W31 -> 0 | AA31: % doanh thu | AB31: =Z31*$AB$17 -> 0
C32: Truyền thông marketing | Q32: =P32 -> 0 | R32: =SUMIFS($F32:$Q32,$F$7:$Q$7,"A") -> 0 | S32: =SUMIFS($F32:$Q32,$F$7:$Q$7,"B") -> 0 | T32: =SUM(R32:S32) -> 0 | U32: =IFERROR(R32/R$17,"") -> 0 | V32: =IFERROR(S32/S$17,"") | W32: =IFERROR(T32/T$17,"") -> 0 | Z32: 0.01 | AA32: % doanh thu | AB32: =Z32*$AB$17 -> 67.898679
B33: Tổng- Biến phí | F33: =SUM(F27:F32) -> 44.542034 | G33: =SUM(G27:G32) -> 79.361793 | H33: =SUM(H27:H32) -> 100.16542 | I33: =SUM(I27:I32) -> 117.50769 | J33: =SUM(J27:J32) -> 109.72712 | K33: =SUM(K27:K32) -> 120.85972 | L33: =SUM(L27:L32) -> 98.146245 | M33: =SUM(M27:M32) -> 104.48357 | ... Q33: =SUM(Q27:Q32) -> 77.759684 | R33: =SUMIFS($F33:$Q33,$F$7:$Q$7,"A") -> 1163.4467 | S33: =SUMIFS($F33:$Q33,$F$7:$Q$7,"B") -> 0 | T33: =SUM(R33:S33) -> 1163.4467 | U33: =IFERROR(R33/R$17,"") -> 0.21479598 | V33: =IFERROR(S33/S$17,"") | W33: =IFERROR(T33/T$17,"") -> 0.21479598 | AB33: =SUM(AB27:AB32) -> 1526.335
B34: Lãi trên biến phí | F34: =F19-F33-F20 -> 149.03797 | G34: =G19-G33-G20 -> 267.93821 | H34: =H19-H33-H20 -> 333.03458 | I34: =I19-I33-I20 -> 398.39231 | J34: =J19-J33-J20 -> 383.62288 | K34: =K19-K33-K20 -> 510.82028 | L34: =L19-L33-L20 -> 378.90376 | M34: =M19-M33-M20 -> 383.51643 | ... Q34: =Q19-Q33-Q20 -> 289.29032 | R34: =SUMIFS($F34:$Q34,$F$7:$Q$7,"A") -> 4252.1733 | S34: =SUMIFS($F34:$Q34,$F$7:$Q$7,"B") -> 0 | T34: =SUM(R34:S34) -> 4252.1733 | U34: =IFERROR(R34/R$17,"") -> 0.78503787 | V34: =IFERROR(S34/S$17,"") | W34: =IFERROR(T34/T$17,"") -> 0.78503787 | AB34: =AB19-AB33-AB20 -> 5263.5329
B35: Định phí | R35: =SUMIFS($F35:$Q35,$F$7:$Q$7,"A") -> 0 | S35: =SUMIFS($F35:$Q35,$F$7:$Q$7,"B") -> 0 | T35: =SUM(R35:S35) -> 0 | U35: =IFERROR(R35/R$17,"") -> 0 | V35: =IFERROR(S35/S$17,"") | W35: =IFERROR(T35/T$17,"") -> 0
C36: Chi phí nhân viên | F36: =74788325/(10^6) -> 74.788325 | G36: =60580772/(10^6) -> 60.580772 | H36: =59675998/(10^6) -> 59.675998 | I36: =56324863/(10^6) -> 56.324863 | J36: =57694576/(10^6) -> 57.694576 | K36: =58799179/(10^6) -> 58.799179 | L36: =63526899/(10^6) -> 63.526899 | M36: =62426611/(10^6) -> 62.426611 | N36: =63625989/(10^6) -> 63.625989 | O36: =67977071/(10^6) -> 67.977071 | P36: =68159326/(10^6) -> 68.159326 | Q36: 68.448783 | R36: =SUMIFS($F36:$Q36,$F$7:$Q$7,"A") -> 762.02839 | S36: =SUMIFS($F36:$Q36,$F$7:$Q$7,"B") -> 0 | T36: =SUM(R36:S36) -> 762.02839 | U36: =IFERROR(R36/R$17,"") -> 0.14068597 | V36: =IFERROR(S36/S$17,"") | W36: =IFERROR(T36/T$17,"") -> 0.14068597 | Z36: 0.02 | AA36: vs 2025 | AB36: =T36*(1+Z36) -> 777.26896
C37: Chi phí thuê địa điểm | F37: =20000000/(10^6) -> 20 | G37: =20000000/(10^6) -> 20 | H37: =20000000/(10^6) -> 20 | I37: =20000000/(10^6) -> 20 | J37: =20000000/(10^6) -> 20 | K37: =20000000/(10^6) -> 20 | L37: =20000000/(10^6) -> 20 | M37: =20000000/(10^6) -> 20 | ... Q37: =20000000/(10^6) -> 20 | R37: =SUMIFS($F37:$Q37,$F$7:$Q$7,"A") -> 240 | S37: =SUMIFS($F37:$Q37,$F$7:$Q$7,"B") -> 0 | T37: =SUM(R37:S37) -> 240 | U37: =IFERROR(R37/R$17,"") -> 0.044308892 | V37: =IFERROR(S37/S$17,"") | W37: =IFERROR(T37/T$17,"") -> 0.044308892 | Z37: 0.02 | AA37: vs 2025 | AB37: =T37*(1+Z37) -> 244.8
C38: Chi phí bảo dưỡng bảo trì máy | R38: =SUMIFS($F38:$Q38,$F$7:$Q$7,"A") -> 0 | S38: =SUMIFS($F38:$Q38,$F$7:$Q$7,"B") -> 0 | T38: =SUM(R38:S38) -> 0 | U38: =IFERROR(R38/R$17,"") -> 0 | V38: =IFERROR(S38/S$17,"") | W38: =IFERROR(T38/T$17,"") -> 0 | AA38: Đề xuất PKT | AB38: ='Site list'!Q5 -> 250.30125
C39: Chi phí vận hành thường xuyên | F39: 43.601338 | G39: 40.172091 | H39: 40.0567 | I39: 47.423887 | J39: 35.223744 | K39: 39.25273 | L39: 35.016929 | M39: 37.277475 | N39: 43.818602 | O39: 34.01631 | P39: 34.076323 | Q39: 40.820495 | R39: =SUMIFS($F39:$Q39,$F$7:$Q$7,"A") -> 470.75663 | S39: =SUMIFS($F39:$Q39,$F$7:$Q$7,"B") -> 0 | T39: =SUM(R39:S39) -> 470.75663 | U39: =IFERROR(R39/R$17,"") -> 0.086911269 | V39: =IFERROR(S39/S$17,"") | W39: =IFERROR(T39/T$17,"") -> 0.086911269 | AA39: không đổi | AB39: =T39 -> 470.75663
C40: Chi phí khác | F40: 50.7629 | G40: 11.6332 | H40: 0.7867 | I40: 67.058228 | J40: 8.3632 | K40: 1.713334 | L40: 4.7722 | M40: 29.473866 | N40: 2.327242 | O40: 1.266691 | P40: 0.6932 | Q40: 5.550515 | R40: =SUMIFS($F40:$Q40,$F$7:$Q$7,"A") -> 184.40128 | S40: =SUMIFS($F40:$Q40,$F$7:$Q$7,"B") -> 0 | T40: =SUM(R40:S40) -> 184.40128 | U40: =IFERROR(R40/R$17,"") -> 0.034044234 | V40: =IFERROR(S40/S$17,"") | W40: =IFERROR(T40/T$17,"") -> 0.034044234 | AA40: không đổi | AB40: =T40 -> 184.40128
B41: Tổng- Định phí | F41: =SUM(F36:F40) -> 189.15256 | G41: =SUM(G36:G40) -> 132.38606 | H41: =SUM(H36:H40) -> 120.5194 | I41: =SUM(I36:I40) -> 190.80698 | J41: =SUM(J36:J40) -> 121.28152 | K41: =SUM(K36:K40) -> 119.76524 | L41: =SUM(L36:L40) -> 123.31603 | M41: =SUM(M36:M40) -> 149.17795 | ... Q41: =SUM(Q36:Q40) -> 134.81979 | R41: =SUMIFS($F41:$Q41,$F$7:$Q$7,"A") -> 1657.1863 | S41: =SUMIFS($F41:$Q41,$F$7:$Q$7,"B") -> 0 | T41: =SUM(R41:S41) -> 1657.1863 | U41: =IFERROR(R41/R$17,"") -> 0.30595037 | V41: =IFERROR(S41/S$17,"") | W41: =IFERROR(T41/T$17,"") -> 0.30595037 | AB41: =SUM(AB36:AB40) -> 1927.5281
B42: EBITDA | F42: =F34-F41 -> -40.114597 | G42: =G34-G41 -> 135.55214 | H42: =H34-H41 -> 212.51519 | I42: =I34-I41 -> 207.58533 | J42: =J34-J41 -> 262.34136 | K42: =K34-K41 -> 391.05503 | L42: =L34-L41 -> 255.58773 | M42: =M34-M41 -> 234.33848 | ... Q42: =Q34-Q41 -> 154.47052 | R42: =SUMIFS($F42:$Q42,$F$7:$Q$7,"A") -> 2594.987 | S42: =SUMIFS($F42:$Q42,$F$7:$Q$7,"B") -> 0 | T42: =SUM(R42:S42) -> 2594.987 | U42: =IFERROR(R42/R$17,"") -> 0.4790875 | V42: =IFERROR(S42/S$17,"") | W42: =IFERROR(T42/T$17,"") -> 0.4790875 | AB42: =AB34-AB41 -> 3336.0048
B43: EBITDA về công ty mẹ | R43: =SUMIFS($F43:$Q43,$F$7:$Q$7,"A") -> 0 | S43: =SUMIFS($F43:$Q43,$F$7:$Q$7,"B") -> 0 | T43: =SUM(R43:S43) -> 0 | U43: =IFERROR(R43/R$17,"") -> 0 | V43: =IFERROR(S43/S$17,"") | W43: =IFERROR(T43/T$17,"") -> 0 | Z43: ='Site list'!H5 -> 0.55 | AA43: Tỷ lệ sở hữu | AB43: =AB42*Z43 -> 1834.8026
R44: =SUMIFS($F44:$Q44,$F$7:$Q$7,"A") -> 0 | S44: =SUMIFS($F44:$Q44,$F$7:$Q$7,"B") -> 0 | T44: =SUM(R44:S44) -> 0 | U44: =IFERROR(R44/R$17,"") -> 0 | V44: =IFERROR(S44/S$17,"") | W44: =IFERROR(T44/T$17,"") -> 0
C45: Chi phí khấu hao máy | F45: =SUM(F46:F50) -> 160 | G45: =SUM(G46:G50) -> 160 | H45: =SUM(H46:H50) -> 160 | I45: =SUM(I46:I50) -> 160 | J45: =SUM(J46:J50) -> 160 | K45: =SUM(K46:K50) -> 160 | L45: =SUM(L46:L50) -> 160 | M45: =SUM(M46:M50) -> 160 | ... P45: =SUM(P46:P50) -> 160 | Q45: =P45 -> 160 | R45: =SUMIFS($F45:$Q45,$F$7:$Q$7,"A") -> 1920 | S45: =SUMIFS($F45:$Q45,$F$7:$Q$7,"B") -> 0 | T45: =SUM(R45:S45) -> 1920 | U45: =IFERROR(R45/R$17,"") -> 0.35447114 | V45: =IFERROR(S45/S$17,"") | W45: =IFERROR(T45/T$17,"") -> 0.35447114 | AA45: không đổi | AB45: =T45 -> 1920
E46: MRI | F46: 160 | G46: 160 | H46: 160 | I46: 160 | J46: 160 | K46: 160 | L46: 160 | M46: 160 | N46: 160 | O46: 160 | P46: 160 | Q46: =P46 -> 160 | R46: =SUMIFS($F46:$Q46,$F$7:$Q$7,"A") -> 1920 | S46: =SUMIFS($F46:$Q46,$F$7:$Q$7,"B") -> 0 | T46: =SUM(R46:S46) -> 1920 | U46: =IFERROR(R46/R$17,"") -> 0.35447114 | V46: =IFERROR(S46/S$17,"") | W46: =IFERROR(T46/T$17,"") -> 0.35447114 | AA46: không đổi | AB46: =T46 -> 1920
E47: Mammo X-Quang | Q47: =P47 -> 0 | R47: =SUMIFS($F47:$Q47,$F$7:$Q$7,"A") -> 0 | S47: =SUMIFS($F47:$Q47,$F$7:$Q$7,"B") -> 0 | T47: =SUM(R47:S47) -> 0 | U47: =IFERROR(R47/R$17,"") -> 0 | V47: =IFERROR(S47/S$17,"") | W47: =IFERROR(T47/T$17,"") -> 0 | AA47: không đổi | AB47: =T47 -> 0
E48: CT | Q48: =P48 -> 0 | R48: =SUMIFS($F48:$Q48,$F$7:$Q$7,"A") -> 0 | S48: =SUMIFS($F48:$Q48,$F$7:$Q$7,"B") -> 0 | T48: =SUM(R48:S48) -> 0 | U48: =IFERROR(R48/R$17,"") -> 0 | V48: =IFERROR(S48/S$17,"") | W48: =IFERROR(T48/T$17,"") -> 0 | AA48: không đổi | AB48: =T48 -> 0
E49: X-Quang | Q49: =P49 -> 0 | R49: =SUMIFS($F49:$Q49,$F$7:$Q$7,"A") -> 0 | S49: =SUMIFS($F49:$Q49,$F$7:$Q$7,"B") -> 0 | T49: =SUM(R49:S49) -> 0 | U49: =IFERROR(R49/R$17,"") -> 0 | V49: =IFERROR(S49/S$17,"") | W49: =IFERROR(T49/T$17,"") -> 0 | AA49: không đổi | AB49: =T49 -> 0
E50: Siêu âm | Q50: =P50 -> 0 | R50: =SUMIFS($F50:$Q50,$F$7:$Q$7,"A") -> 0 | S50: =SUMIFS($F50:$Q50,$F$7:$Q$7,"B") -> 0 | T50: =SUM(R50:S50) -> 0 | U50: =IFERROR(R50/R$17,"") -> 0 | V50: =IFERROR(S50/S$17,"") | W50: =IFERROR(T50/T$17,"") -> 0 | AA50: không đổi | AB50: =T50 -> 0
C51: Chi phí khấu hao khác | F51: 24.695902 | G51: 24.695902 | H51: 24.695902 | I51: 24.695902 | J51: 24.695902 | K51: 24.695902 | L51: 24.695902 | M51: 24.695902 | N51: 24.695902 | O51: 24.695902 | P51: 24.695902 | Q51: 24.695902 | R51: =SUMIFS($F51:$Q51,$F$7:$Q$7,"A") -> 296.35082 | S51: =SUMIFS($F51:$Q51,$F$7:$Q$7,"B") -> 0 | T51: =SUM(R51:S51) -> 296.35082 | U51: =IFERROR(R51/R$17,"") -> 0.054712403 | V51: =IFERROR(S51/S$17,"") | W51: =IFERROR(T51/T$17,"") -> 0.054712403 | AA51: không đổi | AB51: =T51 -> 296.35082
C52: Lợi nhuận khác | Q52: 0 | R52: =SUMIFS($F52:$Q52,$F$7:$Q$7,"A") -> 0 | S52: =SUMIFS($F52:$Q52,$F$7:$Q$7,"B") -> 0 | T52: =SUM(R52:S52) -> 0 | U52: =IFERROR(R52/R$17,"") -> 0 | V52: =IFERROR(S52/S$17,"") | W52: =IFERROR(T52/T$17,"") -> 0 | AB52: 0
C53: Chi phí tài chính | F53: =(62429642/(10^6))*-1 -> -62.429642 | G53: =(91882058/(-10^6))*-1 -> -91.882058 | H53: =(73206544/(-10^6))*-1 -> -73.206544 | I53: =(40194717/(-10^6))*-1 -> -40.194717 | J53: =(69127309/(-10^6))*-1 -> -69.127309 | K53: =(69070040/(-10^6))*-1 -> -69.07004 | L53: =(57499275/(-10^6))*-1 -> -57.499275 | M53: =(64872139/(-10^6))*-1 -> -64.872139 | N53: =(64841912/(-10^6))*-1 -> -64.841912 | O53: =(57971873/(-10^6))*-1 -> -57.971873 | P53: =(59886608/(-10^6))*-1 -> -59.886608 | Q53: -61.880138 | R53: =SUMIFS($F53:$Q53,$F$7:$Q$7,"A") -> -772.86225 | S53: =SUMIFS($F53:$Q53,$F$7:$Q$7,"B") -> 0 | T53: =SUM(R53:S53) -> -772.86225 | U53: =IFERROR(R53/R$17,"") -> -0.14268613 | V53: =IFERROR(S53/S$17,"") | W53: =IFERROR(T53/T$17,"") -> -0.14268613 | AB53: =Z53*AB42 -> 0
B54: Lợi nhuận/(Lỗ) trước thuế | F54: =F42-F45-F51+SUM(F52:F53) -> -287.24014 | G54: =G42-G45-G51+SUM(G52:G53) -> -141.02582 | H54: =H42-H45-H51+SUM(H52:H53) -> -45.38726 | I54: =I42-I45-I51+SUM(I52:I53) -> -17.305287 | J54: =J42-J45-J51+SUM(J52:J53) -> 8.518147 | K54: =K42-K45-K51+SUM(K52:K53) -> 137.28909 | L54: =L42-L45-L51+SUM(L52:L53) -> 13.39255 | M54: =M42-M45-M51+SUM(M52:M53) -> -15.22956 | ... Q54: =Q42-Q45-Q51+SUM(Q52:Q53) -> -92.105517 | R54: =SUMIFS($F54:$Q54,$F$7:$Q$7,"A") -> -394.22607 | S54: =SUMIFS($F54:$Q54,$F$7:$Q$7,"B") -> 0 | T54: =SUM(R54:S54) -> -394.22607 | U54: =IFERROR(R54/R$17,"") -> -0.072782169 | V54: =IFERROR(S54/S$17,"") | W54: =IFERROR(T54/T$17,"") -> -0.072782169 | AB54: =AB42-AB45-AB51+SUM(AB52:AB53) -> 1119.654
C55: Chi phí thuế TNDN | F55: =IF(F54<0,0,F54*20%) -> 0 | G55: =IF(G54<0,0,G54*20%) -> 0 | H55: =IF(H54<0,0,H54*20%) -> 0 | I55: =IF(I54<0,0,I54*20%) -> 0 | J55: =IF(J54<0,0,J54*20%) -> 1.7036294 | K55: =IF(K54<0,0,K54*20%) -> 27.457818 | L55: =IF(L54<0,0,L54*20%) -> 2.67851 | M55: =IF(M54<0,0,M54*20%) -> 0 | ... Q55: =IF(Q54<0,0,Q54*20%) -> 0 | R55: =SUMIFS($F55:$Q55,$F$7:$Q$7,"A") -> 45.429225 | S55: =SUMIFS($F55:$Q55,$F$7:$Q$7,"B") -> 0 | T55: =SUM(R55:S55) -> 45.429225 | U55: =IFERROR(R55/R$17,"") -> 0.008387161 | V55: =IFERROR(S55/S$17,"") | W55: =IFERROR(T55/T$17,"") -> 0.008387161 | AB55: =AB54*20% -> 223.93079
B56: Lợi nhuận sau thuế | F56: =F54-F55 -> -287.24014 | G56: =G54-G55 -> -141.02582 | H56: =H54-H55 -> -45.38726 | I56: =I54-I55 -> -17.305287 | J56: =J54-J55 -> 6.8145176 | K56: =K54-K55 -> 109.83127 | L56: =L54-L55 -> 10.71404 | M56: =M54-M55 -> -15.22956 | ... Q56: =Q54-Q55 -> -92.105517 | R56: =SUMIFS($F56:$Q56,$F$7:$Q$7,"A") -> -439.6553 | S56: =SUMIFS($F56:$Q56,$F$7:$Q$7,"B") -> 0 | T56: =SUM(R56:S56) -> -439.6553 | U56: =IFERROR(R56/R$17,"") -> -0.08116933 | V56: =IFERROR(S56/S$17,"") | W56: =IFERROR(T56/T$17,"") -> -0.08116933 | AB56: =AB54-AB55 -> 895.72316
C57: Cổ đông thiểu số | R57: =SUMIFS($F57:$Q57,$F$7:$Q$7,"A") -> 0 | S57: =SUMIFS($F57:$Q57,$F$7:$Q$7,"B") -> 0 | T57: =SUM(R57:S57) -> 0 | U57: =IFERROR(R57/R$17,"") -> 0 | V57: =IFERROR(S57/S$17,"") | W57: =IFERROR(T57/T$17,"") -> 0 | Z57: 0.14963325 | AB57: =AB56*Z57 -> 134.02997
B58: CÁC CHỈ TIÊU HIỆU QUẢ HOẠT ĐỘNG | R58: =SUMIFS($F58:$Q58,$F$7:$Q$7,"A") -> 0 | S58: =SUMIFS($F58:$Q58,$F$7:$Q$7,"B") -> 0 | T58: =SUM(R58:S58) -> 0 | U58: =IFERROR(R58/R$17,"") -> 0 | V58: =IFERROR(S58/S$17,"") | W58: =IFERROR(T58/T$17,"") -> 0
C59: Số ca/tháng | R59: =SUMIFS($F59:$Q59,$F$7:$Q$7,"A") -> 0 | S59: =SUMIFS($F59:$Q59,$F$7:$Q$7,"B") -> 0 | T59: =SUM(R59:S59) -> 0 | U59: =IFERROR(R59/R$17,"") -> 0 | V59: =IFERROR(S59/S$17,"") | W59: =IFERROR(T59/T$17,"") -> 0
E60: MRI | F60: 257 | G60: 402 | H60: 460 | I60: 538 | J60: 463 | K60: 437 | L60: 449 | M60: 358 | N60: 373 | O60: 353 | P60: 327 | R60: =SUMIFS($F60:$Q60,$F$7:$Q$7,"A") -> 4417 | S60: =SUMIFS($F60:$Q60,$F$7:$Q$7,"B") -> 0 | T60: =SUM(R60:S60) -> 4417 | U60: =IFERROR(R60/R$17,"") -> 0.81546823 | V60: =IFERROR(S60/S$17,"") | W60: =IFERROR(T60/T$17,"") -> 0.81546823
E61: Mammo X-Quang | F61: 7 | G61: 16 | H61: 17 | I61: 37 | J61: 22 | K61: 18 | L61: 21 | M61: 28 | N61: 20 | O61: 18 | P61: 17 | R61: =SUMIFS($F61:$Q61,$F$7:$Q$7,"A") -> 221 | S61: =SUMIFS($F61:$Q61,$F$7:$Q$7,"B") -> 0 | T61: =SUM(R61:S61) -> 221 | U61: =IFERROR(R61/R$17,"") -> 0.040801105 | V61: =IFERROR(S61/S$17,"") | W61: =IFERROR(T61/T$17,"") -> 0.040801105
E62: CT | F62: 108 | G62: 143 | H62: 166 | I62: 201 | J62: 134 | K62: 106 | L62: 81 | M62: 76 | N62: 82 | O62: 92 | P62: 83 | R62: =SUMIFS($F62:$Q62,$F$7:$Q$7,"A") -> 1272 | S62: =SUMIFS($F62:$Q62,$F$7:$Q$7,"B") -> 0 | T62: =SUM(R62:S62) -> 1272 | U62: =IFERROR(R62/R$17,"") -> 0.23483713 | V62: =IFERROR(S62/S$17,"") | W62: =IFERROR(T62/T$17,"") -> 0.23483713
E63: X-Quang | F63: 58 | G63: 83 | H63: 147 | I63: 228 | J63: 168 | K63: 188 | L63: 203 | M63: 155 | N63: 167 | O63: 144 | P63: 187 | R63: =SUMIFS($F63:$Q63,$F$7:$Q$7,"A") -> 1728 | S63: =SUMIFS($F63:$Q63,$F$7:$Q$7,"B") -> 0 | T63: =SUM(R63:S63) -> 1728 | U63: =IFERROR(R63/R$17,"") -> 0.31902402 | V63: =IFERROR(S63/S$17,"") | W63: =IFERROR(T63/T$17,"") -> 0.31902402
E64: Siêu âm | F64: 36 | G64: 72 | H64: 67 | I64: 57 | J64: 42 | K64: 38 | L64: 85 | M64: 46 | N64: 79 | O64: 82 | P64: 44 | R64: =SUMIFS($F64:$Q64,$F$7:$Q$7,"A") -> 648 | S64: =SUMIFS($F64:$Q64,$F$7:$Q$7,"B") -> 0 | T64: =SUM(R64:S64) -> 648 | U64: =IFERROR(R64/R$17,"") -> 0.11963401 | V64: =IFERROR(S64/S$17,"") | W64: =IFERROR(T64/T$17,"") -> 0.11963401
D65: Toàn chi nhánh | F65: =SUM(F60:F64) -> 466 | G65: =SUM(G60:G64) -> 716 | H65: =SUM(H60:H64) -> 857 | I65: =SUM(I60:I64) -> 1061 | J65: =SUM(J60:J64) -> 829 | K65: =SUM(K60:K64) -> 787 | L65: =SUM(L60:L64) -> 839 | M65: =SUM(M60:M64) -> 663 | ... P65: =SUM(P60:P64) -> 658 | R65: =SUMIFS($F65:$Q65,$F$7:$Q$7,"A") -> 8286 | S65: =SUMIFS($F65:$Q65,$F$7:$Q$7,"B") -> 0 | T65: =SUM(R65:S65) -> 8286 | U65: =IFERROR(R65/R$17,"") -> 1.5297645 | V65: =IFERROR(S65/S$17,"") | W65: =IFERROR(T65/T$17,"") -> 1.5297645
R66: =SUMIFS($F66:$Q66,$F$7:$Q$7,"A") -> 0 | S66: =SUMIFS($F66:$Q66,$F$7:$Q$7,"B") -> 0 | T66: =SUM(R66:S66) -> 0 | U66: =IFERROR(R66/R$17,"") -> 0 | V66: =IFERROR(S66/S$17,"") | W66: =IFERROR(T66/T$17,"") -> 0
C67: Số ngày làm việc/tháng | F67: 30 | G67: =28-7 -> 21 | H67: 31 | I67: =30-2 -> 28 | J67: 31 | K67: 30 | L67: 31 | M67: 31 | N67: =30-2 -> 28 | O67: 31 | P67: 30 | R67: =SUMIFS($F67:$Q67,$F$7:$Q$7,"A") -> 322 | S67: =SUMIFS($F67:$Q67,$F$7:$Q$7,"B") -> 0 | T67: =SUM(R67:S67) -> 322 | U67: =IFERROR(R67/R$17,"") -> 0.059447764 | V67: =IFERROR(S67/S$17,"") | W67: =IFERROR(T67/T$17,"") -> 0.059447764
R68: =SUMIFS($F68:$Q68,$F$7:$Q$7,"A") -> 0 | S68: =SUMIFS($F68:$Q68,$F$7:$Q$7,"B") -> 0 | T68: =SUM(R68:S68) -> 0 | U68: =IFERROR(R68/R$17,"") -> 0 | V68: =IFERROR(S68/S$17,"") | W68: =IFERROR(T68/T$17,"") -> 0
C69: Doanh thu TB/ngày/máy | R69: =SUMIFS($F69:$Q69,$F$7:$Q$7,"A") -> 0 | S69: =SUMIFS($F69:$Q69,$F$7:$Q$7,"B") -> 0 | T69: =SUM(R69:S69) -> 0 | U69: =IFERROR(R69/R$17,"") -> 0 | V69: =IFERROR(S69/S$17,"") | W69: =IFERROR(T69/T$17,"") -> 0
E70: MRI | R70: =SUMIFS($F70:$Q70,$F$7:$Q$7,"A") -> 0 | S70: =SUMIFS($F70:$Q70,$F$7:$Q$7,"B") -> 0 | T70: =SUM(R70:S70) -> 0 | U70: =IFERROR(R70/R$17,"") -> 0 | V70: =IFERROR(S70/S$17,"") | W70: =IFERROR(T70/T$17,"") -> 0
E71: Mammo X-Quang | R71: =SUMIFS($F71:$Q71,$F$7:$Q$7,"A") -> 0 | S71: =SUMIFS($F71:$Q71,$F$7:$Q$7,"B") -> 0 | T71: =SUM(R71:S71) -> 0 | U71: =IFERROR(R71/R$17,"") -> 0 | V71: =IFERROR(S71/S$17,"") | W71: =IFERROR(T71/T$17,"") -> 0
E72: CT | R72: =SUMIFS($F72:$Q72,$F$7:$Q$7,"A") -> 0 | S72: =SUMIFS($F72:$Q72,$F$7:$Q$7,"B") -> 0 | T72: =SUM(R72:S72) -> 0 | U72: =IFERROR(R72/R$17,"") -> 0 | V72: =IFERROR(S72/S$17,"") | W72: =IFERROR(T72/T$17,"") -> 0
E73: X-Quang | R73: =SUMIFS($F73:$Q73,$F$7:$Q$7,"A") -> 0 | S73: =SUMIFS($F73:$Q73,$F$7:$Q$7,"B") -> 0 | T73: =SUM(R73:S73) -> 0 | U73: =IFERROR(R73/R$17,"") -> 0 | V73: =IFERROR(S73/S$17,"") | W73: =IFERROR(T73/T$17,"") -> 0
E74: Siêu âm | R74: =SUMIFS($F74:$Q74,$F$7:$Q$7,"A") -> 0 | S74: =SUMIFS($F74:$Q74,$F$7:$Q$7,"B") -> 0 | T74: =SUM(R74:S74) -> 0 | U74: =IFERROR(R74/R$17,"") -> 0 | V74: =IFERROR(S74/S$17,"") | W74: =IFERROR(T74/T$17,"") -> 0
D75: Toàn chi nhánh | R75: =SUMIFS($F75:$Q75,$F$7:$Q$7,"A") -> 0 | S75: =SUMIFS($F75:$Q75,$F$7:$Q$7,"B") -> 0 | T75: =SUM(R75:S75) -> 0 | U75: =IFERROR(R75/R$17,"") -> 0 | V75: =IFERROR(S75/S$17,"") | W75: =IFERROR(T75/T$17,"") -> 0
C76: Maximum capacity (Công suất tối đa ca/ngày) | R76: =SUMIFS($F76:$Q76,$F$7:$Q$7,"A") -> 0 | S76: =SUMIFS($F76:$Q76,$F$7:$Q$7,"B") -> 0 | T76: =SUM(R76:S76) -> 0 | U76: =IFERROR(R76/R$17,"") -> 0 | V76: =IFERROR(S76/S$17,"") | W76: =IFERROR(T76/T$17,"") -> 0
E77: MRI | R77: =SUMIFS($F77:$Q77,$F$7:$Q$7,"A") -> 0 | S77: =SUMIFS($F77:$Q77,$F$7:$Q$7,"B") -> 0 | T77: =SUM(R77:S77) -> 0 | U77: =IFERROR(R77/R$17,"") -> 0 | V77: =IFERROR(S77/S$17,"") | W77: =IFERROR(T77/T$17,"") -> 0
E78: Mammo X-Quang | R78: =SUMIFS($F78:$Q78,$F$7:$Q$7,"A") -> 0 | S78: =SUMIFS($F78:$Q78,$F$7:$Q$7,"B") -> 0 | T78: =SUM(R78:S78) -> 0 | U78: =IFERROR(R78/R$17,"") -> 0 | V78: =IFERROR(S78/S$17,"") | W78: =IFERROR(T78/T$17,"") -> 0
E79: CT | R79: =SUMIFS($F79:$Q79,$F$7:$Q$7,"A") -> 0 | S79: =SUMIFS($F79:$Q79,$F$7:$Q$7,"B") -> 0 | T79: =SUM(R79:S79) -> 0 | U79: =IFERROR(R79/R$17,"") -> 0 | V79: =IFERROR(S79/S$17,"") | W79: =IFERROR(T79/T$17,"") -> 0
E80: X-Quang | R80: =SUMIFS($F80:$Q80,$F$7:$Q$7,"A") -> 0 | S80: =SUMIFS($F80:$Q80,$F$7:$Q$7,"B") -> 0 | T80: =SUM(R80:S80) -> 0 | U80: =IFERROR(R80/R$17,"") -> 0 | V80: =IFERROR(S80/S$17,"") | W80: =IFERROR(T80/T$17,"") -> 0
E81: Siêu âm | R81: =SUMIFS($F81:$Q81,$F$7:$Q$7,"A") -> 0 | S81: =SUMIFS($F81:$Q81,$F$7:$Q$7,"B") -> 0 | T81: =SUM(R81:S81) -> 0 | U81: =IFERROR(R81/R$17,"") -> 0 | V81: =IFERROR(S81/S$17,"") | W81: =IFERROR(T81/T$17,"") -> 0
C82: Utilization rate (Công suất sử dụng) | R82: =SUMIFS($F82:$Q82,$F$7:$Q$7,"A") -> 0 | S82: =SUMIFS($F82:$Q82,$F$7:$Q$7,"B") -> 0 | T82: =SUM(R82:S82) -> 0 | U82: =IFERROR(R82/R$17,"") -> 0 | V82: =IFERROR(S82/S$17,"") | W82: =IFERROR(T82/T$17,"") -> 0
E83: MRI | R83: =SUMIFS($F83:$Q83,$F$7:$Q$7,"A") -> 0 | S83: =SUMIFS($F83:$Q83,$F$7:$Q$7,"B") -> 0 | T83: =SUM(R83:S83) -> 0 | U83: =IFERROR(R83/R$17,"") -> 0 | V83: =IFERROR(S83/S$17,"") | W83: =IFERROR(T83/T$17,"") -> 0
E84: Mammo X-Quang | R84: =SUMIFS($F84:$Q84,$F$7:$Q$7,"A") -> 0 | S84: =SUMIFS($F84:$Q84,$F$7:$Q$7,"B") -> 0 | T84: =SUM(R84:S84) -> 0 | U84: =IFERROR(R84/R$17,"") -> 0 | V84: =IFERROR(S84/S$17,"") | W84: =IFERROR(T84/T$17,"") -> 0
E85: CT | R85: =SUMIFS($F85:$Q85,$F$7:$Q$7,"A") -> 0 | S85: =SUMIFS($F85:$Q85,$F$7:$Q$7,"B") -> 0 | T85: =SUM(R85:S85) -> 0 | U85: =IFERROR(R85/R$17,"") -> 0 | V85: =IFERROR(S85/S$17,"") | W85: =IFERROR(T85/T$17,"") -> 0
E86: X-Quang | R86: =SUMIFS($F86:$Q86,$F$7:$Q$7,"A") -> 0 | S86: =SUMIFS($F86:$Q86,$F$7:$Q$7,"B") -> 0 | T86: =SUM(R86:S86) -> 0 | U86: =IFERROR(R86/R$17,"") -> 0 | V86: =IFERROR(S86/S$17,"") | W86: =IFERROR(T86/T$17,"") -> 0
E87: Siêu âm | R87: =SUMIFS($F87:$Q87,$F$7:$Q$7,"A") -> 0 | S87: =SUMIFS($F87:$Q87,$F$7:$Q$7,"B") -> 0 | T87: =SUM(R87:S87) -> 0 | U87: =IFERROR(R87/R$17,"") -> 0 | V87: =IFERROR(S87/S$17,"") | W87: =IFERROR(T87/T$17,"") -> 0
B88: Lợi nhuận về công ty mẹ | R88: =SUMIFS($F88:$Q88,$F$7:$Q$7,"A") -> 0 | S88: =SUMIFS($F88:$Q88,$F$7:$Q$7,"B") -> 0 | T88: =SUM(R88:S88) -> 0 | U88: =IFERROR(R88/R$17,"") -> 0 | V88: =IFERROR(S88/S$17,"") | W88: =IFERROR(T88/T$17,"") -> 0 | AB88: =AB56-AB57 -> 761.69319
F89: =-288137174.579563/(10^6) -> -288.13717 | G89: =-142597609.351801/(10^6) -> -142.59761 | H89: =-47522676.2203755/(10^6) -> -47.522676 | I89: =-19662977.0277008/(10^6) -> -19.662977 | J89: =6216025.4241305/(10^6) -> 6.2160254 | K89: =134034367.392736/(10^6) -> 134.03437 | L89: =11106305.1246537/(10^6) -> 11.106305 | M89: =-17603126.728224/(10^6) -> -17.603127 | N89: =-25142589.0680209/(10^6) -> -25.142589 | O89: =38447649.3225608/(10^6) -> 38.447649 | P89: =24664233.3681133/(10^6) -> 24.664233 | Q89: =-93772389.6565097/(10^6) -> -93.77239
B90: Gốc vay ngân hàng | F90: =VTB_CaMau!L7 -> 660 | I90: =F90 -> 660 | L90: =F90 -> 660 | O90: =F90 -> 660 | Z90: ='Site list'!G5 -> 10000
B91: Thừa/(Thiếu) tiền | F91: =F42+F53-F90 -> -762.54424 | G91: =G42+G53-G90 -> 43.670086 | H91: =H42+H53-H90 -> 139.30864 | I91: =I42+I53-I90 -> -492.60938 | J91: =J42+J53-J90 -> 193.21405 | K91: =K42+K53-K90 -> 321.98499 | L91: =L42+L53-L90 -> -461.91155 | M91: =M42+M53-M90 -> 169.46634 | ... Q91: =Q42+Q53-Q90 -> 92.590385 | R91: =SUMIFS($F91:$Q91,$F$7:$Q$7,"A") -> -817.87525 | S91: =SUMIFS($F91:$Q91,$F$7:$Q$7,"B") -> 0 | T91: =SUM(R91:S91) -> -817.87525 | Z91: =1-'Site list'!H5 -> 0.45 | AB91: =Z90*Z91 -> 4500
B93: Số ca
E94: MRI | F94: 97 | G94: 182 | H94: 218 | I94: 266 | J94: 255 | K94: 321 | L94: 248 | M94: 250 | N94: 232 | O94: 273 | P94: 255 | Q94: 189 | R94: =SUMIFS($F94:$Q94,$F$7:$Q$7,"A") -> 2786 | S94: =SUMIFS($F94:$Q94,$F$7:$Q$7,"B") -> 0 | T94: =SUM(R94:S94) -> 2786 | AB94: =AB102*T98 -> 3440
E95: Mammo X-Quang | F95: 16 | G95: 16 | H95: 51 | I95: 31 | J95: 35 | K95: 89 | L95: 40 | M95: 49 | N95: 28 | O95: 23 | P95: 58 | Q95: 27 | R95: =SUMIFS($F95:$Q95,$F$7:$Q$7,"A") -> 463 | S95: =SUMIFS($F95:$Q95,$F$7:$Q$7,"B") -> 0 | T95: =SUM(R95:S95) -> 463 | AB95: =AB103*T99 -> 784
F96: =SUM(F94:F95) -> 113 | G96: =SUM(G94:G95) -> 198 | H96: =SUM(H94:H95) -> 269 | I96: =SUM(I94:I95) -> 297 | J96: =SUM(J94:J95) -> 290 | K96: =SUM(K94:K95) -> 410 | L96: =SUM(L94:L95) -> 288 | M96: =SUM(M94:M95) -> 299 | ... Q96: =SUM(Q94:Q95) -> 216
B97: Capacity
E98: MRI | F98: =30*9*60/20 -> 810 | G98: =30*9*60/20 -> 810 | H98: =30*9*60/20 -> 810 | I98: =30*9*60/20 -> 810 | J98: =30*9*60/20 -> 810 | K98: =30*9*60/20 -> 810 | L98: =30*9*60/20 -> 810 | M98: =30*9*60/20 -> 810 | ... Q98: =30*9*60/20 -> 810 | R98: =SUMIFS($F98:$Q98,$F$7:$Q$7,"A") -> 9720 | S98: =SUMIFS($F98:$Q98,$F$7:$Q$7,"B") -> 0 | T98: =SUM(R98:S98) -> 9720
E99: Mammo X-Quang | F99: =30*9*60/15 -> 1080 | G99: =30*9*60/15 -> 1080 | H99: =30*9*60/15 -> 1080 | I99: =30*9*60/15 -> 1080 | J99: =30*9*60/15 -> 1080 | K99: =30*9*60/15 -> 1080 | L99: =30*9*60/15 -> 1080 | M99: =30*9*60/15 -> 1080 | ... Q99: =30*9*60/15 -> 1080 | R99: =SUMIFS($F99:$Q99,$F$7:$Q$7,"A") -> 12960 | S99: =SUMIFS($F99:$Q99,$F$7:$Q$7,"B") -> 0 | T99: =SUM(R99:S99) -> 12960
B101: Utilization
E102: MRI | F102: =F94/F98 -> 0.11975309 | G102: =G94/G98 -> 0.22469136 | H102: =H94/H98 -> 0.2691358 | I102: =I94/I98 -> 0.32839506 | J102: =J94/J98 -> 0.31481481 | K102: =K94/K98 -> 0.3962963 | L102: =L94/L98 -> 0.30617284 | M102: =M94/M98 -> 0.30864198 | ... R102: =R94/R98 -> 0.28662551 | T102: =T94/T98 -> 0.28662551 | AB102: =AVERAGE(I102,K102,O102) -> 0.35390947
E103: Mammo X-Quang | F103: =F95/F99 -> 0.014814815 | G103: =G95/G99 -> 0.014814815 | H103: =H95/H99 -> 0.047222222 | I103: =I95/I99 -> 0.028703704 | J103: =J95/J99 -> 0.032407407 | K103: =K95/K99 -> 0.082407407 | L103: =L95/L99 -> 0.037037037 | M103: =M95/M99 -> 0.04537037 | ... R103: =R95/R99 -> 0.035725309 | T103: =T95/T99 -> 0.035725309 | AB103: =AVERAGE(K103,M103,P103) -> 0.060493827
B104: Giá trung bình
E105: MRI | F105: =F12*10^6/F94 -> 1913195.9 | G105: =G12*10^6/G94 -> 1864285.7 | H105: =H12*10^6/H94 -> 1870183.5 | I105: =I12*10^6/I94 -> 1881203 | J105: =J12*10^6/J94 -> 1870588.2 | K105: =K12*10^6/K94 -> 1846822.4 | L105: =L12*10^6/L94 -> 1845362.9 | M105: =M12*10^6/M94 -> 1854000 | ... Q105: =Q12*10^6/Q94 -> 1871164 | T105: =T12*10^6/T94 -> 1864472.4
E106: Mammo X-Quang | F106: =F13*10^6/F95 -> 500000 | G106: =G13*10^6/G95 -> 500000 | H106: =H13*10^6/H95 -> 500000 | I106: =I13*10^6/I95 -> 500000 | J106: =J13*10^6/J95 -> 480000 | K106: =K13*10^6/K95 -> 441573.03 | L106: =L13*10^6/L95 -> 485000 | M106: =M13*10^6/M95 -> 500000 | ... Q106: =Q13*10^6/Q95 -> 496296.3 | T106: =T13*10^6/T95 -> 479697.62

Sheet ThanhHoa
G2: =10^6 -> 1000000
B6: BÁO CÁO KẾT QUẢ HOẠT ĐỘNG KINH DOANH CHI NHÁNH VÀ DỰ BÁO 2026
B7: THANH HÓA | F7: A | G7: A | H7: A | I7: A | J7: A | K7: A | L7: A | M7: A | N7: A | O7: A | P7: A | Q7: A
B8: Năm tài chính 2025 | F8: Tháng | R8: ------------------Tổng-------------------- | U8: ------%Doanh thu------- | X8: ------------vs--------------
B9: VND triệu | F9: 1 | G9: 2 | H9: 3 | I9: 4 | J9: 5 | K9: 6 | L9: 7 | M9: 8 | N9: 9 | O9: 10 | P9: 11 | Q9: 12 | R9: Year to date | S9: Year to go | T9: LATEST ESTIMATE | U9: YTD | V9: YTG | W9: LE | X9: Last month | Y9: Last year | AA9: Assumption | AB9: Note | AC9: 2026F
B10: Doanh thu
D11: Chẩn đoán hình ảnh
E12: MRI | F12: =177800000/(-10^6) -> 177.8 | G12: =333200000/(-10^6) -> 333.2 | H12: =304672000/(-10^6) -> 304.672 | I12: =403271600/(-10^6) -> 403.2716 | J12: =537330100/(-10^6) -> 537.3301 | K12: =256166800/(-10^6) -> 256.1668 | L12: =296200000/(-10^6) -> 296.2 | M12: =376500000/(-10^6) -> 376.5 | N12: =304624300/(-10^6) -> 304.6243 | O12: =185900000/(-10^6) -> 185.9 | P12: =174200000/(-10^6) -> 174.2 | Q12: 155.5 | R12: =SUMIFS($F12:$Q12,$F$7:$Q$7,"A") -> 3505.3648 | S12: =SUMIFS($F12:$Q12,$F$7:$Q$7,"B") -> 0 | T12: =SUM(R12:S12) -> 3505.3648 | U12: =IFERROR(R12/R$17,"") -> 0.32123678 | V12: =IFERROR(S12/S$17,"") | W12: =T12/$T$17 -> 0.32123678 | AA12: 0.1 | AB12: vs 2025 | AC12: =AC94*AC102/10^6 -> 9360
E13: Mammo X-Quang | Q13: =P13 -> 0 | R13: =SUMIFS($F13:$Q13,$F$7:$Q$7,"A") -> 0 | S13: =SUMIFS($F13:$Q13,$F$7:$Q$7,"B") -> 0 | T13: =SUM(R13:S13) -> 0 | U13: =IFERROR(R13/R$17,"") -> 0 | V13: =IFERROR(S13/S$17,"") | W13: =T13/$T$17 -> 0 | AA13: 0.1 | AB13: vs 2025 | AC13: =T13*(1+AA13) -> 0
E14: CT | F14: =54600000/(-10^6) -> 54.6 | G14: =690000000/(-10^6) -> 690 | H14: =1059200000/(-10^6) -> 1059.2 | I14: =810238800/(-10^6) -> 810.2388 | J14: =1010743600/(-10^6) -> 1010.7436 | K14: =1263131000/(-10^6) -> 1263.131 | L14: =862961000/(-10^6) -> 862.961 | M14: =342006000/(-10^6) -> 342.006 | N14: =1206845300/(-10^6) -> 1206.8453 | O14: =33600000/(-10^6) -> 33.6 | P14: =35000000/(-10^6) -> 35 | Q14: 38.4 | R14: =SUMIFS($F14:$Q14,$F$7:$Q$7,"A") -> 7406.7257 | S14: =SUMIFS($F14:$Q14,$F$7:$Q$7,"B") -> 0 | T14: =SUM(R14:S14) -> 7406.7257 | U14: =IFERROR(R14/R$17,"") -> 0.67876322 | V14: =IFERROR(S14/S$17,"") | W14: =T14/$T$17 -> 0.67876322 | AA14: 0.1 | AB14: vs 2025 | AC14: =AC96*AC104/10^6 -> 2005.7143
E15: X-Quang | Q15: =P15 -> 0 | R15: =SUMIFS($F15:$Q15,$F$7:$Q$7,"A") -> 0 | S15: =SUMIFS($F15:$Q15,$F$7:$Q$7,"B") -> 0 | T15: =SUM(R15:S15) -> 0 | U15: =IFERROR(R15/R$17,"") -> 0 | V15: =IFERROR(S15/S$17,"") | W15: =T15/$T$17 -> 0 | AA15: 0.1 | AB15: vs 2025 | AC15: =T15*(1+AA15) -> 0
E16: Siêu âm | Q16: =P16 -> 0 | R16: =SUMIFS($F16:$Q16,$F$7:$Q$7,"A") -> 0 | S16: =SUMIFS($F16:$Q16,$F$7:$Q$7,"B") -> 0 | T16: =SUM(R16:S16) -> 0 | U16: =IFERROR(R16/R$17,"") -> 0 | V16: =IFERROR(S16/S$17,"") | W16: =T16/$T$17 -> 0 | AA16: 0.1 | AB16: vs 2025 | AC16: =T16*(1+AA16) -> 0
D17: Tổng- Chẩn đoán hình ảnh | F17: =SUM(F12:F16) -> 232.4 | G17: =SUM(G12:G16) -> 1023.2 | H17: =SUM(H12:H16) -> 1363.872 | I17: =SUM(I12:I16) -> 1213.5104 | J17: =SUM(J12:J16) -> 1548.0737 | K17: =SUM(K12:K16) -> 1519.2978 | L17: =SUM(L12:L16) -> 1159.161 | M17: =SUM(M12:M16) -> 718.506 | ... Q17: =SUM(Q12:Q16) -> 193.9 | R17: =SUMIFS($F17:$Q17,$F$7:$Q$7,"A") -> 10912.091 | S17: =SUMIFS($F17:$Q17,$F$7:$Q$7,"B") -> 0 | T17: =SUM(R17:S17) -> 10912.091 | U17: =IFERROR(R17/R$17,"") -> 1 | V17: =IFERROR(S17/S$17,"") | W17: =T17/$T$17 -> 1 | AC17: =SUM(AC12:AC16) -> 11365.714
D18: Tổng- Khác | F18: 0 | G18: 0 | H18: 0 | I18: 0 | J18: 0 | K18: 0 | L18: 0 | M18: 0 | N18: 0 | O18: 0 | P18: 0 | Q18: 0 | R18: =SUMIFS($F18:$Q18,$F$7:$Q$7,"A") -> 0 | S18: =SUMIFS($F18:$Q18,$F$7:$Q$7,"B") -> 0 | T18: =SUM(R18:S18) -> 0 | U18: =IFERROR(R18/R$17,"") -> 0 | V18: =IFERROR(S18/S$17,"") | AC18: 0
B19: Tổng- Doanh thu | F19: =SUM(F17,F18) -> 232.4 | G19: =SUM(G17,G18) -> 1023.2 | H19: =SUM(H17,H18) -> 1363.872 | I19: =SUM(I17,I18) -> 1213.5104 | J19: =SUM(J17,J18) -> 1548.0737 | K19: =SUM(K17,K18) -> 1519.2978 | L19: =SUM(L17,L18) -> 1159.161 | M19: =SUM(M17,M18) -> 718.506 | ... Q19: =SUM(Q17,Q18) -> 193.9 | R19: =SUMIFS($F19:$Q19,$F$7:$Q$7,"A") -> 10912.091 | S19: =SUMIFS($F19:$Q19,$F$7:$Q$7,"B") -> 0 | T19: =SUM(R19:S19) -> 10912.091 | U19: =IFERROR(R19/R$17,"") -> 1 | V19: =IFERROR(S19/S$17,"") | W19: =T19/$T$17 -> 1 | AC19: =SUM(AC17,AC18) -> 11365.714
B20: Giảm trừ doanh thu | F20: =SUBTOTAL(9,F21:F24) -> 0.1 | G20: =SUBTOTAL(9,G21:G24) -> 0.78 | H20: =SUBTOTAL(9,H21:H24) -> 2.46 | I20: =SUBTOTAL(9,I21:I24) -> 0.78 | J20: =SUBTOTAL(9,J21:J24) -> 0 | K20: =SUBTOTAL(9,K21:K24) -> 0.57 | L20: =SUBTOTAL(9,L21:L24) -> 0 | M20: =SUBTOTAL(9,M21:M24) -> 0 | ... Q20: =SUBTOTAL(9,Q21:Q24) -> 0 | R20: =SUMIFS($F20:$Q20,$F$7:$Q$7,"A") -> 8.32 | S20: =SUMIFS($F20:$Q20,$F$7:$Q$7,"B") -> 0 | T20: =SUM(R20:S20) -> 8.32 | U20: =IFERROR(R20/R$17,"") -> 0.00076245702 | V20: =IFERROR(S20/S$17,"") | AC20: 0
E21: MRI | F21: 0.1 | G21: 0.78 | H21: 2.46 | I21: 0.78 | J21: 0 | K21: 0.57 | L21: 0 | M21: 0 | N21: 0 | O21: 0 | P21: 3.63 | Q21: 0 | T21: =SUM(R21:S21) -> 0 | U21: =IFERROR(R21/R12,"") -> 0 | V21: =IFERROR(S21/S12,"") | W21: =IFERROR(T21/T12,"") -> 0
E22: Mammo X-Quang | T22: =SUM(R22:S22) -> 0 | U22: =IFERROR(R22/R13,"") | V22: =IFERROR(S22/S13,"") | W22: =IFERROR(T22/T13,"")
E23: CT | T23: =SUM(R23:S23) -> 0 | U23: =IFERROR(R23/R14,"") -> 0 | V23: =IFERROR(S23/S14,"") | W23: =IFERROR(T23/T14,"") -> 0
E24: X-Quang | T24: =SUM(R24:S24) -> 0 | U24: =IFERROR(R24/R15,"") | V24: =IFERROR(S24/S15,"") | W24: =IFERROR(T24/T15,"")
B25: Biến phí | T25: =SUM(R25:S25) -> 0
C26: Vật tư tiêu hao | F26: =3982581/(10^6) -> 3.982581 | G26: =34967991/(10^6) -> 34.967991 | H26: =43656483/(10^6) -> 43.656483 | I26: =38436353/(10^6) -> 38.436353 | J26: =55687973/(10^6) -> 55.687973 | K26: =38616177/(10^6) -> 38.616177 | L26: =31979000/(10^6) -> 31.979 | M26: =19227959/(10^6) -> 19.227959 | N26: =43976479/(10^6) -> 43.976479 | O26: =1966107/(10^6) -> 1.966107 | P26: =2486989/(10^6) -> 2.486989 | Q26: 1.350152 | R26: =SUMIFS($F26:$Q26,$F$7:$Q$7,"A") -> 316.33424 | S26: =SUMIFS($F26:$Q26,$F$7:$Q$7,"B") -> 0 | T26: =SUM(R26:S26) -> 316.33424 | U26: =IFERROR(R26/R$17,"") -> 0.028989335 | V26: =IFERROR(S26/S$17,"") | W26: =T26/$T$17 -> 0.028989335 | AA26: =W26 -> 0.028989335 | AB26: % doanh thu | AC26: =AA26*$AC$17 -> 329.4845
C27: Chi phí đọc kết quả online | F27: =15410000/(10^6) -> 15.41 | G27: =75555000/(10^6) -> 75.555 | H27: =108790000/(10^6) -> 108.79 | I27: =88535000/(10^6) -> 88.535 | J27: =176320000/(10^6) -> 176.32 | K27: =136370000/(10^6) -> 136.37 | L27: =100830000/(10^6) -> 100.83 | M27: =50930000/(10^6) -> 50.93 | N27: =133300000/(10^6) -> 133.3 | O27: =15065000/(10^6) -> 15.065 | P27: =14330000/(10^6) -> 14.33 | Q27: 13.685 | R27: =SUMIFS($F27:$Q27,$F$7:$Q$7,"A") -> 929.12 | S27: =SUMIFS($F27:$Q27,$F$7:$Q$7,"B") -> 0 | T27: =SUM(R27:S27) -> 929.12 | U27: =IFERROR(R27/R$17,"") -> 0.085145921 | V27: =IFERROR(S27/S$17,"") | W27: =T27/$T$17 -> 0.085145921 | AA27: =W27 -> 0.085145921 | AB27: % doanh thu | AC27: =AA27*$AC$17 -> 967.74422
C28: Tiền thuốc | F28: =15364000/(10^6) -> 15.364 | G28: =141608000/(10^6) -> 141.608 | H28: =196816000/(10^6) -> 196.816 | I28: =116270000/(10^6) -> 116.27 | J28: =16290000/(10^6) -> 16.29 | K28: =20020000/(10^6) -> 20.02 | L28: =21704000/(10^6) -> 21.704 | M28: =75218000/(10^6) -> 75.218 | N28: =4420000/(10^6) -> 4.42 | O28: =8190000/(10^6) -> 8.19 | P28: =3042000/(10^6) -> 3.042 | Q28: 4.108 | R28: =SUMIFS($F28:$Q28,$F$7:$Q$7,"A") -> 623.05 | S28: =SUMIFS($F28:$Q28,$F$7:$Q$7,"B") -> 0 | T28: =SUM(R28:S28) -> 623.05 | U28: =IFERROR(R28/R$17,"") -> 0.057097217 | V28: =IFERROR(S28/S$17,"") | W28: =T28/$T$17 -> 0.057097217 | AA28: =W28 -> 0.057097217 | AB28: % doanh thu | AC28: =AA28*$AC$17 -> 648.95066
C29: Tư vấn chuyên môn | F29: =34800000/(10^6) -> 34.8 | G29: =142300000/(10^6) -> 142.3 | H29: =193400000/(10^6) -> 193.4 | I29: =165010000/(10^6) -> 165.01 | J29: =123725000/(10^6) -> 123.725 | K29: =71170000/(10^6) -> 71.17 | L29: =112580000/(10^6) -> 112.58 | M29: =90600000/(10^6) -> 90.6 | N29: =98210000/(10^6) -> 98.21 | O29: =28800000/(10^6) -> 28.8 | P29: =24600000/(10^6) -> 24.6 | Q29: 27.5 | R29: =SUMIFS($F29:$Q29,$F$7:$Q$7,"A") -> 1112.695 | S29: =SUMIFS($F29:$Q29,$F$7:$Q$7,"B") -> 0 | T29: =SUM(R29:S29) -> 1112.695 | U29: =IFERROR(R29/R$17,"") -> 0.101969 | V29: =IFERROR(S29/S$17,"") | W29: =T29/$T$17 -> 0.101969 | AA29: =W29 -> 0.101969 | AB29: % doanh thu | AC29: =AA29*$AC$17 -> 1158.9506
C30: Hoa hồng + thưởng nhân viên | F30: =4340000/(10^6) -> 4.34 | G30: =8160000/(10^6) -> 8.16 | H30: =20480000/(10^6) -> 20.48 | I30: =39964400/(10^6) -> 39.9644 | J30: =16490000/(10^6) -> 16.49 | K30: =113316000/(10^6) -> 113.316 | L30: =53000000/(10^6) -> 53 | M30: =17660000/(10^6) -> 17.66 | N30: =45196000/(10^6) -> 45.196 | O30: =4440000/(10^6) -> 4.44 | P30: =4300000/(10^6) -> 4.3 | Q30: 4.08 | R30: =SUMIFS($F30:$Q30,$F$7:$Q$7,"A") -> 331.4264 | S30: =SUMIFS($F30:$Q30,$F$7:$Q$7,"B") -> 0 | T30: =SUM(R30:S30) -> 331.4264 | U30: =IFERROR(R30/R$17,"") -> 0.030372402 | V30: =IFERROR(S30/S$17,"") | W30: =T30/$T$17 -> 0.030372402 | AA30: =W30 -> 0.030372402 | AB30: % doanh thu | AC30: =AA30*$AC$17 -> 345.20404
C31: Truyền thông marketing | F31: =17886282/(10^6) -> 17.886282 | G31: =14938282/(10^6) -> 14.938282 | H31: =13227556/(10^6) -> 13.227556 | I31: =12788278/(10^6) -> 12.788278 | J31: =0/(10^6) -> 0 | K31: =0/(10^6) -> 0 | L31: =2900000/(10^6) -> 2.9 | M31: =2100000/(10^6) -> 2.1 | N31: =7682219/(10^6) -> 7.682219 | O31: =8739103/(10^6) -> 8.739103 | P31: =4573495/(10^6) -> 4.573495 | Q31: 7.836 | R31: =SUMIFS($F31:$Q31,$F$7:$Q$7,"A") -> 92.671215 | S31: =SUMIFS($F31:$Q31,$F$7:$Q$7,"B") -> 0 | T31: =SUM(R31:S31) -> 92.671215 | U31: =IFERROR(R31/R$17,"") -> 0.0084925262 | V31: =IFERROR(S31/S$17,"") | W31: =T31/$T$17 -> 0.0084925262 | AA31: 0.01 | AB31: % doanh thu | AC31: =AA31*$AC$17 -> 113.65714
B32: Tổng- Biến phí | F32: =SUM(F26:F31) -> 91.782863 | G32: =SUM(G26:G31) -> 417.52927 | H32: =SUM(H26:H31) -> 576.37004 | I32: =SUM(I26:I31) -> 461.00403 | J32: =SUM(J26:J31) -> 388.51297 | K32: =SUM(K26:K31) -> 379.49218 | L32: =SUM(L26:L31) -> 322.993 | M32: =SUM(M26:M31) -> 255.73596 | ... S32: =SUM(S26:S31) -> 0 | T32: =SUM(R32:S32) -> 3405.2969 | U32: =IFERROR(R32/R$17,"") -> 0.31206641 | V32: =IFERROR(S32/S$17,"") | W32: =T32/$T$17 -> 0.31206641 | AC32: =SUM(AC26:AC31) -> 3563.9911
B33: Lãi trên biến phí | F33: =F19-F32-F20 -> 140.51714 | G33: =G19-G32-G20 -> 604.89073 | H33: =H19-H32-H20 -> 785.04196 | I33: =I19-I32-I20 -> 751.72637 | J33: =J19-J32-J20 -> 1159.5607 | K33: =K19-K32-K20 -> 1139.2356 | L33: =L19-L32-L20 -> 836.168 | M33: =M19-M32-M20 -> 462.77004 | ... S33: =S19-S32-S20 -> 0 | T33: =SUM(R33:S33) -> 7498.4736 | U33: =IFERROR(R33/R$17,"") -> 0.68717114 | V33: =IFERROR(S33/S$17,"") | W33: =T33/$T$17 -> 0.68717114 | AC33: =AC19-AC32-AC20 -> 7801.7232
B34: Định phí | T34: =SUM(R34:S34) -> 0 | U34: =IFERROR(R34/R$17,"") -> 0 | V34: =IFERROR(S34/S$17,"")
C35: Chi phí nhân viên | F35: 125.66381 | G35: 183.02883 | H35: 221.00857 | I35: 178.6885 | J35: 125.03369 | K35: 160.04484 | L35: 132.81675 | M35: 111.34462 | N35: 223.1117 | O35: 84.022 | P35: 95.735 | Q35: 111.85 | R35: =SUMIFS($F35:$Q35,$F$7:$Q$7,"A") -> 1752.3483 | S35: =SUMIFS($F35:$Q35,$F$7:$Q$7,"B") -> 0 | T35: =SUM(R35:S35) -> 1752.3483 | U35: =IFERROR(R35/R$17,"") -> 0.16058777 | V35: =IFERROR(S35/S$17,"") | W35: =T35/$T$17 -> 0.16058777 | AA35: 0.02 | AB35: vs 2025 | AC35: =T35*(1+AA35) -> 1787.3953
C36: Chi phí thuê địa điểm | F36: =95083333/(10^6) -> 95.083333 | G36: =58333333/(10^6) -> 58.333333 | H36: =58333333/(10^6) -> 58.333333 | I36: =58333333/(10^6) -> 58.333333 | J36: =58333333/(10^6) -> 58.333333 | K36: =58333333/(10^6) -> 58.333333 | L36: =58333333/(10^6) -> 58.333333 | M36: =58333333/(10^6) -> 58.333333 | N36: =58333333/(10^6) -> 58.333333 | ... P36: =58333333/(10^6) -> 58.333333 | Q36: =60000000/(10^6) -> 60 | R36: =SUMIFS($F36:$Q36,$F$7:$Q$7,"A") -> 738.41666 | S36: =SUMIFS($F36:$Q36,$F$7:$Q$7,"B") -> 0 | T36: =SUM(R36:S36) -> 738.41666 | U36: =IFERROR(R36/R$17,"") -> 0.067669588 | V36: =IFERROR(S36/S$17,"") | W36: =T36/$T$17 -> 0.067669588 | AA36: 0.02 | AB36: vs 2025 | AC36: =T36*(1+AA36) -> 753.185
C37: Chi phí bảo dưỡng bảo trì máy | R37: =SUMIFS($F37:$Q37,$F$7:$Q$7,"A") -> 0 | S37: =SUMIFS($F37:$Q37,$F$7:$Q$7,"B") -> 0 | T37: =SUM(R37:S37) -> 0 | U37: =IFERROR(R37/R$17,"") -> 0 | V37: =IFERROR(S37/S$17,"") | W37: =T37/$T$17 -> 0 | AB37: Đề xuất PKT | AC37: ='Site list'!Q6 -> 320.30125
C38: Chi phí vận hành thường xuyên | F38: 44.706397 | G38: 47.038602 | H38: 52.666004 | I38: 59.304651 | J38: 68.375147 | K38: 64.192198 | L38: 67.200168 | M38: 54.267249 | N38: 69.980061 | O38: 58.741334 | P38: 48.469529 | Q38: 49.922794 | R38: =SUMIFS($F38:$Q38,$F$7:$Q$7,"A") -> 684.86413 | S38: =SUMIFS($F38:$Q38,$F$7:$Q$7,"B") -> 0 | T38: =SUM(R38:S38) -> 684.86413 | U38: =IFERROR(R38/R$17,"") -> 0.062761955 | V38: =IFERROR(S38/S$17,"") | W38: =T38/$T$17 -> 0.062761955 | AB38: không đổi | AC38: =T38 -> 684.86413
C39: Chi phí khác | F39: 3.111169 | G39: 0 | H39: 8.0352 | I39: 6.29 | J39: 2.742 | K39: 87.044007 | L39: 66.225624 | M39: 10.788 | N39: 125.42306 | O39: 5.359 | P39: 3.6327 | Q39: 0 | R39: =SUMIFS($F39:$Q39,$F$7:$Q$7,"A") -> 318.65076 | S39: =SUMIFS($F39:$Q39,$F$7:$Q$7,"B") -> 0 | T39: =SUM(R39:S39) -> 318.65076 | U39: =IFERROR(R39/R$17,"") -> 0.029201624 | V39: =IFERROR(S39/S$17,"") | W39: =T39/$T$17 -> 0.029201624 | AB39: không đổi | AC39: =T39 -> 318.65076
B40: Tổng- Định phí | F40: =SUM(F35:F39) -> 268.56471 | G40: =SUM(G35:G39) -> 288.40077 | H40: =SUM(H35:H39) -> 340.04311 | I40: =SUM(I35:I39) -> 302.61648 | J40: =SUM(J35:J39) -> 254.48417 | K40: =SUM(K35:K39) -> 369.61438 | L40: =SUM(L35:L39) -> 324.57588 | M40: =SUM(M35:M39) -> 234.7332 | ... S40: =SUM(S35:S39) -> 0 | T40: =SUM(R40:S40) -> 3494.2799 | U40: =IFERROR(R40/R$17,"") -> 0.32022094 | V40: =IFERROR(S40/S$17,"") | W40: =T40/$T$17 -> 0.32022094 | AC40: =SUM(AC35:AC39) -> 3864.3964 | AE40: =T40/12 -> 291.18999
B41: EBITDA | F41: =F33-F40 -> -128.04757 | G41: =G33-G40 -> 316.48996 | H41: =H33-H40 -> 444.99886 | I41: =I33-I40 -> 449.10989 | J41: =J33-J40 -> 905.07656 | K41: =K33-K40 -> 769.62125 | L41: =L33-L40 -> 511.59212 | M41: =M33-M40 -> 228.03684 | ... S41: =S33-S40 -> 0 | T41: =SUM(R41:S41) -> 4004.1938 | U41: =IFERROR(R41/R$17,"") -> 0.3669502 | V41: =IFERROR(S41/S$17,"") | W41: =T41/$T$17 -> 0.3669502 | AC41: =AC33-AC40 -> 3937.3268
B42: EBITDA chuyền về công ty | T42: =SUM(R42:S42) -> 0 | U42: =IFERROR(R42/R$17,"") -> 0 | V42: =IFERROR(S42/S$17,"") | AA42: ='Site list'!H6 -> 0.6 | AC42: =AC41*AA42 -> 2362.3961
T43: =SUM(R43:S43) -> 0 | U43: =IFERROR(R43/R$17,"") -> 0 | V43: =IFERROR(S43/S$17,"")
C44: Chi phí khấu hao máy | F44: =SUM(F45:F49) -> 177.76986 | G44: =SUM(G45:G49) -> 177.76986 | H44: =SUM(H45:H49) -> 177.76986 | I44: =SUM(I45:I49) -> 177.76986 | J44: =SUM(J45:J49) -> 177.76986 | K44: =SUM(K45:K49) -> 177.76986 | L44: =SUM(L45:L49) -> 177.76986 | M44: =SUM(M45:M49) -> 177.76986 | ... P44: =SUM(P45:P49) -> 177.76986 | Q44: =P44 -> 177.76986 | R44: =SUM(R45:R49) -> 2133.2383 | S44: =SUM(S45:S49) -> 0 | T44: =SUM(R44:S44) -> 2133.2383 | U44: =IFERROR(R44/R$17,"") -> 0.19549309 | V44: =IFERROR(S44/S$17,"") | W44: =T44/$T$17 -> 0.19549309 | AB44: không đổi | AC44: =T44 -> 2133.2383 | AE44: =Q44+Q50 -> 207.78478
E45: MRI | F45: =145269855.25/(10^6) -> 145.26986 | G45: =145269855.25/(10^6) -> 145.26986 | H45: =145269855.25/(10^6) -> 145.26986 | I45: =145269855.25/(10^6) -> 145.26986 | J45: =145269855.25/(10^6) -> 145.26986 | K45: =145269855.25/(10^6) -> 145.26986 | L45: =145269855.25/(10^6) -> 145.26986 | M45: =145269855.25/(10^6) -> 145.26986 | ... P45: =145269855.25/(10^6) -> 145.26986 | Q45: =P45 -> 145.26986 | R45: =SUMIFS($F45:$Q45,$F$7:$Q$7,"A") -> 1743.2383 | S45: =SUMIFS($F45:$Q45,$F$7:$Q$7,"B") -> 0 | T45: =SUM(R45:S45) -> 1743.2383 | U45: =IFERROR(R45/R$17,"") -> 0.15975291 | V45: =IFERROR(S45/S$17,"") | W45: =T45/$T$17 -> 0.15975291 | AB45: không đổi | AC45: =T45 -> 1743.2383 | AE45: =T52/12 -> 76.810557
E46: Mammo X-Quang | F46: =0/(10^6) -> 0 | G46: =0/(10^6) -> 0 | H46: =0/(10^6) -> 0 | I46: =0/(10^6) -> 0 | J46: =0/(10^6) -> 0 | K46: =0/(10^6) -> 0 | L46: =0/(10^6) -> 0 | M46: =0/(10^6) -> 0 | ... P46: =0/(10^6) -> 0 | Q46: =P46 -> 0 | R46: =SUMIFS($F46:$Q46,$F$7:$Q$7,"A") -> 0 | S46: =SUMIFS($F46:$Q46,$F$7:$Q$7,"B") -> 0 | T46: =SUM(R46:S46) -> 0 | U46: =IFERROR(R46/R$17,"") -> 0 | V46: =IFERROR(S46/S$17,"") | W46: =T46/$T$17 -> 0 | AB46: không đổi | AC46: =T46 -> 0 | AE46: =AE40+AE44+AE45 -> 575.78532
E47: CT | F47: =32500000/(10^6) -> 32.5 | G47: =32500000/(10^6) -> 32.5 | H47: =32500000/(10^6) -> 32.5 | I47: =32500000/(10^6) -> 32.5 | J47: =32500000/(10^6) -> 32.5 | K47: =32500000/(10^6) -> 32.5 | L47: =32500000/(10^6) -> 32.5 | M47: =32500000/(10^6) -> 32.5 | ... P47: =32500000/(10^6) -> 32.5 | Q47: =P47 -> 32.5 | R47: =SUMIFS($F47:$Q47,$F$7:$Q$7,"A") -> 390 | S47: =SUMIFS($F47:$Q47,$F$7:$Q$7,"B") -> 0 | T47: =SUM(R47:S47) -> 390 | U47: =IFERROR(R47/R$17,"") -> 0.035740173 | V47: =IFERROR(S47/S$17,"") | W47: =T47/$T$17 -> 0.035740173 | AB47: không đổi | AC47: =T47 -> 390
E48: X-Quang | F48: =0/(10^6) -> 0 | G48: =0/(10^6) -> 0 | H48: =0/(10^6) -> 0 | I48: =0/(10^6) -> 0 | J48: =0/(10^6) -> 0 | K48: =0/(10^6) -> 0 | L48: =0/(10^6) -> 0 | M48: =0/(10^6) -> 0 | ... P48: =0/(10^6) -> 0 | Q48: =P48 -> 0 | R48: =SUMIFS($F48:$Q48,$F$7:$Q$7,"A") -> 0 | S48: =SUMIFS($F48:$Q48,$F$7:$Q$7,"B") -> 0 | T48: =SUM(R48:S48) -> 0 | U48: =IFERROR(R48/R$17,"") -> 0 | V48: =IFERROR(S48/S$17,"") | W48: =T48/$T$17 -> 0 | AB48: không đổi | AC48: =T48 -> 0
E49: Siêu âm | F49: =0/(10^6) -> 0 | G49: =0/(10^6) -> 0 | H49: =0/(10^6) -> 0 | I49: =0/(10^6) -> 0 | J49: =0/(10^6) -> 0 | K49: =0/(10^6) -> 0 | L49: =0/(10^6) -> 0 | M49: =0/(10^6) -> 0 | ... P49: =0/(10^6) -> 0 | Q49: =P49 -> 0 | R49: =SUMIFS($F49:$Q49,$F$7:$Q$7,"A") -> 0 | S49: =SUMIFS($F49:$Q49,$F$7:$Q$7,"B") -> 0 | T49: =SUM(R49:S49) -> 0 | U49: =IFERROR(R49/R$17,"") -> 0 | V49: =IFERROR(S49/S$17,"") | W49: =T49/$T$17 -> 0 | AB49: không đổi | AC49: =T49 -> 0
C50: Chi phí khấu hao khác | F50: =30014922/(10^6) -> 30.014922 | G50: =30014922/(10^6) -> 30.014922 | H50: =30014922/(10^6) -> 30.014922 | I50: =30014922/(10^6) -> 30.014922 | J50: =30014922/(10^6) -> 30.014922 | K50: =30014922/(10^6) -> 30.014922 | L50: =30014922/(10^6) -> 30.014922 | M50: =30014922/(10^6) -> 30.014922 | ... P50: =30014922/(10^6) -> 30.014922 | Q50: =P50 -> 30.014922 | R50: =SUMIFS($F50:$Q50,$F$7:$Q$7,"A") -> 360.17906 | S50: =SUMIFS($F50:$Q50,$F$7:$Q$7,"B") -> 0 | T50: =SUM(R50:S50) -> 360.17906 | U50: =IFERROR(R50/R$17,"") -> 0.033007338 | V50: =IFERROR(S50/S$17,"") | W50: =T50/$T$17 -> 0.033007338 | AB50: không đổi | AC50: =T50 -> 360.17906
C51: Lợi nhuận khác | Q51: 0 | R51: =SUMIFS($F51:$Q51,$F$7:$Q$7,"A") -> 0 | S51: =SUMIFS($F51:$Q51,$F$7:$Q$7,"B") -> 0 | T51: =SUM(R51:S51) -> 0 | U51: =IFERROR(R51/R$17,"") -> 0 | V51: =IFERROR(S51/S$17,"") | W51: =T51/$T$17 -> 0 | AC51: 0
C52: Chi phí tài chính | F52: 96.866731 | G52: 76.222118 | H52: 84.382037 | I52: 81.602151 | J52: 80.443157 | K52: 81.4928 | L52: 62.798801 | M52: 72.688446 | N52: 67.49921 | O52: 82.726338 | P52: 67.501842 | Q52: 67.503055 | R52: =SUMIFS($F52:$Q52,$F$7:$Q$7,"A") -> 921.72669 | S52: =SUMIFS($F52:$Q52,$F$7:$Q$7,"B") -> 0 | T52: =SUM(R52:S52) -> 921.72669 | U52: =IFERROR(R52/R$17,"") -> 0.084468387 | V52: =IFERROR(S52/S$17,"") | W52: =T52/$T$17 -> 0.084468387 | AC52: =SUM('BIDV-THH'!I10:I13)/10^6 -> 814.07402
B53: Lợi nhuận/(Lỗ) trước thuế | F53: =F41-F44-F50+F51-F52 -> -432.69908 | G53: =G41-G44-G50+G51-G52 -> 32.483064 | H53: =H41-H44-H50+H51-H52 -> 152.83204 | I53: =I41-I44-I50+I51-I52 -> 159.72296 | J53: =J41-J44-J50+J51-J52 -> 616.84862 | K53: =K41-K44-K50+K51-K52 -> 480.34367 | L53: =L41-L44-L50+L51-L52 -> 241.00854 | M53: =M41-M44-M50+M51-M52 -> -52.436379 | ... Q53: =Q41-Q44-Q50+Q51-Q52 -> -361.71978 | R53: =SUMIFS($F53:$Q53,$F$7:$Q$7,"A") -> 589.04977 | S53: =SUMIFS($F53:$Q53,$F$7:$Q$7,"B") -> 0 | T53: =SUM(R53:S53) -> 589.04977 | U53: =IFERROR(R53/R$17,"") -> 0.053981386 | V53: =IFERROR(S53/S$17,"") | W53: =T53/$T$17 -> 0.053981386 | AC53: =AC41-AC44-AC50+SUM(AC51:AC52) -> 2257.9834
C54: Chi phí thuế TNDN (tạm tính) | F54: =IF(F53<0,0,F53*20%) -> 0 | G54: =IF(G53<0,0,G53*20%) -> 6.4966128 | H54: =IF(H53<0,0,H53*20%) -> 30.566408 | I54: =IF(I53<0,0,I53*20%) -> 31.944592 | J54: =IF(J53<0,0,J53*20%) -> 123.36972 | K54: =IF(K53<0,0,K53*20%) -> 96.068734 | L54: =IF(L53<0,0,L53*20%) -> 48.201709 | M54: =IF(M53<0,0,M53*20%) -> 0 | ... Q54: =IF(Q53<0,0,Q53*20%) -> 0 | R54: =SUMIFS($F54:$Q54,$F$7:$Q$7,"A") -> 421.95833 | S54: =SUMIFS($F54:$Q54,$F$7:$Q$7,"B") -> 0 | T54: =SUM(R54:S54) -> 421.95833 | U54: =IFERROR(R54/R$17,"") -> 0.038668881 | V54: =IFERROR(S54/S$17,"") | W54: =T54/$T$17 -> 0.038668881 | AC54: =AC53*20% -> 451.59669
B55: Lợi nhuận sau thuế | F55: =F53-F54 -> -432.69908 | G55: =G53-G54 -> 25.986451 | H55: =H53-H54 -> 122.26563 | I55: =I53-I54 -> 127.77837 | J55: =J53-J54 -> 493.4789 | K55: =K53-K54 -> 384.27494 | L55: =L53-L54 -> 192.80683 | M55: =M53-M54 -> -52.436379 | ... Q55: =Q53-Q54 -> -361.71978 | R55: =SUMIFS($F55:$Q55,$F$7:$Q$7,"A") -> 167.09143 | S55: =SUMIFS($F55:$Q55,$F$7:$Q$7,"B") -> 0 | T55: =SUM(R55:S55) -> 167.09143 | U55: =IFERROR(R55/R$17,"") -> 0.015312504 | V55: =IFERROR(S55/S$17,"") | W55: =T55/$T$17 -> 0.015312504 | AC55: =AC53-AC54 -> 1806.3868
C56: Cổ đông địa phương | F56: -134.32749 | G56: 33.051721 | H56: 72.121047 | I56: 73.388141 | J56: 211.98924 | K56: 170.80911 | L56: 92.363504 | M56: 4.6197745 | N56: 112.64607 | O56: -78.579685 | P56: -78.513212 | Q56: -88.263246 | R56: =SUMIFS($F56:$Q56,$F$7:$Q$7,"A") -> 391.30498 | S56: =SUMIFS($F56:$Q56,$F$7:$Q$7,"B") -> 0 | T56: =SUM(R56:S56) -> 391.30498 | U56: =IFERROR(R56/R$17,"") -> 0.035859763 | V56: =IFERROR(S56/S$17,"") | W56: =T56/$T$17 -> 0.035859763 | AA56: =1-'Site list'!H6 -> 0.4 | AC56: =AC55*AA56 -> 722.5547
B57: CÁC CHỈ TIÊU HIỆU QUẢ HOẠT ĐỘNG | T57: =SUM(R57:S57) -> 0 | U57: =IFERROR(R57/R$17,"") -> 0 | V57: =IFERROR(S57/S$17,"") | W57: =T57/$T$17 -> 0
C58: Số ca/tháng | T58: =SUM(R58:S58) -> 0 | U58: =IFERROR(R58/R$17,"") -> 0 | V58: =IFERROR(S58/S$17,"") | W58: =T58/$T$17 -> 0
E59: MRI | F59: 257 | G59: 402 | H59: 460 | I59: 538 | J59: 463 | K59: 437 | L59: 449 | M59: 358 | N59: 373 | O59: 353 | P59: 327 | T59: =SUM(R59:S59) -> 0 | U59: =IFERROR(R59/R$17,"") -> 0 | V59: =IFERROR(S59/S$17,"") | W59: =T59/$T$17 -> 0
E60: Mammo X-Quang | F60: 7 | G60: 16 | H60: 17 | I60: 37 | J60: 22 | K60: 18 | L60: 21 | M60: 28 | N60: 20 | O60: 18 | P60: 17 | T60: =SUM(R60:S60) -> 0 | U60: =IFERROR(R60/R$17,"") -> 0 | V60: =IFERROR(S60/S$17,"") | W60: =T60/$T$17 -> 0
E61: CT | F61: 108 | G61: 143 | H61: 166 | I61: 201 | J61: 134 | K61: 106 | L61: 81 | M61: 76 | N61: 82 | O61: 92 | P61: 83 | T61: =SUM(R61:S61) -> 0 | U61: =IFERROR(R61/R$17,"") -> 0 | V61: =IFERROR(S61/S$17,"") | W61: =T61/$T$17 -> 0
E62: X-Quang | F62: 58 | G62: 83 | H62: 147 | I62: 228 | J62: 168 | K62: 188 | L62: 203 | M62: 155 | N62: 167 | O62: 144 | P62: 187 | T62: =SUM(R62:S62) -> 0 | U62: =IFERROR(R62/R$17,"") -> 0 | V62: =IFERROR(S62/S$17,"") | W62: =T62/$T$17 -> 0
E63: Siêu âm | F63: 36 | G63: 72 | H63: 67 | I63: 57 | J63: 42 | K63: 38 | L63: 85 | M63: 46 | N63: 79 | O63: 82 | P63: 44 | T63: =SUM(R63:S63) -> 0 | U63: =IFERROR(R63/R$17,"") -> 0 | V63: =IFERROR(S63/S$17,"") | W63: =T63/$T$17 -> 0
D64: Toàn chi nhánh | F64: =SUM(F59:F63) -> 466 | G64: =SUM(G59:G63) -> 716 | H64: =SUM(H59:H63) -> 857 | I64: =SUM(I59:I63) -> 1061 | J64: =SUM(J59:J63) -> 829 | K64: =SUM(K59:K63) -> 787 | L64: =SUM(L59:L63) -> 839 | M64: =SUM(M59:M63) -> 663 | ... P64: =SUM(P59:P63) -> 658 | T64: =SUM(R64:S64) -> 0 | U64: =IFERROR(R64/R$17,"") -> 0 | V64: =IFERROR(S64/S$17,"") | W64: =T64/$T$17 -> 0
T65: =SUM(R65:S65) -> 0 | U65: =IFERROR(R65/R$17,"") -> 0 | V65: =IFERROR(S65/S$17,"") | W65: =T65/$T$17 -> 0
C66: Số ngày làm việc/tháng | F66: 30 | G66: =28-7 -> 21 | H66: 31 | I66: =30-2 -> 28 | J66: 31 | K66: 30 | L66: 31 | M66: 31 | N66: =30-2 -> 28 | O66: 31 | P66: 30 | T66: =SUM(R66:S66) -> 0 | U66: =IFERROR(R66/R$17,"") -> 0 | V66: =IFERROR(S66/S$17,"") | W66: =T66/$T$17 -> 0
T67: =SUM(R67:S67) -> 0 | U67: =IFERROR(R67/R$17,"") -> 0 | V67: =IFERROR(S67/S$17,"") | W67: =T67/$T$17 -> 0
C68: Doanh thu TB/ngày/máy | T68: =SUM(R68:S68) -> 0 | U68: =IFERROR(R68/R$17,"") -> 0 | V68: =IFERROR(S68/S$17,"") | W68: =T68/$T$17 -> 0
E69: MRI | T69: =SUM(R69:S69) -> 0 | U69: =IFERROR(R69/R$17,"") -> 0 | V69: =IFERROR(S69/S$17,"") | W69: =T69/$T$17 -> 0
E70: Mammo X-Quang | T70: =SUM(R70:S70) -> 0 | U70: =IFERROR(R70/R$17,"") -> 0 | V70: =IFERROR(S70/S$17,"") | W70: =T70/$T$17 -> 0
E71: CT | T71: =SUM(R71:S71) -> 0 | U71: =IFERROR(R71/R$17,"") -> 0 | V71: =IFERROR(S71/S$17,"") | W71: =T71/$T$17 -> 0
E72: X-Quang | T72: =SUM(R72:S72) -> 0 | U72: =IFERROR(R72/R$17,"") -> 0 | V72: =IFERROR(S72/S$17,"") | W72: =T72/$T$17 -> 0
E73: Siêu âm | T73: =SUM(R73:S73) -> 0 | U73: =IFERROR(R73/R$17,"") -> 0 | V73: =IFERROR(S73/S$17,"") | W73: =T73/$T$17 -> 0
D74: Toàn chi nhánh | T74: =SUM(R74:S74) -> 0 | U74: =IFERROR(R74/R$17,"") -> 0 | V74: =IFERROR(S74/S$17,"") | W74: =T74/$T$17 -> 0
C75: Maximum capacity (Công suất tối đa ca/ngày) | T75: =SUM(R75:S75) -> 0 | U75: =IFERROR(R75/R$17,"") -> 0 | V75: =IFERROR(S75/S$17,"") | W75: =T75/$T$17 -> 0
E76: MRI | T76: =SUM(R76:S76) -> 0 | U76: =IFERROR(R76/R$17,"") -> 0 | V76: =IFERROR(S76/S$17,"") | W76: =T76/$T$17 -> 0
E77: Mammo X-Quang | T77: =SUM(R77:S77) -> 0 | U77: =IFERROR(R77/R$17,"") -> 0 | V77: =IFERROR(S77/S$17,"") | W77: =T77/$T$17 -> 0
E78: CT | T78: =SUM(R78:S78) -> 0 | U78: =IFERROR(R78/R$17,"") -> 0 | V78: =IFERROR(S78/S$17,"") | W78: =T78/$T$17 -> 0
E79: X-Quang | T79: =SUM(R79:S79) -> 0 | U79: =IFERROR(R79/R$17,"") -> 0 | V79: =IFERROR(S79/S$17,"") | W79: =T79/$T$17 -> 0
E80: Siêu âm | T80: =SUM(R80:S80) -> 0 | U80: =IFERROR(R80/R$17,"") -> 0 | V80: =IFERROR(S80/S$17,"") | W80: =T80/$T$17 -> 0
C81: Utilization rate (Công suất sử dụng) | T81: =SUM(R81:S81) -> 0 | U81: =IFERROR(R81/R$17,"") -> 0 | V81: =IFERROR(S81/S$17,"") | W81: =T81/$T$17 -> 0
E82: MRI | T82: =SUM(R82:S82) -> 0 | U82: =IFERROR(R82/R$17,"") -> 0 | V82: =IFERROR(S82/S$17,"") | W82: =T82/$T$17 -> 0
E83: Mammo X-Quang | T83: =SUM(R83:S83) -> 0 | U83: =IFERROR(R83/R$17,"") -> 0 | V83: =IFERROR(S83/S$17,"") | W83: =T83/$T$17 -> 0
E84: CT | T84: =SUM(R84:S84) -> 0 | U84: =IFERROR(R84/R$17,"") -> 0 | V84: =IFERROR(S84/S$17,"") | W84: =T84/$T$17 -> 0
E85: X-Quang | T85: =SUM(R85:S85) -> 0 | U85: =IFERROR(R85/R$17,"") -> 0 | V85: =IFERROR(S85/S$17,"") | W85: =T85/$T$17 -> 0
E86: Siêu âm | T86: =SUM(R86:S86) -> 0 | U86: =IFERROR(R86/R$17,"") -> 0 | V86: =IFERROR(S86/S$17,"") | W86: =T86/$T$17 -> 0
B87: Lợi nhuận về công ty mẹ | F87: =F55-F56 -> -298.37158 | G87: =G55-G56 -> -7.0652704 | H87: =H55-H56 -> 50.144586 | I87: =I55-I56 -> 54.390228 | J87: =J55-J56 -> 281.48966 | K87: =K55-K56 -> 213.46582 | L87: =L55-L56 -> 100.44333 | M87: =M55-M56 -> -57.056154 | ... Q87: =Q55-Q56 -> -273.45653 | R87: =SUMIFS($F87:$Q87,$F$7:$Q$7,"A") -> -224.21354 | S87: =SUMIFS($F87:$Q87,$F$7:$Q$7,"B") -> 0 | T87: =SUM(R87:S87) -> -224.21354 | U87: =IFERROR(R87/R$17,"") -> -0.020547258 | V87: =IFERROR(S87/S$17,"") | W87: =T87/$T$17 -> -0.020547258 | AC87: =AC55-AC56 -> 1083.8321
B89: Vốn góp | AA89: ='Site list'!G6 -> 26000
B90: Phải trả cổ đông hợp tác kinh doanh gốc | F90: ='Site list'!$G$6*(1-'Site list'!$H$6)/10/12 -> 86.666667 | G90: ='Site list'!$G$6*(1-'Site list'!$H$6)/10/12 -> 86.666667 | H90: ='Site list'!$G$6*(1-'Site list'!$H$6)/10/12 -> 86.666667 | I90: ='Site list'!$G$6*(1-'Site list'!$H$6)/10/12 -> 86.666667 | J90: ='Site list'!$G$6*(1-'Site list'!$H$6)/10/12 -> 86.666667 | K90: ='Site list'!$G$6*(1-'Site list'!$H$6)/10/12 -> 86.666667 | L90: ='Site list'!$G$6*(1-'Site list'!$H$6)/10/12 -> 86.666667 | M90: ='Site list'!$G$6*(1-'Site list'!$H$6)/10/12 -> 86.666667 | ... Q90: ='Site list'!$G$6*(1-'Site list'!$H$6)/10/12 -> 86.666667 | AA90: =AA56 -> 0.4 | AC90: =AA89*AA90/10 -> 1040
B92: CÁC CHỈ TIÊU HIỆU QUẢ HOẠT ĐỘNG
C93: Số ca/tháng
E94: MRI | F94: 83 | G94: 154 | H94: 144 | I94: 193 | J94: 251 | K94: 125 | L94: 142 | M94: 179 | N94: 147 | O94: 100 | P94: 92 | Q94: 85 | R94: =SUMIFS($F94:$Q94,$F$7:$Q$7,"A") -> 1695 | S94: =SUMIFS($F94:$Q94,$F$7:$Q$7,"B") -> 0 | T94: =SUM(R94:S94) -> 1695 | AC94: =15*26*12 -> 4680 | AE94: =T94-SUM(J94:L94)-N94 -> 1030 | AF94: =AE94/SUM($AE$94,$AE$96) -> 0.29907085
E95: Mammo X-Quang | R95: =SUMIFS($F95:$Q95,$F$7:$Q$7,"A") -> 0 | S95: =SUMIFS($F95:$Q95,$F$7:$Q$7,"B") -> 0 | T95: =SUM(R95:S95) -> 0
E96: CT | F96: 51 | G96: 503 | H96: 772 | I96: 693 | J96: 1741 | K96: 1815 | L96: 1237 | M96: 299 | N96: 1772 | O96: 31 | P96: 31 | Q96: 34 | R96: =SUMIFS($F96:$Q96,$F$7:$Q$7,"A") -> 8979 | S96: =SUMIFS($F96:$Q96,$F$7:$Q$7,"B") -> 0 | T96: =SUM(R96:S96) -> 8979 | AC96: =AC94*3/7 -> 2005.7143 | AE96: =T96-SUM(J96:L96)-N96 -> 2414 | AF96: =AE96/SUM($AE$94,$AE$96) -> 0.70092915
E97: X-Quang
E98: Siêu âm
D99: Toàn chi nhánh
C101: Giá trung bình
E102: MRI | F102: =F12*10^6/F94 -> 2142168.7 | G102: =G12*10^6/G94 -> 2163636.4 | H102: =H12*10^6/H94 -> 2115777.8 | I102: =I12*10^6/I94 -> 2089490.2 | J102: =J12*10^6/J94 -> 2140757.4 | K102: =K12*10^6/K94 -> 2049334.4 | L102: =L12*10^6/L94 -> 2085915.5 | M102: =M12*10^6/M94 -> 2103352 | ... Q102: =Q12*10^6/Q94 -> 1829411.8 | T102: =T12*10^6/T94 -> 2068061.8 | AC102: ='Điểm hòa vốn'!H83 -> 2000000
E103: Mammo X-Quang
E104: CT | F104: =F14*10^6/F96 -> 1070588.2 | G104: =G14*10^6/G96 -> 1371769.4 | H104: =H14*10^6/H96 -> 1372020.7 | I104: =I14*10^6/I96 -> 1169175.8 | J104: =J14*10^6/J96 -> 580553.48 | K104: =K14*10^6/K96 -> 695939.94 | L104: =L14*10^6/L96 -> 697624.09 | M104: =M14*10^6/M96 -> 1143832.8 | ... Q104: =Q14*10^6/Q96 -> 1129411.8 | T104: =T14*10^6/T96 -> 824894.28 | AC104: ='Điểm hòa vốn'!H84 -> 1000000
E105: X-Quang
E106: Siêu âm
C108: Maximum capacity (Công suất tối đa ca/tháng)
...

Sheet ThaiNguyen
B6: BÁO CÁO KẾT QUẢ HOẠT ĐỘNG KINH DOANH CHI NHÁNH
B7: THÁI NGUYÊN | F7: A | G7: A | H7: A | I7: A | J7: A | K7: A | L7: A | M7: A | N7: A | O7: A | P7: A | Q7: A
B8: Năm tài chính 2025 | F8: Tháng | R8: ------------------Tổng-------------------- | U8: ------%Doanh thu------- | X8: ------------vs--------------
B9: VND triệu | F9: 1 | G9: 2 | H9: 3 | I9: 4 | J9: 5 | K9: 6 | L9: 7 | M9: 8 | N9: 9 | O9: 10 | P9: 11 | Q9: 12 | R9: Year to date | S9: Year to go | T9: LATEST ESTIMATE | U9: YTD | V9: YTG | W9: LE | X9: Last month | Y9: Last year
B10: Doanh thu
D11: Chẩn đoán hình ảnh
E12: MRI | F12: =75600000/(10^6) -> 75.6 | G12: =127900000/(10^6) -> 127.9 | H12: =206550000/(10^6) -> 206.55 | I12: =173900000/(10^6) -> 173.9 | J12: =239200000/(10^6) -> 239.2 | K12: =249200000/(10^6) -> 249.2 | L12: =272400000/(10^6) -> 272.4 | M12: =344600000/(10^6) -> 344.6 | N12: =336300000/(10^6) -> 336.3 | O12: =373300000/(10^6) -> 373.3 | P12: =431700000/(10^6) -> 431.7 | Q12: 448.3 | R12: =SUMIFS($F12:$Q12,$F$7:$Q$7,"A") -> 3278.95 | S12: =SUMIFS($F12:$Q12,$F$7:$Q$7,"B") -> 0 | T12: =SUM(R12:S12) -> 3278.95 | U12: =IFERROR(R12/R$17,"") -> 0.98702608 | V12: =IFERROR(S12/S$17,"") | W12: =IFERROR(T12/T$17,"") -> 0.98702608
E13: Mammo X-Quang | F13: =0/(10^6) -> 0 | G13: =0/(10^6) -> 0 | H13: =0/(10^6) -> 0 | I13: =0/(10^6) -> 0 | J13: =0/(10^6) -> 0 | K13: =0/(10^6) -> 0 | L13: =0/(10^6) -> 0 | M13: =0/(10^6) -> 0 | ... P13: =0/(10^6) -> 0 | Q13: =P13 -> 0 | R13: =SUMIFS($F13:$Q13,$F$7:$Q$7,"A") -> 0 | S13: =SUMIFS($F13:$Q13,$F$7:$Q$7,"B") -> 0 | T13: =SUM(R13:S13) -> 0 | U13: =IFERROR(R13/R$17,"") -> 0 | V13: =IFERROR(S13/S$17,"") | W13: =IFERROR(T13/T$17,"") -> 0
E14: CT | F14: =0/(10^6) -> 0 | G14: =0/(10^6) -> 0 | H14: =0/(10^6) -> 0 | I14: =0/(10^6) -> 0 | J14: =0/(10^6) -> 0 | K14: =0/(10^6) -> 0 | L14: =1500000/(10^6) -> 1.5 | M14: =1000000/(10^6) -> 1 | N14: =12250000/(10^6) -> 12.25 | O14: =4500000/(10^6) -> 4.5 | P14: =750000/(10^6) -> 0.75 | Q14: 15 | R14: =SUMIFS($F14:$Q14,$F$7:$Q$7,"A") -> 35 | S14: =SUMIFS($F14:$Q14,$F$7:$Q$7,"B") -> 0 | T14: =SUM(R14:S14) -> 35 | U14: =IFERROR(R14/R$17,"") -> 0.010535663 | V14: =IFERROR(S14/S$17,"") | W14: =IFERROR(T14/T$17,"") -> 0.010535663
E15: X-Quang | N15: 0.6 | O15: 3.15 | P15: 2.7 | Q15: 1.65 | R15: =SUMIFS($F15:$Q15,$F$7:$Q$7,"A") -> 8.1 | S15: =SUMIFS($F15:$Q15,$F$7:$Q$7,"B") -> 0 | T15: =SUM(R15:S15) -> 8.1 | U15: =IFERROR(R15/R$17,"") -> 0.0024382535 | V15: =IFERROR(S15/S$17,"") | W15: =IFERROR(T15/T$17,"") -> 0.0024382535
E16: Siêu âm | Q16: =P16 -> 0 | R16: =SUMIFS($F16:$Q16,$F$7:$Q$7,"A") -> 0 | S16: =SUMIFS($F16:$Q16,$F$7:$Q$7,"B") -> 0 | T16: =SUM(R16:S16) -> 0 | U16: =IFERROR(R16/R$17,"") -> 0 | V16: =IFERROR(S16/S$17,"") | W16: =IFERROR(T16/T$17,"") -> 0
D17: Tổng- Chẩn đoán hình ảnh | F17: =SUM(F12:F16) -> 75.6 | G17: =SUM(G12:G16) -> 127.9 | H17: =SUM(H12:H16) -> 206.55 | I17: =SUM(I12:I16) -> 173.9 | J17: =SUM(J12:J16) -> 239.2 | K17: =SUM(K12:K16) -> 249.2 | L17: =SUM(L12:L16) -> 273.9 | M17: =SUM(M12:M16) -> 345.6 | ... Q17: =SUM(Q12:Q16) -> 464.95 | R17: =SUMIFS($F17:$Q17,$F$7:$Q$7,"A") -> 3322.05 | S17: =SUMIFS($F17:$Q17,$F$7:$Q$7,"B") -> 0 | T17: =SUM(R17:S17) -> 3322.05 | U17: =IFERROR(R17/R$17,"") -> 1 | V17: =IFERROR(S17/S$17,"") | W17: =IFERROR(T17/T$17,"") -> 1
D18: Tổng- Khác | F18: 0 | G18: 0 | H18: 0 | I18: 0 | J18: 0 | K18: 0 | L18: 0 | M18: 0 | N18: 0 | O18: 0 | P18: 0 | Q18: 0 | R18: =SUMIFS($F18:$Q18,$F$7:$Q$7,"A") -> 0 | S18: =SUMIFS($F18:$Q18,$F$7:$Q$7,"B") -> 0 | T18: =SUM(R18:S18) -> 0 | U18: =IFERROR(R18/R$17,"") -> 0 | V18: =IFERROR(S18/S$17,"") | W18: =IFERROR(T18/T$17,"") -> 0
B19: Tổng- Doanh thu | F19: =SUM(F17,F18) -> 75.6 | G19: =SUM(G17,G18) -> 127.9 | H19: =SUM(H17,H18) -> 206.55 | I19: =SUM(I17,I18) -> 173.9 | J19: =SUM(J17,J18) -> 239.2 | K19: =SUM(K17,K18) -> 249.2 | L19: =SUM(L17,L18) -> 273.9 | M19: =SUM(M17,M18) -> 345.6 | ... Q19: =SUM(Q17,Q18) -> 464.95 | R19: =SUMIFS($F19:$Q19,$F$7:$Q$7,"A") -> 3322.05 | S19: =SUMIFS($F19:$Q19,$F$7:$Q$7,"B") -> 0 | T19: =SUM(R19:S19) -> 3322.05 | U19: =IFERROR(R19/R$17,"") -> 1 | V19: =IFERROR(S19/S$17,"") | W19: =IFERROR(T19/T$17,"") -> 1
B20: Giảm trừ doanh thu | F20: =SUBTOTAL(9,F21:F25) -> 0 | G20: =SUBTOTAL(9,G21:G25) -> 25.58 | H20: =SUBTOTAL(9,H21:H25) -> 42.75 | I20: =SUBTOTAL(9,I21:I25) -> 35.32 | J20: =SUBTOTAL(9,J21:J25) -> 56.66 | K20: =SUBTOTAL(9,K21:K25) -> 50.02 | L20: =SUBTOTAL(9,L21:L25) -> 54.66 | M20: =SUBTOTAL(9,M21:M25) -> 76.5 | ... Q20: =SUBTOTAL(9,Q21:Q25) -> 93.32 | R20: =SUMIFS($F20:$Q20,$F$7:$Q$7,"A") -> 675.48 | S20: =SUMIFS($F20:$Q20,$F$7:$Q$7,"B") -> 0 | T20: =SUM(R20:S20) -> 675.48 | U20: =IFERROR(R20/R$17,"") -> 0.20333228 | V20: =IFERROR(S20/S$17,"") | W20: =IFERROR(T20/T$17,"") -> 0.20333228
E21: MRI | F21: =0/(10^6) -> 0 | G21: =25580000/(10^6) -> 25.58 | H21: =42750000/(10^6) -> 42.75 | I21: =35320000/(10^6) -> 35.32 | J21: =56660000/(10^6) -> 56.66 | K21: =50020000/(10^6) -> 50.02 | L21: =54660000/(10^6) -> 54.66 | M21: =76500000/(10^6) -> 76.5 | N21: =70370000/(10^6) -> 70.37 | O21: =77900000/(10^6) -> 77.9 | P21: =92400000/(10^6) -> 92.4 | Q21: =93320000/(10^6) -> 93.32 | R21: =SUMIFS($F21:$Q21,$F$7:$Q$7,"A") -> 675.48 | S21: =SUMIFS($F21:$Q21,$F$7:$Q$7,"B") -> 0 | T21: =SUM(R21:S21) -> 675.48 | U21: =IFERROR(R21/R12,"") -> 0.20600497 | V21: =IFERROR(S21/S12,"") | W21: =IFERROR(T21/T12,"") -> 0.20600497
E22: Mammo X-Quang | R22: =SUMIFS($F22:$Q22,$F$7:$Q$7,"A") -> 0 | S22: =SUMIFS($F22:$Q22,$F$7:$Q$7,"B") -> 0 | T22: =SUM(R22:S22) -> 0 | U22: =IFERROR(R22/R13,"") | V22: =IFERROR(S22/S13,"") | W22: =IFERROR(T22/T13,"")
E23: CT | R23: =SUMIFS($F23:$Q23,$F$7:$Q$7,"A") -> 0 | S23: =SUMIFS($F23:$Q23,$F$7:$Q$7,"B") -> 0 | T23: =SUM(R23:S23) -> 0 | U23: =IFERROR(R23/R14,"") -> 0 | V23: =IFERROR(S23/S14,"") | W23: =IFERROR(T23/T14,"") -> 0
E24: X-Quang | R24: =SUMIFS($F24:$Q24,$F$7:$Q$7,"A") -> 0 | S24: =SUMIFS($F24:$Q24,$F$7:$Q$7,"B") -> 0 | T24: =SUM(R24:S24) -> 0 | U24: =IFERROR(R24/R15,"") -> 0 | V24: =IFERROR(S24/S15,"") | W24: =IFERROR(T24/T15,"") -> 0
E25: Siêu âm | R25: =SUMIFS($F25:$Q25,$F$7:$Q$7,"A") -> 0 | S25: =SUMIFS($F25:$Q25,$F$7:$Q$7,"B") -> 0 | T25: =SUM(R25:S25) -> 0 | U25: =IFERROR(R25/R16,"") | V25: =IFERROR(S25/S16,"") | W25: =IFERROR(T25/T16,"")
B26: Biến phí
C27: Vật tư tiêu hao | F27: =2479500/(10^6) -> 2.4795 | G27: =4075500/(10^6) -> 4.0755 | H27: =6982500/(10^6) -> 6.9825 | I27: =5671500/(10^6) -> 5.6715 | J27: =7609500/(10^6) -> 7.6095 | K27: =13025049/(10^6) -> 13.025049 | L27: =9199623/(10^6) -> 9.199623 | M27: =11153324/(10^6) -> 11.153324 | N27: =10855305/(10^6) -> 10.855305 | O27: =11724031/(10^6) -> 11.724031 | P27: =14041250/(10^6) -> 14.04125 | Q27: 14.599018 | R27: =SUMIFS($F27:$Q27,$F$7:$Q$7,"A") -> 111.4161 | S27: =SUMIFS($F27:$Q27,$F$7:$Q$7,"B") -> 0 | T27: =SUM(R27:S27) -> 111.4161 | U27: =IFERROR(R27/R$17,"") -> 0.033538357 | V27: =IFERROR(S27/S$17,"") | W27: =IFERROR(T27/T$17,"") -> 0.033538357
C28: Chi phí đọc kết quả online | F28: =4950000/(10^6) -> 4.95 | G28: =7705000/(10^6) -> 7.705 | H28: =13110000/(10^6) -> 13.11 | I28: =11040000/(10^6) -> 11.04 | J28: =14145000/(10^6) -> 14.145 | K28: =14950000/(10^6) -> 14.95 | L28: =16790000/(10^6) -> 16.79 | M28: =20930000/(10^6) -> 20.93 | N28: =22174000/(10^6) -> 22.174 | O28: =24512000/(10^6) -> 24.512 | P28: =26995000/(10^6) -> 26.995 | Q28: 29.89 | R28: =SUMIFS($F28:$Q28,$F$7:$Q$7,"A") -> 207.191 | S28: =SUMIFS($F28:$Q28,$F$7:$Q$7,"B") -> 0 | T28: =SUM(R28:S28) -> 207.191 | U28: =IFERROR(R28/R$17,"") -> 0.062368417 | V28: =IFERROR(S28/S$17,"") | W28: =IFERROR(T28/T$17,"") -> 0.062368417
C29: Tiền thuốc | F29: =0/(10^6) -> 0 | G29: =0/(10^6) -> 0 | H29: =0/(10^6) -> 0 | I29: =0/(10^6) -> 0 | J29: =0/(10^6) -> 0 | K29: =0/(10^6) -> 0 | L29: =6292000/(10^6) -> 6.292 | M29: =6292000/(10^6) -> 6.292 | N29: =5720000/(10^6) -> 5.72 | O29: =6292000/(10^6) -> 6.292 | P29: =5720000/(10^6) -> 5.72 | Q29: 3.432 | R29: =SUMIFS($F29:$Q29,$F$7:$Q$7,"A") -> 33.748 | S29: =SUMIFS($F29:$Q29,$F$7:$Q$7,"B") -> 0 | T29: =SUM(R29:S29) -> 33.748 | U29: =IFERROR(R29/R$17,"") -> 0.010158787 | V29: =IFERROR(S29/S$17,"") | W29: =IFERROR(T29/T$17,"") -> 0.010158787
C30: Tư vấn chuyên môn | F30: =12600000/(10^6) -> 12.6 | G30: =19950000/(10^6) -> 19.95 | H30: =32200000/(10^6) -> 32.2 | I30: =26850000/(10^6) -> 26.85 | J30: =32650000/(10^6) -> 32.65 | K30: =35950000/(10^6) -> 35.95 | L30: =41000000/(10^6) -> 41 | M30: =50100000/(10^6) -> 50.1 | N30: =47750000/(10^6) -> 47.75 | O30: =48600000/(10^6) -> 48.6 | P30: =56900000/(10^6) -> 56.9 | Q30: 61.85 | R30: =SUMIFS($F30:$Q30,$F$7:$Q$7,"A") -> 466.4 | S30: =SUMIFS($F30:$Q30,$F$7:$Q$7,"B") -> 0 | T30: =SUM(R30:S30) -> 466.4 | U30: =IFERROR(R30/R$17,"") -> 0.14039524 | V30: =IFERROR(S30/S$17,"") | W30: =IFERROR(T30/T$17,"") -> 0.14039524
C31: Hoa hồng + thưởng nhân viên | F31: 0 | G31: 0 | H31: 4.44 | I31: 3.7 | J31: 4.58 | K31: 5.16 | L31: 6.28 | M31: 7.6 | N31: 8.76 | O31: 9.87 | P31: 11.25 | Q31: 12.29 | R31: =SUMIFS($F31:$Q31,$F$7:$Q$7,"A") -> 73.93 | S31: =SUMIFS($F31:$Q31,$F$7:$Q$7,"B") -> 0 | T31: =SUM(R31:S31) -> 73.93 | U31: =IFERROR(R31/R$17,"") -> 0.022254331 | V31: =IFERROR(S31/S$17,"") | W31: =IFERROR(T31/T$17,"") -> 0.022254331
C32: Truyền thông marketing | F32: =1139600/(10^6) -> 1.1396 | G32: =150000/(10^6) -> 0.15 | H32: =0/(10^6) -> 0 | I32: =4187333/(10^6) -> 4.187333 | J32: =11933333/(10^6) -> 11.933333 | K32: =1433334/(10^6) -> 1.433334 | L32: =1836000/(10^6) -> 1.836 | M32: =28391380/(10^6) -> 28.39138 | N32: =14994333/(10^6) -> 14.994333 | O32: =13288499/(10^6) -> 13.288499 | P32: =17825204/(10^6) -> 17.825204 | Q32: 2.25 | R32: =SUMIFS($F32:$Q32,$F$7:$Q$7,"A") -> 97.429016 | S32: =SUMIFS($F32:$Q32,$F$7:$Q$7,"B") -> 0 | T32: =SUM(R32:S32) -> 97.429016 | U32: =IFERROR(R32/R$17,"") -> 0.02932798 | V32: =IFERROR(S32/S$17,"") | W32: =IFERROR(T32/T$17,"") -> 0.02932798
B33: Tổng- Biến phí | F33: =SUM(F27:F32) -> 21.1691 | G33: =SUM(G27:G32) -> 31.8805 | H33: =SUM(H27:H32) -> 56.7325 | I33: =SUM(I27:I32) -> 51.448833 | J33: =SUM(J27:J32) -> 70.917833 | K33: =SUM(K27:K32) -> 70.518383 | L33: =SUM(L27:L32) -> 81.397623 | M33: =SUM(M27:M32) -> 124.4667 | ... Q33: =SUM(Q27:Q32) -> 124.31102 | R33: =SUMIFS($F33:$Q33,$F$7:$Q$7,"A") -> 990.11412 | S33: =SUMIFS($F33:$Q33,$F$7:$Q$7,"B") -> 0 | T33: =SUM(R33:S33) -> 990.11412 | U33: =IFERROR(R33/R$17,"") -> 0.29804311 | V33: =IFERROR(S33/S$17,"") | W33: =IFERROR(T33/T$17,"") -> 0.29804311
B34: Lãi trên biến phí | F34: =F19-F33-F20 -> 54.4309 | G34: =G19-G33-G20 -> 70.4395 | H34: =H19-H33-H20 -> 107.0675 | I34: =I19-I33-I20 -> 87.131167 | J34: =J19-J33-J20 -> 111.62217 | K34: =K19-K33-K20 -> 128.66162 | L34: =L19-L33-L20 -> 137.84238 | M34: =M19-M33-M20 -> 144.6333 | ... Q34: =Q19-Q33-Q20 -> 247.31898 | R34: =SUMIFS($F34:$Q34,$F$7:$Q$7,"A") -> 1656.4559 | S34: =SUMIFS($F34:$Q34,$F$7:$Q$7,"B") -> 0 | T34: =SUM(R34:S34) -> 1656.4559 | U34: =IFERROR(R34/R$17,"") -> 0.49862461 | V34: =IFERROR(S34/S$17,"") | W34: =IFERROR(T34/T$17,"") -> 0.49862461
B35: Định phí | R35: =SUMIFS($F35:$Q35,$F$7:$Q$7,"A") -> 0 | S35: =SUMIFS($F35:$Q35,$F$7:$Q$7,"B") -> 0 | T35: =SUM(R35:S35) -> 0 | U35: =IFERROR(R35/R$17,"") -> 0 | V35: =IFERROR(S35/S$17,"") | W35: =IFERROR(T35/T$17,"") -> 0
C36: Chi phí nhân viên | F36: 105.04074 | G36: 93.078646 | H36: 96.14881 | I36: 99.908 | J36: 103.68574 | K36: 90.56 | L36: 88.948567 | M36: 109.07308 | N36: 102.16072 | O36: 91.889029 | P36: 96.52625 | Q36: 105.93042 | R36: =SUMIFS($F36:$Q36,$F$7:$Q$7,"A") -> 1182.95 | S36: =SUMIFS($F36:$Q36,$F$7:$Q$7,"B") -> 0 | T36: =SUM(R36:S36) -> 1182.95 | U36: =IFERROR(R36/R$17,"") -> 0.35609037 | V36: =IFERROR(S36/S$17,"") | W36: =IFERROR(T36/T$17,"") -> 0.35609037
C37: Chi phí thuê địa điểm | F37: =72885771/(10^6) -> 72.885771 | G37: =71166667/(10^6) -> 71.166667 | H37: =71166667/(10^6) -> 71.166667 | I37: =67666667/(10^6) -> 67.666667 | J37: =67666667/(10^6) -> 67.666667 | K37: =38500000/(10^6) -> 38.5 | L37: =38500000/(10^6) -> 38.5 | M37: =38500000/(10^6) -> 38.5 | N37: =38500000/(10^6) -> 38.5 | O37: =38888889/(10^6) -> 38.888889 | P37: =38888889/(10^6) -> 38.888889 | Q37: =38888889/(10^6) -> 38.888889 | R37: =SUMIFS($F37:$Q37,$F$7:$Q$7,"A") -> 621.21911 | S37: =SUMIFS($F37:$Q37,$F$7:$Q$7,"B") -> 0 | T37: =SUM(R37:S37) -> 621.21911 | U37: =IFERROR(R37/R$17,"") -> 0.18699872 | V37: =IFERROR(S37/S$17,"") | W37: =IFERROR(T37/T$17,"") -> 0.18699872
C38: Chi phí bảo dưỡng bảo trì máy | R38: =SUMIFS($F38:$Q38,$F$7:$Q$7,"A") -> 0 | S38: =SUMIFS($F38:$Q38,$F$7:$Q$7,"B") -> 0 | T38: =SUM(R38:S38) -> 0 | U38: =IFERROR(R38/R$17,"") -> 0 | V38: =IFERROR(S38/S$17,"") | W38: =IFERROR(T38/T$17,"") -> 0
C39: Chi phí vận hành thường xuyên | F39: 75.350039 | G39: 63.717651 | H39: 71.144692 | I39: 78.90607 | J39: 72.817214 | K39: 71.340979 | L39: 57.713592 | M39: 63.092723 | N39: 58.377881 | O39: 57.335951 | P39: 51.055349 | Q39: 51.735282 | R39: =SUMIFS($F39:$Q39,$F$7:$Q$7,"A") -> 772.58742 | S39: =SUMIFS($F39:$Q39,$F$7:$Q$7,"B") -> 0 | T39: =SUM(R39:S39) -> 772.58742 | U39: =IFERROR(R39/R$17,"") -> 0.23256345 | V39: =IFERROR(S39/S$17,"") | W39: =IFERROR(T39/T$17,"") -> 0.23256345
C40: Chi phí khác | F40: 7.237719 | G40: 2.919079 | H40: 2.669079 | I40: 2.715279 | J40: 3.252279 | K40: 17.894598 | L40: 3.279079 | M40: 11.248608 | N40: 7.925439 | O40: 25.93781 | P40: 6.289017 | Q40: 3.275859 | R40: =SUMIFS($F40:$Q40,$F$7:$Q$7,"A") -> 94.643845 | S40: =SUMIFS($F40:$Q40,$F$7:$Q$7,"B") -> 0 | T40: =SUM(R40:S40) -> 94.643845 | U40: =IFERROR(R40/R$17,"") -> 0.028489591 | V40: =IFERROR(S40/S$17,"") | W40: =IFERROR(T40/T$17,"") -> 0.028489591
B41: Tổng- Định phí | F41: =SUM(F36:F40) -> 260.51427 | G41: =SUM(G36:G40) -> 230.88204 | H41: =SUM(H36:H40) -> 241.12925 | I41: =SUM(I36:I40) -> 249.19602 | J41: =SUM(J36:J40) -> 247.4219 | K41: =SUM(K36:K40) -> 218.29558 | L41: =SUM(L36:L40) -> 188.44124 | M41: =SUM(M36:M40) -> 221.91441 | ... Q41: =SUM(Q36:Q40) -> 199.83045 | R41: =SUMIFS($F41:$Q41,$F$7:$Q$7,"A") -> 2671.4004 | S41: =SUMIFS($F41:$Q41,$F$7:$Q$7,"B") -> 0 | T41: =SUM(R41:S41) -> 2671.4004 | U41: =IFERROR(R41/R$17,"") -> 0.80414213 | V41: =IFERROR(S41/S$17,"") | W41: =IFERROR(T41/T$17,"") -> 0.80414213
B42: EBITDA | F42: =F34-F41 -> -206.08337 | G42: =G34-G41 -> -160.44254 | H42: =H34-H41 -> -134.06175 | I42: =I34-I41 -> -162.06485 | J42: =J34-J41 -> -135.79973 | K42: =K34-K41 -> -89.63396 | L42: =L34-L41 -> -50.598861 | M42: =M34-M41 -> -77.281112 | ... Q42: =Q34-Q41 -> 47.488533 | R42: =SUMIFS($F42:$Q42,$F$7:$Q$7,"A") -> -1014.9445 | S42: =SUMIFS($F42:$Q42,$F$7:$Q$7,"B") -> 0 | T42: =SUM(R42:S42) -> -1014.9445 | U42: =IFERROR(R42/R$17,"") -> -0.30551752 | V42: =IFERROR(S42/S$17,"") | W42: =IFERROR(T42/T$17,"") -> -0.30551752
B43: EBITDA về công ty mẹ | R43: =SUMIFS($F43:$Q43,$F$7:$Q$7,"A") -> 0 | S43: =SUMIFS($F43:$Q43,$F$7:$Q$7,"B") -> 0 | T43: =SUM(R43:S43) -> 0 | U43: =IFERROR(R43/R$17,"") -> 0 | V43: =IFERROR(S43/S$17,"") | W43: =IFERROR(T43/T$17,"") -> 0
C44: Chi phí khấu hao máy | F44: =SUM(F45:F49) -> 143.33333 | G44: =SUM(G45:G49) -> 143.33333 | H44: =SUM(H45:H49) -> 143.33333 | I44: =SUM(I45:I49) -> 143.33333 | J44: =SUM(J45:J49) -> 143.33333 | K44: =SUM(K45:K49) -> 143.33333 | L44: =SUM(L45:L49) -> 143.33333 | M44: =SUM(M45:M49) -> 165.91398 | ... P44: =SUM(P45:P49) -> 171.03333 | Q44: =P44 -> 171.03333 | R44: =SUMIFS($F44:$Q44,$F$7:$Q$7,"A") -> 1851.7306 | S44: =SUMIFS($F44:$Q44,$F$7:$Q$7,"B") -> 0 | T44: =SUM(R44:S44) -> 1851.7306 | U44: =IFERROR(R44/R$17,"") -> 0.55740601 | V44: =IFERROR(S44/S$17,"") | W44: =IFERROR(T44/T$17,"") -> 0.55740601
E45: MRI | F45: 143.33333 | G45: 143.33333 | H45: 143.33333 | I45: 143.33333 | J45: 143.33333 | K45: 143.33333 | L45: 143.33333 | M45: 143.33333 | N45: 143.33333 | O45: 143.33333 | P45: 143.33333 | Q45: 143.33333 | R45: =SUMIFS($F45:$Q45,$F$7:$Q$7,"A") -> 1720 | S45: =SUMIFS($F45:$Q45,$F$7:$Q$7,"B") -> 0 | T45: =SUM(R45:S45) -> 1720 | U45: =IFERROR(R45/R$17,"") -> 0.51775259 | V45: =IFERROR(S45/S$17,"") | W45: =IFERROR(T45/T$17,"") -> 0.51775259
E46: Mammo X-Quang | F46: 0 | G46: 0 | H46: 0 | I46: 0 | J46: 0 | K46: 0 | L46: 0 | M46: 0 | N46: 0 | O46: 0 | P46: 0 | Q46: =P46 -> 0 | R46: =SUMIFS($F46:$Q46,$F$7:$Q$7,"A") -> 0 | S46: =SUMIFS($F46:$Q46,$F$7:$Q$7,"B") -> 0 | T46: =SUM(R46:S46) -> 0 | U46: =IFERROR(R46/R$17,"") -> 0 | V46: =IFERROR(S46/S$17,"") | W46: =IFERROR(T46/T$17,"") -> 0
E47: CT | M47: =22580645/10^6 -> 22.580645 | N47: 25 | O47: 25 | P47: 25 | Q47: 25 | R47: =SUMIFS($F47:$Q47,$F$7:$Q$7,"A") -> 122.58065 | S47: =SUMIFS($F47:$Q47,$F$7:$Q$7,"B") -> 0 | T47: =SUM(R47:S47) -> 122.58065 | U47: =IFERROR(R47/R$17,"") -> 0.036899097 | V47: =IFERROR(S47/S$17,"") | W47: =IFERROR(T47/T$17,"") -> 0.036899097
E48: X-Quang | F48: =0/(10^6) -> 0 | G48: =0/(10^6) -> 0 | H48: =0/(10^6) -> 0 | I48: =0/(10^6) -> 0 | J48: =0/(10^6) -> 0 | K48: =0/(10^6) -> 0 | L48: =0/(10^6) -> 0 | M48: =0/(10^6) -> 0 | N48: 0.6 | O48: 3.15 | P48: 2.7 | Q48: 1.65 | R48: =SUMIFS($F48:$Q48,$F$7:$Q$7,"A") -> 8.1 | S48: =SUMIFS($F48:$Q48,$F$7:$Q$7,"B") -> 0 | T48: =SUM(R48:S48) -> 8.1 | U48: =IFERROR(R48/R$17,"") -> 0.0024382535 | V48: =IFERROR(S48/S$17,"") | W48: =IFERROR(T48/T$17,"") -> 0.0024382535
E49: Siêu âm | F49: =0/(10^6) -> 0 | G49: =0/(10^6) -> 0 | H49: =0/(10^6) -> 0 | I49: =0/(10^6) -> 0 | J49: =0/(10^6) -> 0 | K49: =0/(10^6) -> 0 | L49: =0/(10^6) -> 0 | M49: =0/(10^6) -> 0 | ... P49: =0/(10^6) -> 0 | Q49: =P49 -> 0 | R49: =SUMIFS($F49:$Q49,$F$7:$Q$7,"A") -> 0 | S49: =SUMIFS($F49:$Q49,$F$7:$Q$7,"B") -> 0 | T49: =SUM(R49:S49) -> 0 | U49: =IFERROR(R49/R$17,"") -> 0 | V49: =IFERROR(S49/S$17,"") | W49: =IFERROR(T49/T$17,"") -> 0
C50: Chi phí khấu hao khác | F50: 25.220377 | G50: 25.220377 | H50: 25.220377 | I50: 25.220377 | J50: 25.220377 | K50: 25.220377 | L50: 25.220377 | M50: 25.220377 | N50: 25.220377 | O50: 25.220377 | P50: 25.220377 | Q50: 25.220377 | R50: =SUMIFS($F50:$Q50,$F$7:$Q$7,"A") -> 302.64452 | S50: =SUMIFS($F50:$Q50,$F$7:$Q$7,"B") -> 0 | T50: =SUM(R50:S50) -> 302.64452 | U50: =IFERROR(R50/R$17,"") -> 0.091101737 | V50: =IFERROR(S50/S$17,"") | W50: =IFERROR(T50/T$17,"") -> 0.091101737
C51: Lợi nhuận khác | Q51: 0 | R51: =SUMIFS($F51:$Q51,$F$7:$Q$7,"A") -> 0 | S51: =SUMIFS($F51:$Q51,$F$7:$Q$7,"B") -> 0 | T51: =SUM(R51:S51) -> 0 | U51: =IFERROR(R51/R$17,"") -> 0 | V51: =IFERROR(S51/S$17,"") | W51: =IFERROR(T51/T$17,"") -> 0
C52: Chi phí tài chính | F52: =62998000/(10^6) -> 62.998 | G52: =60423455/(10^6) -> 60.423455 | H52: =59475860/(10^6) -> 59.47586 | I52: =60965753/(10^6) -> 60.965753 | J52: =62997945/(10^6) -> 62.997945 | K52: =62997891/(10^6) -> 62.997891 | L52: =62997945/(10^6) -> 62.997945 | M52: =62997945/(10^6) -> 62.997945 | N52: =60965753/(10^6) -> 60.965753 | O52: =59060206/(10^6) -> 59.060206 | P52: =57917466/(10^6) -> 57.917466 | Q52: =68829452/(10^6) -> 68.829452 | R52: =SUMIFS($F52:$Q52,$F$7:$Q$7,"A") -> 742.62767 | S52: =SUMIFS($F52:$Q52,$F$7:$Q$7,"B") -> 0 | T52: =SUM(R52:S52) -> 742.62767 | U52: =IFERROR(R52/R$17,"") -> 0.223545 | V52: =IFERROR(S52/S$17,"") | W52: =IFERROR(T52/T$17,"") -> 0.223545
B53: Lợi nhuận/(Lỗ) trước thuế | F53: =F42-F44-F50+F51-F52 -> -437.63508 | G53: =G42-G44-G50+G51-G52 -> -389.41971 | H53: =H42-H44-H50+H51-H52 -> -362.09132 | I53: =I42-I44-I50+I51-I52 -> -391.58431 | J53: =J42-J44-J50+J51-J52 -> -367.35139 | K53: =K42-K44-K50+K51-K52 -> -321.18556 | L53: =L42-L44-L50+L51-L52 -> -282.15052 | M53: =M42-M44-M50+M51-M52 -> -331.41341 | ... Q53: =Q42-Q44-Q50+Q51-Q52 -> -217.59463 | R53: =SUMIFS($F53:$Q53,$F$7:$Q$7,"A") -> -3911.9473 | S53: =SUMIFS($F53:$Q53,$F$7:$Q$7,"B") -> 0 | T53: =SUM(R53:S53) -> -3911.9473 | U53: =IFERROR(R53/R$17,"") -> -1.1775703 | V53: =IFERROR(S53/S$17,"") | W53: =IFERROR(T53/T$17,"") -> -1.1775703
C54: Chi phí thuế TNDN | F54: =IF(F53<0,0,F53*20%) -> 0 | R54: =SUMIFS($F54:$Q54,$F$7:$Q$7,"A") -> 0 | S54: =SUMIFS($F54:$Q54,$F$7:$Q$7,"B") -> 0 | T54: =SUM(R54:S54) -> 0 | U54: =IFERROR(R54/R$17,"") -> 0 | V54: =IFERROR(S54/S$17,"") | W54: =IFERROR(T54/T$17,"") -> 0
B55: Lợi nhuận sau thuế | F55: =F53-F54 -> -437.63508 | G55: =G53-G54 -> -389.41971 | H55: =H53-H54 -> -362.09132 | I55: =I53-I54 -> -391.58431 | J55: =J53-J54 -> -367.35139 | K55: =K53-K54 -> -321.18556 | L55: =L53-L54 -> -282.15052 | M55: =M53-M54 -> -331.41341 | ... Q55: =Q53-Q54 -> -217.59463 | R55: =SUMIFS($F55:$Q55,$F$7:$Q$7,"A") -> -3911.9473 | S55: =SUMIFS($F55:$Q55,$F$7:$Q$7,"B") -> 0 | T55: =SUM(R55:S55) -> -3911.9473 | U55: =IFERROR(R55/R$17,"") -> -1.1775703 | V55: =IFERROR(S55/S$17,"") | W55: =IFERROR(T55/T$17,"") -> -1.1775703
C56: Cổ đông thiểu số | R56: =SUMIFS($F56:$Q56,$F$7:$Q$7,"A") -> 0 | S56: =SUMIFS($F56:$Q56,$F$7:$Q$7,"B") -> 0 | T56: =SUM(R56:S56) -> 0 | U56: =IFERROR(R56/R$17,"") -> 0 | V56: =IFERROR(S56/S$17,"") | W56: =IFERROR(T56/T$17,"") -> 0
B57: Lợi nhuận về công ty mẹ | R57: =SUMIFS($F57:$Q57,$F$7:$Q$7,"A") -> 0 | S57: =SUMIFS($F57:$Q57,$F$7:$Q$7,"B") -> 0 | T57: =SUM(R57:S57) -> 0 | U57: =IFERROR(R57/R$17,"") -> 0 | V57: =IFERROR(S57/S$17,"") | W57: =IFERROR(T57/T$17,"") -> 0
B59: Vốn góp
B60: Phải trả cổ đông hợp tác kinh doanh gốc | F60: ='Site list'!$G$7*(1-'Site list'!$H$7)/10/12 -> 8.3324475 | G60: ='Site list'!$G$7*(1-'Site list'!$H$7)/10/12 -> 8.3324475 | H60: ='Site list'!$G$7*(1-'Site list'!$H$7)/10/12 -> 8.3324475 | I60: ='Site list'!$G$7*(1-'Site list'!$H$7)/10/12 -> 8.3324475 | J60: ='Site list'!$G$7*(1-'Site list'!$H$7)/10/12 -> 8.3324475 | K60: ='Site list'!$G$7*(1-'Site list'!$H$7)/10/12 -> 8.3324475 | L60: ='Site list'!$G$7*(1-'Site list'!$H$7)/10/12 -> 8.3324475 | M60: ='Site list'!$G$7*(1-'Site list'!$H$7)/10/12 -> 8.3324475 | ... Q60: ='Site list'!$G$7*(1-'Site list'!$H$7)/10/12 -> 8.3324475
B61: Số ca/tháng
E62: MRI | F62: 42 | G62: 67 | H62: 111 | I62: 96 | J62: 123 | K62: 130 | L62: 144 | M62: 181 | N62: 176 | O62: 200 | P62: 232 | Q62: 243 | R62: =SUMIFS($F62:$Q62,$F$7:$Q$7,"A") -> 1745 | S62: =SUMIFS($F62:$Q62,$F$7:$Q$7,"B") -> 0 | T62: =SUM(R62:S62) -> 1745
E63: CT | L63: 2 | M63: 1 | N63: 15 | O63: 6 | P63: 1 | Q63: 15 | R63: =SUMIFS($F63:$Q63,$F$7:$Q$7,"A") -> 40 | S63: =SUMIFS($F63:$Q63,$F$7:$Q$7,"B") -> 0 | T63: =SUM(R63:S63) -> 40
E64: X Quang | N64: 4 | O64: 21 | P64: 18 | Q64: 11 | R64: =SUMIFS($F64:$Q64,$F$7:$Q$7,"A") -> 54 | S64: =SUMIFS($F64:$Q64,$F$7:$Q$7,"B") -> 0 | T64: =SUM(R64:S64) -> 54
B65: Giá trung bình
E66: MRI | F66: =F12*10^6/F62 -> 1800000 | G66: =G12*10^6/G62 -> 1908955.2 | H66: =H12*10^6/H62 -> 1860810.8 | I66: =I12*10^6/I62 -> 1811458.3 | J66: =J12*10^6/J62 -> 1944715.4 | K66: =K12*10^6/K62 -> 1916923.1 | L66: =L12*10^6/L62 -> 1891666.7 | M66: =M12*10^6/M62 -> 1903867.4 | ... Q66: =Q12*10^6/Q62 -> 1844856
E67: CT | L67: =L14*10^6/L63 -> 750000 | M67: =M14*10^6/M63 -> 1000000 | N67: =N14*10^6/N63 -> 816666.67 | O67: =O14*10^6/O63 -> 750000 | P67: =P14*10^6/P63 -> 750000 | Q67: =Q14*10^6/Q63 -> 1000000
E68: X Quang | N68: =N15*10^6/N64 -> 150000 | O68: =O15*10^6/O64 -> 150000 | P68: =P15*10^6/P64 -> 150000 | Q68: =Q15*10^6/Q64 -> 150000
B70: Maximum capacity (Công suất tối đa ca/ngày)
E71: MRI | F71: =30*9*60/20 -> 810 | G71: =30*9*60/20 -> 810 | H71: =30*9*60/20 -> 810 | I71: =30*9*60/20 -> 810 | J71: =30*9*60/20 -> 810 | K71: =30*9*60/20 -> 810 | L71: =30*9*60/20 -> 810 | M71: =30*9*60/20 -> 810 | ... Q71: =30*9*60/20 -> 810 | R71: =SUMIFS($F71:$Q71,$F$7:$Q$7,"A") -> 9720 | S71: =SUMIFS($F71:$Q71,$F$7:$Q$7,"B") -> 0 | T71: =SUM(R71:S71) -> 9720
E72: Mammo X-Quang | F72: =30*9*60/15 -> 1080 | G72: =30*9*60/15 -> 1080 | H72: =30*9*60/15 -> 1080 | I72: =30*9*60/15 -> 1080 | J72: =30*9*60/15 -> 1080 | K72: =30*9*60/15 -> 1080 | L72: =30*9*60/15 -> 1080 | M72: =30*9*60/15 -> 1080 | ... Q72: =30*9*60/15 -> 1080 | R72: =SUMIFS($F72:$Q72,$F$7:$Q$7,"A") -> 12960 | S72: =SUMIFS($F72:$Q72,$F$7:$Q$7,"B") -> 0 | T72: =SUM(R72:S72) -> 12960
E73: CT | F73: =30*9*60/10 -> 1620 | G73: =30*9*60/10 -> 1620 | H73: =30*9*60/10 -> 1620 | I73: =30*9*60/10 -> 1620 | J73: =30*9*60/10 -> 1620 | K73: =30*9*60/10 -> 1620 | L73: =30*9*60/10 -> 1620 | M73: =30*9*60/10 -> 1620 | ... Q73: =30*9*60/10 -> 1620 | R73: =SUMIFS($F73:$Q73,$F$7:$Q$7,"A") -> 19440 | S73: =SUMIFS($F73:$Q73,$F$7:$Q$7,"B") -> 0 | T73: =SUM(R73:S73) -> 19440
E74: X-Quang | F74: =30*9*60/8 -> 2025 | G74: =30*9*60/8 -> 2025 | H74: =30*9*60/8 -> 2025 | I74: =30*9*60/8 -> 2025 | J74: =30*9*60/8 -> 2025 | K74: =30*9*60/8 -> 2025 | L74: =30*9*60/8 -> 2025 | M74: =30*9*60/8 -> 2025 | ... Q74: =30*9*60/8 -> 2025 | R74: =SUMIFS($F74:$Q74,$F$7:$Q$7,"A") -> 24300 | S74: =SUMIFS($F74:$Q74,$F$7:$Q$7,"B") -> 0 | T74: =SUM(R74:S74) -> 24300
B76: Utilization
E77: MRI | F77: =F62/F71 -> 0.051851852 | G77: =G62/G71 -> 0.082716049 | H77: =H62/H71 -> 0.13703704 | I77: =I62/I71 -> 0.11851852 | J77: =J62/J71 -> 0.15185185 | K77: =K62/K71 -> 0.16049383 | L77: =L62/L71 -> 0.17777778 | M77: =M62/M71 -> 0.22345679 | ... R77: =R62/R71 -> 0.17952675 | T77: =T62/T71 -> 0.17952675
E78: Mammo X-Quang
